Workbook

Sheet README
A1: LandLab-style Simulator - Systems & Flows (v2)
A3: What this is | B3: The full systems catalog for the clone: 168 systems, 797 input/output flows, and 62 resources, with quantities, periods, costs, and labor. A working balance model sits on top, so the Needs Checklist works like the game's results table.
A4: How to use it | B4: Set counts in the yellow "Count in design" column on Systems (a starter design matching the game screenshot is loaded). Then read Needs Checklist and Design Summary. Change climate on Assumptions.
A5: Color key | B5: Yellow fill = cells to edit. Blue text = typed inputs. Green text = formulas tied to Assumptions or another sheet. Black = calculated.
A7: Sheet: Needs Checklist | B7: The game's 11-row results table, driven by the design. Provided vs needed per week, % covered, overall score.
A8: Sheet: Design Summary | B8: Costs, setup labor, weekly labor, land used, days of water and battery storage, weekly cash flow.
A9: Sheet: Systems | B9: One row per system: categories, cost (purchase and DIY), setup and weekly labor, footprint, lifespan, thermal and rain-catchment parameters, and provenance.
A10: Sheet: Flows | B10: THE MODEL TABLE. One row per input or output: quantity, unit (looked up from Resources so every resource has one unit), and period. Weekly-equivalent and design totals are formulas.
A11: Sheet: Resources | B11: Every resource with unit, class (Flow / Capacity / Ambient / Service / Money), its checklist row and conversion factor, and a live weekly balance for the design.
A12: Sheet: Matrix | B12: System x resource grid: IN (blue), OUT (green), I/O (yellow).
A13: Sheet: Categories | B13: The dropdown categories with live counts against the 3-20 target (12-20 for Energy and Shelter).
A14: Sheet: Assumptions | B14: Climate (degree-days, sun, rain, wind) and the period conversion table.
A16: Periods | B16: Each flow has a period: Daily, Weekly, Monthly, Per season, Yearly, One-time, or Capacity. Everything is converted to a weekly average for balancing. One-time flows (setup materials) are excluded from weekly totals. Capacity flows (sq ft of shelter, gallons of tank) are stocks, not consumption, and compare one-to-one.
... A21: Changes from v1 | B21: Categories normalized to the 24 dropdown categories (Plant merged into Plants; Foul renamed Fowl; off-dropdown tags folded in, originals kept in "Original game tags"). New Household category for Human Being.
B22: Game systems with N/A inputs/outputs were filled in (Source says so). Woody Biomass self-loop replaced with a harvest. Sunlight now outputs Sunlight instead of Heat. Green feed merged into Green biomass. Pollen dropped (no consumer). GoSun Cooler outputs Food storage, IBC Tank outputs Water storage, Solar Hot Water Heater outputs Hot water.
B23: Raised Beds recalibrated: the game card shows 8 lbs/week and 100 gal/week from 24 sq ft; realistic intensive yields are ~18 lbs/season and ~15 gal/week.
B24: Labor: the game shows both a Labor input and a separate "weekly maintenance" estimate that disagree. Here weekly upkeep (Systems col K) is added to each system's Labor input automatically.
B25: New resources: Hot water, Greywater, Root crops, Grain, Meat, Milk, Fish, Nuts, Mushrooms, Hay, Gasoline, Propane, Wool, Rainfall, Wind, Stream flow, Water storage, Battery storage, Food storage, Land area, Fenced paddock, Nesting habitat, Pest control.
A27: Known limits | B27: Numbers are rounded rules of thumb (see Confidence column), not engineering sizing. Weekly averages hide seasonality: a garden's output and a stove's fuel use are spread across the year. The balance assumes every system runs at its rated flow; a real engine must curtail systems when inputs run short.
B28: Waste lumber has no on-site producer on purpose: it must be brought in. Several resources are end products (Wool, Wellbeing, storage capacities).

Sheet Needs Checklist
A1: Human Needs Checklist
A2: Humans in design | B2: =SUMIFS(Systems!$R$2:$R$179,Systems!$B$2:$B$179,"Human Being") -> 1
A3: Overall off-grid score | B3: =IFERROR(AVERAGEIF(D6:D16,">0",E6:E16),0) -> 0.48502892
A5: Human need | B5: Unit | C5: Provided by your design (per week) | D5: ="Total system needs for "&B2&" human"&IF(B2=1,"","s")&" (per week)" -> Total system needs for 1 human (per week) | E5: % of need covered | F5: Covered? | G5: Resources that feed this row
A6: Water | B6: gal | C6: =SUMIFS(Flows!$L$2:$L$1500,Flows!$K$2:$K$1500,$A6,Flows!$C$2:$C$1500,"Output") -> 1000 | D6: =SUMIFS(Flows!$L$2:$L$1500,Flows!$K$2:$K$1500,$A6,Flows!$C$2:$C$1500,"Input") -> 151 | E6: =IF(D6=0,0,MIN(1,C6/D6)) -> 1 | F6: =IF(D6=0,"n/a",IF(E6>=1,"✓","✗")) -> ✓ | G6: Water
A7: Drinking water | B7: gal | C7: =SUMIFS(Flows!$L$2:$L$1500,Flows!$K$2:$K$1500,$A7,Flows!$C$2:$C$1500,"Output") -> 0 | D7: =SUMIFS(Flows!$L$2:$L$1500,Flows!$K$2:$K$1500,$A7,Flows!$C$2:$C$1500,"Input") -> 5 | E7: =IF(D7=0,0,MIN(1,C7/D7)) -> 0 | F7: =IF(D7=0,"n/a",IF(E7>=1,"✓","✗")) -> ✗ | G7: Drinking water
A8: Food | B8: kcal | C8: =SUMIFS(Flows!$L$2:$L$1500,Flows!$K$2:$K$1500,$A8,Flows!$C$2:$C$1500,"Output") -> 4978.8462 | D8: =SUMIFS(Flows!$L$2:$L$1500,Flows!$K$2:$K$1500,$A8,Flows!$C$2:$C$1500,"Input") -> 16000 | E8: =IF(D8=0,0,MIN(1,C8/D8)) -> 0.31117788 | F8: =IF(D8=0,"n/a",IF(E8>=1,"✓","✗")) -> ✗ | G8: Food; Vegetables fruit fiber herbs; Root crops; Grain; Eggs; Honey; Meat; Milk; Fish; Nuts; Mushrooms
A9: Shelter | B9: sq ft | C9: =SUMIFS(Flows!$L$2:$L$1500,Flows!$K$2:$K$1500,$A9,Flows!$C$2:$C$1500,"Output") -> 210 | D9: =SUMIFS(Flows!$L$2:$L$1500,Flows!$K$2:$K$1500,$A9,Flows!$C$2:$C$1500,"Input") -> 200 | E9: =IF(D9=0,0,MIN(1,C9/D9)) -> 1 | F9: =IF(D9=0,"n/a",IF(E9>=1,"✓","✗")) -> ✓ | G9: Shelter
A10: Sanitation | B10: lbs | C10: =SUMIFS(Flows!$L$2:$L$1500,Flows!$K$2:$K$1500,$A10,Flows!$C$2:$C$1500,"Output") -> 35 | D10: =SUMIFS(Flows!$L$2:$L$1500,Flows!$K$2:$K$1500,$A10,Flows!$C$2:$C$1500,"Input") -> 17.5 | E10: =IF(D10=0,0,MIN(1,C10/D10)) -> 1 | F10: =IF(D10=0,"n/a",IF(E10>=1,"✓","✗")) -> ✓ | G10: Sanitation
A11: Electricity | B11: kWh | C11: =SUMIFS(Flows!$L$2:$L$1500,Flows!$K$2:$K$1500,$A11,Flows!$C$2:$C$1500,"Output") -> 14 | D11: =SUMIFS(Flows!$L$2:$L$1500,Flows!$K$2:$K$1500,$A11,Flows!$C$2:$C$1500,"Input") -> 24 | E11: =IF(D11=0,0,MIN(1,C11/D11)) -> 0.58333333 | F11: =IF(D11=0,"n/a",IF(E11>=1,"✓","✗")) -> ✗ | G11: Electricity
A12: Transportation | B12: miles | C12: =SUMIFS(Flows!$L$2:$L$1500,Flows!$K$2:$K$1500,$A12,Flows!$C$2:$C$1500,"Output") -> 50 | D12: =SUMIFS(Flows!$L$2:$L$1500,Flows!$K$2:$K$1500,$A12,Flows!$C$2:$C$1500,"Input") -> 150 | E12: =IF(D12=0,0,MIN(1,C12/D12)) -> 0.33333333 | F12: =IF(D12=0,"n/a",IF(E12>=1,"✓","✗")) -> ✗ | G12: Transportation
A13: Cooking fuel | B13: hours | C13: =SUMIFS(Flows!$L$2:$L$1500,Flows!$K$2:$K$1500,$A13,Flows!$C$2:$C$1500,"Output") -> 0 | D13: =SUMIFS(Flows!$L$2:$L$1500,Flows!$K$2:$K$1500,$A13,Flows!$C$2:$C$1500,"Input") -> 5 | E13: =IF(D13=0,0,MIN(1,C13/D13)) -> 0 | F13: =IF(D13=0,"n/a",IF(E13>=1,"✓","✗")) -> ✗ | G13: Cooking fuel
A14: Heated shelter | B14: BTU | C14: =SUMIFS(Flows!$L$2:$L$1500,Flows!$K$2:$K$1500,$A14,Flows!$C$2:$C$1500,"Output") -> 0 | D14: =SUMIFS(Flows!$L$2:$L$1500,Flows!$K$2:$K$1500,$A14,Flows!$C$2:$C$1500,"Input") -> 697846.15 | E14: =IF(D14=0,0,MIN(1,C14/D14)) -> 0 | F14: =IF(D14=0,"n/a",IF(E14>=1,"✓","✗")) -> ✗ | G14: Heat
A15: Cooled shelter | B15: BTU | C15: =SUMIFS(Flows!$L$2:$L$1500,Flows!$K$2:$K$1500,$A15,Flows!$C$2:$C$1500,"Output") -> 10000 | D15: =SUMIFS(Flows!$L$2:$L$1500,Flows!$K$2:$K$1500,$A15,Flows!$C$2:$C$1500,"Input") -> 93046.154 | E15: =IF(D15=0,0,MIN(1,C15/D15)) -> 0.10747354 | F15: =IF(D15=0,"n/a",IF(E15>=1,"✓","✗")) -> ✗ | G15: Cooling
A16: Est. Required Labor | B16: hours | C16: =SUMIFS(Flows!$L$2:$L$1500,Flows!$K$2:$K$1500,$A16,Flows!$C$2:$C$1500,"Output") -> 50 | D16: =SUMIFS(Flows!$L$2:$L$1500,Flows!$K$2:$K$1500,$A16,Flows!$C$2:$C$1500,"Input") -> 9.67 | E16: =IF(D16=0,0,MIN(1,C16/D16)) -> 1 | F16: =IF(D16=0,"n/a",IF(E16>=1,"✓","✗")) -> ✓ | G16: Labor
A18: How it is computed
A19: Provided = every Output flow of that resource family x count in design, converted to the row unit (e.g. lbs of vegetables x 150 kcal). Needed = every Input flow the same way, so animals, gardens, and shelters add to the need alongside people. % = provided / needed, capped at 100%. Overall score = average of rows that have any need.

Sheet Design Summary
A1: Design summary
A2: Everything here updates from the yellow "Count in design" column on Systems.
A4: Metric | B4: Value | C4: Unit | D4: How it is computed
A5: Humans | B5: ='Needs Checklist'!B2 -> 1 | C5: people | D5: Count of Human Being.
A6: Systems placed (excluding people and site) | B6: =SUM(Systems!$R$2:$R$179)-B5-SUMIFS(Systems!$R$2:$R$179,Systems!$C$2:$C$179,"Land",Systems!$L$2:$L$179,0) -> 10 | C6: systems | D6: Sum of counts, minus Human Being and zero-footprint Land systems (Sunlight, Rainfall, etc.).
A7: Overall off-grid score | B7: ='Needs Checklist'!B3 -> 0.48502892 | C7: % | D7: Average coverage across the checklist.
A8: Purchase cost (ready-made) | B8: =SUMPRODUCT(Systems!$G$2:$G$179,Systems!$R$2:$R$179) -> 73110 | C8: $ | D8: Sum of purchase cost x count.
A9: Cheapest build cost | B9: =SUMPRODUCT(Systems!$I$2:$I$179,Systems!$R$2:$R$179) -> 67765 | C9: $ | D9: DIY where offered, otherwise purchase.
A10: Setup labor | B10: =SUMPRODUCT(Systems!$J$2:$J$179,Systems!$R$2:$R$179) -> 123 | C10: hours | D10: One-time build hours.
A11: Labor available per week | B11: ='Needs Checklist'!C16 -> 50 | C11: hours/week | D11: Labor output of Human Being x count.
A12: Labor required per week | B12: ='Needs Checklist'!D16 -> 9.67 | C12: hours/week | D12: All Labor inputs, including upkeep and jobs.
A13: Land available | B13: =SUMIFS(Flows!$J$2:$J$1500,Flows!$D$2:$D$1500,"Land area",Flows!$C$2:$C$1500,"Output") -> 43560 | C13: sq ft | D13: From Land Title or Mortgage.
A14: Land used by footprints | B14: =SUMPRODUCT(Systems!$L$2:$L$179,Systems!$R$2:$R$179) -> 1427 | C14: sq ft | D14: Footprint x count. Roof-mounted systems overlap shelters in reality.
A15: Land used (% of available) | B15: =IF(B13=0,0,B14/B13) -> 0.032759412 | C15: % | D15: Over 100% means the design does not fit.
A16: Water storage | B16: =SUMIFS(Flows!$J$2:$J$1500,Flows!$D$2:$D$1500,"Water storage",Flows!$C$2:$C$1500,"Output") -> 0 | C16: gal | D16: Tanks, cisterns, ponds.
A17: Days of water in storage | B17: =IFERROR(B16/(('Needs Checklist'!D6+'Needs Checklist'!D7)/7),0) -> 0 | C17: days | D17: Storage divided by daily water + drinking-water need.
A18: Battery storage | B18: =SUMIFS(Flows!$J$2:$J$1500,Flows!$D$2:$D$1500,"Battery storage",Flows!$C$2:$C$1500,"Output") -> 0 | C18: kWh | D18: Usable battery capacity.
A19: Days of electricity in batteries | B19: =IFERROR(B18/('Needs Checklist'!D11/7),0) -> 0 | C19: days | D19: Battery kWh divided by daily electricity need.
A20: Food storage | B20: =SUMIFS(Flows!$J$2:$J$1500,Flows!$D$2:$D$1500,"Food storage",Flows!$C$2:$C$1500,"Output") -> 0 | C20: cu ft | D20: Cellar, freezer, canned and dried goods.
A21: Capital in per week | B21: =SUMIFS(Flows!$J$2:$J$1500,Flows!$D$2:$D$1500,"Capital",Flows!$C$2:$C$1500,"Output") -> 0 | C21: $/week | D21: Income from Average Job.
A22: Capital out per week | B22: =SUMIFS(Flows!$J$2:$J$1500,Flows!$D$2:$D$1500,"Capital",Flows!$C$2:$C$1500,"Input") -> 0 | C22: $/week | D22: Running costs of conventional systems.
A23: Net capital per week | B23: =B21-B22 -> 0 | C23: $/week | D23: Negative means the design burns savings.
A24: Wellbeing points per week | B24: =SUMIFS(Flows!$J$2:$J$1500,Flows!$D$2:$D$1500,"Wellbeing",Flows!$C$2:$C$1500,"Output") -> 10 | C24: points | D24: Game-style score.
A25: Resources in deficit | B25: =COUNTIF(Resources!$L$2:$L$64,"Deficit") -> 18 | C25: resources | D25: See Resources, column L.

Sheet Systems
A1: System ID | B1: System | C1: Categories | D1: Original game tags | E1: Source | F1: Description | G1: Purchase cost ($) | H1: DIY cost ($) | I1: Cheapest build ($) | J1: Setup labor (hrs) | K1: Weekly upkeep (hrs) | L1: Footprint (sq ft) | M1: Lifespan (yrs) | N1: Conditioned area (sq ft) | O1: Heat-loss factor (BTU/hr·°F per sq ft) | P1: Catchment area (sq ft) | Q1: Capture efficiency | R1: Count in design | S1: # Inputs | T1: # Outputs | U1: Game-listed inputs | V1: Game-listed outputs | W1: Confidence | X1: Notes
A2: S001 | B2: 2kwh Lead Acid Battery | C2: Energy; Storage | D2: Battery; Energy; Storage | E2: Game (captured) | F2: Deep-cycle lead-acid bank; about 1 kWh usable at 50% depth of discharge. | G2: 450 | H2: 300 | I2: =IF(H2="",G2,MIN(G2,H2)) -> 300 | J2: 2 | K2: 0.1 | L2: 4 | M2: 5 | R2: 0 | S2: =COUNTIFS(Flows!$B$2:$B$1500,$B2,Flows!$C$2:$C$1500,"Input") -> 2 | T2: =COUNTIFS(Flows!$B$2:$B$1500,$B2,Flows!$C$2:$C$1500,"Output") -> 2 | U2: Electricity | V2: Electricity | W2: medium | X2: Stores and returns power with ~80% round-trip efficiency; a net user of electricity.
A3: S002 | B3: 500W Photovoltaic Panels | C3: Energy; Solar | D3: Energy; Solar | E3: Game (captured) | F3: Ground- or roof-mounted 500 W panel set. | G3: 500 | H3: 300 | I3: =IF(H3="",G3,MIN(G3,H3)) -> 300 | J3: 3 | K3: 0.05 | L3: 30 | M3: 25 | R3: 1 | S3: =COUNTIFS(Flows!$B$2:$B$1500,$B3,Flows!$C$2:$C$1500,"Input") -> 2 | T3: =COUNTIFS(Flows!$B$2:$B$1500,$B3,Flows!$C$2:$C$1500,"Output") -> 1 | U3: Sunlight | V3: Electricity | W3: medium
A4: S003 | B4: All Power Labs CHP | C4: Energy; Biomass | D4: Energy; Biomass | E4: Game (captured) | F4: Wood gasifier combined heat and power unit (PP20-class), run ~2 hrs/day. | G4: 35000 | I4: =IF(H4="",G4,MIN(G4,H4)) -> 35000 | J4: 40 | K4: 4 | L4: 100 | M4: 15 | R4: 0 | S4: =COUNTIFS(Flows!$B$2:$B$1500,$B4,Flows!$C$2:$C$1500,"Input") -> 2 | T4: =COUNTIFS(Flows!$B$2:$B$1500,$B4,Flows!$C$2:$C$1500,"Output") -> 3 | U4: Wood pellets | V4: Heat; Biochar; Electricity | W4: low
A5: S004 | B5: Biochar | C5: Biomass; Purification | D5: Energy; Biomass | E5: Game (captured) | F5: Open cone (Kon-Tiki style) kiln that turns brush into biochar. | G5: 400 | H5: 60 | I5: =IF(H5="",G5,MIN(G5,H5)) -> 60 | J5: 2 | K5: 2 | L5: 20 | M5: 10 | R5: 0 | S5: =COUNTIFS(Flows!$B$2:$B$1500,$B5,Flows!$C$2:$C$1500,"Input") -> 3 | T5: =COUNTIFS(Flows!$B$2:$B$1500,$B5,Flows!$C$2:$C$1500,"Output") -> 1 | U5: Woody biomass | V5: Biochar | W5: low | X5: Added quench water. ~15% char yield by mass.
A6: S005 | B6: Biochar Double Barrel Retort | C6: Biomass; Compost | D6: Energy; Compost | E6: Game (captured) | F6: Retort that bakes chips in an inner barrel with an outer fire. | G6: 300 | H6: 80 | I6: =IF(H6="",G6,MIN(G6,H6)) -> 80 | J6: 6 | K6: 2 | L6: 15 | M6: 5 | R6: 0 | S6: =COUNTIFS(Flows!$B$2:$B$1500,$B6,Flows!$C$2:$C$1500,"Input") -> 4 | T6: =COUNTIFS(Flows!$B$2:$B$1500,$B6,Flows!$C$2:$C$1500,"Output") -> 2 | U6: Wood chips; Woody biomass; Waste lumber | V6: Heat; Biochar | W6: low | X6: Heat only counts if the retort sits beside a shelter; entered low.
A7: S006 | B7: A-Frame House | C7: Shelter | D7: Shelter | E7: Game (captured) | F7: Kit-built A-frame, ~800 sq ft conditioned. | G7: 120000 | H7: 55000 | I7: =IF(H7="",G7,MIN(G7,H7)) -> 55000 | J7: 1500 | K7: 1 | L7: 900 | M7: 60 | N7: 800 | O7: 0.3 | R7: 0 | S7: =COUNTIFS(Flows!$B$2:$B$1500,$B7,Flows!$C$2:$C$1500,"Input") -> 4 | T7: =COUNTIFS(Flows!$B$2:$B$1500,$B7,Flows!$C$2:$C$1500,"Output") -> 2 | U7: Capital; Capital | V7: Shelter | W7: medium | X7: Capital = taxes, insurance, upkeep. Duplicate Capital pill merged.
A8: S007 | B8: Average Suburban Home | C8: Shelter; Conventional | D8: Shelter; Conventional | E8: Game (captured) | F8: Median US detached home on city water and sewer. | G8: 420000 | I8: =IF(H8="",G8,MIN(G8,H8)) -> 420000 | J8: 0 | K8: 2 | L8: 2000 | M8: 70 | N8: 2000 | O8: 0.25 | R8: 0 | S8: =COUNTIFS(Flows!$B$2:$B$1500,$B8,Flows!$C$2:$C$1500,"Input") -> 4 | T8: =COUNTIFS(Flows!$B$2:$B$1500,$B8,Flows!$C$2:$C$1500,"Output") -> 6 | U8: Capital; Capital | V8: Sanitation; Drinking water; Water; Roofing area; Shelter | W8: medium | X8: Includes municipal water/sewer and a gas water heater.
A9: S008 | B9: Bell Tent | C9: Shelter; Canvas | D9: Shelter; Canvas | E9: Game (captured) | F9: 5 m canvas bell tent (~210 sq ft). | G9: 800 | H9: 300 | I9: =IF(H9="",G9,MIN(G9,H9)) -> 300 | J9: 3 | K9: 0.25 | L9: 210 | M9: 5 | N9: 210 | O9: 1.2 | R9: 1 | S9: =COUNTIFS(Flows!$B$2:$B$1500,$B9,Flows!$C$2:$C$1500,"Input") -> 3 | T9: =COUNTIFS(Flows!$B$2:$B$1500,$B9,Flows!$C$2:$C$1500,"Output") -> 1 | U9: Labor | V9: Shelter | W9: medium
A10: S009 | B10: Camp 365 Off-Grid Camper | C10: Shelter; Transportation | D10: Shelter; Transportation | E10: Game (captured) | F10: Towable off-grid camper; needs a tow vehicle to move. | G10: 65000 | I10: =IF(H10="",G10,MIN(G10,H10)) -> 65000 | J10: 2 | K10: 0.5 | L10: 150 | M10: 20 | N10: 150 | O10: 0.6 | R10: 0 | S10: =COUNTIFS(Flows!$B$2:$B$1500,$B10,Flows!$C$2:$C$1500,"Input") -> 4 | T10: =COUNTIFS(Flows!$B$2:$B$1500,$B10,Flows!$C$2:$C$1500,"Output") -> 2 | U10: Capital; Labor | V10: Shelter | W10: low
A11: S010 | B11: Camper Van | C11: Transportation; Shelter | D11: Transportation; Shelter | E11: Game (captured) | F11: Converted cargo van; home and vehicle in one. | G11: 80000 | H11: 25000 | I11: =IF(H11="",G11,MIN(G11,H11)) -> 25000 | J11: 300 | K11: 1 | L11: 80 | M11: 15 | N11: 60 | O11: 0.8 | R11: 0 | S11: =COUNTIFS(Flows!$B$2:$B$1500,$B11,Flows!$C$2:$C$1500,"Input") -> 5 | T11: =COUNTIFS(Flows!$B$2:$B$1500,$B11,Flows!$C$2:$C$1500,"Output") -> 2 | U11: Capital; Capital | V11: Shelter; Transportation | W11: low
A12: S011 | B12: Green Biomass | C12: Biomass | D12: Biomass; Nitrogen | E12: Game (captured) | F12: Cut-and-carry greens patch (comfrey, alfalfa, weeds), ~400 sq ft. | G12: 50 | H12: 20 | I12: =IF(H12="",G12,MIN(G12,H12)) -> 20 | J12: 4 | K12: 1.5 | L12: 400 | M12: 10 | R12: 0 | S12: =COUNTIFS(Flows!$B$2:$B$1500,$B12,Flows!$C$2:$C$1500,"Input") -> 3 | T12: =COUNTIFS(Flows!$B$2:$B$1500,$B12,Flows!$C$2:$C$1500,"Output") -> 1 | U12: Labor | V12: Green biomass | W12: low
A13: S012 | B13: Woody Biomass | C13: Biomass | D13: Biomass | E13: Game (captured) | F13: Brush and deadfall harvest with a splitting station. | G13: 150 | H13: 50 | I13: =IF(H13="",G13,MIN(G13,H13)) -> 50 | J13: 4 | K13: 3 | L13: 50 | M13: 20 | R13: 0 | S13: =COUNTIFS(Flows!$B$2:$B$1500,$B13,Flows!$C$2:$C$1500,"Input") -> 1 | T13: =COUNTIFS(Flows!$B$2:$B$1500,$B13,Flows!$C$2:$C$1500,"Output") -> 1 | U13: Woody biomass | V13: Woody biomass | W13: low | X13: Game loops Woody biomass to itself; redefined as a harvest from existing woods (labor in, wood out).
A14: S013 | B14: Firepit | C14: Cooking; Heating | D14: Energy; Biomass | E14: Game (captured) | F14: Outdoor stone firepit. | G14: 300 | H14: 50 | I14: =IF(H14="",G14,MIN(G14,H14)) -> 50 | J14: 2 | K14: 0.5 | L14: 30 | M14: 15 | R14: 0 | S14: =COUNTIFS(Flows!$B$2:$B$1500,$B14,Flows!$C$2:$C$1500,"Input") -> 2 | T14: =COUNTIFS(Flows!$B$2:$B$1500,$B14,Flows!$C$2:$C$1500,"Output") -> 3 | U14: Woody biomass | V14: Cooking fuel; Heat | W14: low | X14: Outdoor heat entered low; it does not warm a shelter.
A15: S014 | B15: Livestock Guardian Dog | C15: Livestock | D15: Pet | E15: Game (captured) | F15: Working guardian dog for poultry and goats. | G15: 1500 | I15: =IF(H15="",G15,MIN(G15,H15)) -> 1500 | J15: 20 | K15: 3.5 | L15: 0 | M15: 10 | R15: 0 | S15: =COUNTIFS(Flows!$B$2:$B$1500,$B15,Flows!$C$2:$C$1500,"Input") -> 3 | T15: =COUNTIFS(Flows!$B$2:$B$1500,$B15,Flows!$C$2:$C$1500,"Output") -> 3 | U15: Water; Food | V15: Organic waste; Wellbeing | W15: low
A16: S015 | B16: Baby Chicks | C16: Livestock; Fowl | D16: Livestock; Foul | E16: Game (captured) | F16: Batch of 12 chicks for their first 8 weeks. | G16: 100 | I16: =IF(H16="",G16,MIN(G16,H16)) -> 100 | J16: 3 | K16: 1 | L16: 20 | M16: 0.15 | R16: 0 | S16: =COUNTIFS(Flows!$B$2:$B$1500,$B16,Flows!$C$2:$C$1500,"Input") -> 3 | T16: =COUNTIFS(Flows!$B$2:$B$1500,$B16,Flows!$C$2:$C$1500,"Output") -> 1 | U16: Water; Chicken feed | V16: Manure | W16: low
A17: S016 | B17: Beehive + Bee Colony | C17: Livestock; Insects | D17: Livestock; Insects | E17: Game (captured) | F17: Langstroth hive with one colony. | G17: 500 | H17: 200 | I17: =IF(H17="",G17,MIN(G17,H17)) -> 200 | J17: 6 | K17: 0.5 | L17: 10 | M17: 10 | R17: 0 | S17: =COUNTIFS(Flows!$B$2:$B$1500,$B17,Flows!$C$2:$C$1500,"Input") -> 3 | T17: =COUNTIFS(Flows!$B$2:$B$1500,$B17,Flows!$C$2:$C$1500,"Output") -> 2 | U17: Pollinator flowers; Water | V17: Honey; Pollination; Pollen | W17: low | X17: Pollen output dropped (no consumer); honey ~40 lbs/yr harvestable.
A18: S017 | B18: Black Soldier Fly Protopod (BSF) | C18: Insects; Compost | D18: Livestock; Insects | E18: Game (captured) | F18: Self-harvesting BSF larva bin. | G18: 180 | H18: 60 | I18: =IF(H18="",G18,MIN(G18,H18)) -> 60 | J18: 2 | K18: 0.5 | L18: 6 | M18: 5 | R18: 0 | S18: =COUNTIFS(Flows!$B$2:$B$1500,$B18,Flows!$C$2:$C$1500,"Input") -> 3 | T18: =COUNTIFS(Flows!$B$2:$B$1500,$B18,Flows!$C$2:$C$1500,"Output") -> 2 | U18: Coffee grounds; Food waste | V18: Manure; Grubs | W18: low
A19: S018 | B19: Chicken | C19: Livestock; Fowl | D19: Livestock; Foul | E19: Game (captured) | F19: A single laying hen. | G19: 25 | I19: =IF(H19="",G19,MIN(G19,H19)) -> 25 | J19: 0.5 | K19: 0.15 | L19: 10 | M19: 5 | R19: 0 | S19: =COUNTIFS(Flows!$B$2:$B$1500,$B19,Flows!$C$2:$C$1500,"Input") -> 6 | T19: =COUNTIFS(Flows!$B$2:$B$1500,$B19,Flows!$C$2:$C$1500,"Output") -> 2 | U19: Green biomass; Grubs; Food waste; Water | V19: Manure; Eggs | W19: medium | X19: Added bagged feed; free-range forage alone rarely sustains laying.
A20: S019 | B20: Aptera Electric Vehicle (Solar Charge) | C20: Transportation; Solar | D20: Transportation; Solar | E20: Game (captured) | F20: Three-wheel solar EV with grid top-up. | G20: 33000 | I20: =IF(H20="",G20,MIN(G20,H20)) -> 33000 | J20: 1 | K20: 0.1 | L20: 100 | M20: 15 | R20: 0 | S20: =COUNTIFS(Flows!$B$2:$B$1500,$B20,Flows!$C$2:$C$1500,"Input") -> 4 | T20: =COUNTIFS(Flows!$B$2:$B$1500,$B20,Flows!$C$2:$C$1500,"Output") -> 1 | U20: Sunlight; Capital | V20: Transportation | W20: low
A21: S020 | B21: Average American Vehicle | C21: Transportation; Conventional | D21: Transportation; Conventional | E21: Game (captured) | F21: Gasoline sedan, ~13,000 miles/yr. | G21: 48000 | I21: =IF(H21="",G21,MIN(G21,H21)) -> 48000 | J21: 1 | K21: 0.2 | L21: 150 | M21: 12 | R21: 0 | S21: =COUNTIFS(Flows!$B$2:$B$1500,$B21,Flows!$C$2:$C$1500,"Input") -> 3 | T21: =COUNTIFS(Flows!$B$2:$B$1500,$B21,Flows!$C$2:$C$1500,"Output") -> 1 | U21: Capital | V21: Transportation | W21: medium | X21: Capital = insurance, repairs, depreciation (fuel separate).
A22: S021 | B22: Bike | C22: Transportation | D22: Transportation | E22: Game (captured) | F22: Commuter bicycle. | G22: 600 | H22: 150 | I22: =IF(H22="",G22,MIN(G22,H22)) -> 150 | J22: 1 | K22: 0.2 | L22: 10 | M22: 10 | R22: 0 | S22: =COUNTIFS(Flows!$B$2:$B$1500,$B22,Flows!$C$2:$C$1500,"Input") -> 3 | T22: =COUNTIFS(Flows!$B$2:$B$1500,$B22,Flows!$C$2:$C$1500,"Output") -> 2 | U22: Labor | V22: Wellbeing; Transportation | W22: medium | X22: Riding time counts as labor; ~40 kcal/mile of rider food.
A23: S022 | B23: Drinking Water Filter | C23: Water-System; Purification | D23: Water-System; Purification | E23: Game (captured) | F23: Gravity ceramic/carbon filter (Berkey-type). | G23: 350 | I23: =IF(H23="",G23,MIN(G23,H23)) -> 350 | J23: 0.5 | K23: 0.25 | L23: 2 | M23: 10 | R23: 0 | S23: =COUNTIFS(Flows!$B$2:$B$1500,$B23,Flows!$C$2:$C$1500,"Input") -> 2 | T23: =COUNTIFS(Flows!$B$2:$B$1500,$B23,Flows!$C$2:$C$1500,"Output") -> 1 | U23: Labor; Water | V23: Drinking water | W23: medium
A24: S023 | B24: GoSun Water Filter | C24: Water-System; Purification | D24: Water-System; Purification | E24: Game (captured) | F24: Solar pasteurizing water flask. | G24: 150 | I24: =IF(H24="",G24,MIN(G24,H24)) -> 150 | J24: 0.25 | K24: 0.1 | L24: 2 | M24: 5 | R24: 0 | S24: =COUNTIFS(Flows!$B$2:$B$1500,$B24,Flows!$C$2:$C$1500,"Input") -> 3 | T24: =COUNTIFS(Flows!$B$2:$B$1500,$B24,Flows!$C$2:$C$1500,"Output") -> 1 | U24: Water | V24: Drinking water | W24: low
A25: S024 | B25: Rainwater Collection System + Cistern (550 Gallons) | C25: Water-System; Storage | D25: Water-System; Storage | E25: Game (captured) | F25: Gutters, first-flush diverter, and a 550-gal cistern. | G25: 1200 | H25: 500 | I25: =IF(H25="",G25,MIN(G25,H25)) -> 500 | J25: 12 | K25: 0.25 | L25: 20 | M25: 20 | P25: 1000 | Q25: 0.8 | R25: 0 | S25: =COUNTIFS(Flows!$B$2:$B$1500,$B25,Flows!$C$2:$C$1500,"Input") -> 3 | T25: =COUNTIFS(Flows!$B$2:$B$1500,$B25,Flows!$C$2:$C$1500,"Output") -> 2 | U25: Roofing area | V25: Water | W25: medium | X25: Water out = catchment x rainfall x 0.623 gal/sq ft-in x efficiency. Catchment must be covered by Roofing area.
A26: S025 | B26: Solar Hot Water Heater | C26: Solar; Water-System; Heating | D26: Solar; Water-System; Heating | E26: Game (captured) | F26: Flat-plate solar collector with storage tank. | G26: 4500 | H26: 1500 | I26: =IF(H26="",G26,MIN(G26,H26)) -> 1500 | J26: 16 | K26: 0.1 | L26: 40 | M26: 20 | R26: 0 | S26: =COUNTIFS(Flows!$B$2:$B$1500,$B26,Flows!$C$2:$C$1500,"Input") -> 3 | T26: =COUNTIFS(Flows!$B$2:$B$1500,$B26,Flows!$C$2:$C$1500,"Output") -> 1 | U26: Water | V26: Water | W26: low | X26: Output changed from Water to Hot water.
A27: S026 | B27: WaterDrop Water Filter | C27: Purification; Water-System | D27: Purification; Water-System | E27: Game (captured) | F27: Under-sink tankless reverse-osmosis filter. | G27: 300 | I27: =IF(H27="",G27,MIN(G27,H27)) -> 300 | J27: 1 | K27: 0.1 | L27: 2 | M27: 5 | R27: 0 | S27: =COUNTIFS(Flows!$B$2:$B$1500,$B27,Flows!$C$2:$C$1500,"Input") -> 3 | T27: =COUNTIFS(Flows!$B$2:$B$1500,$B27,Flows!$C$2:$C$1500,"Output") -> 2 | U27: Labor; Water | V27: Drinking water | W27: low | X27: RO rejects about half its input.
A28: S027 | B28: Average Job | C28: Conventional | D28: Conventional | E28: Game (captured) | F28: Full-time job at US median weekly earnings. | G28: 0 | I28: =IF(H28="",G28,MIN(G28,H28)) -> 0 | J28: 0 | K28: 0 | L28: 0 | M28: 40 | R28: 0 | S28: =COUNTIFS(Flows!$B$2:$B$1500,$B28,Flows!$C$2:$C$1500,"Input") -> 2 | T28: =COUNTIFS(Flows!$B$2:$B$1500,$B28,Flows!$C$2:$C$1500,"Output") -> 1 | U28: Labor | V28: Capital | W28: medium | X28: Commute of ~30 miles/day added.
A29: S028 | B29: Big Box Grocery Store | C29: Conventional; Food System | D29: Conventional; Food System | E29: Game (captured) | F29: Groceries for one person for a week. | G29: 0 | I29: =IF(H29="",G29,MIN(G29,H29)) -> 0 | J29: 0 | K29: 0 | L29: 0 | M29: 1 | R29: 0 | S29: =COUNTIFS(Flows!$B$2:$B$1500,$B29,Flows!$C$2:$C$1500,"Input") -> 2 | T29: =COUNTIFS(Flows!$B$2:$B$1500,$B29,Flows!$C$2:$C$1500,"Output") -> 2 | U29: Capital | V29: Food | W29: medium
A30: S029 | B30: Central Power Plant (Coal / NatGas / Nuclear) | C30: Energy; Conventional | D30: Energy; Conventional | E30: Game (captured) | F30: Utility electric and gas service for one home. | G30: 2500 | I30: =IF(H30="",G30,MIN(G30,H30)) -> 2500 | J30: 4 | K30: 0 | L30: 0 | M30: 50 | R30: 0 | S30: =COUNTIFS(Flows!$B$2:$B$1500,$B30,Flows!$C$2:$C$1500,"Input") -> 1 | T30: =COUNTIFS(Flows!$B$2:$B$1500,$B30,Flows!$C$2:$C$1500,"Output") -> 4 | U30: Capital | V30: Heat; Cooking fuel; Cooling; Electricity | W30: medium | X30: Purchase cost = connection fee.
A31: S030 | B31: Factory Farmed Food (Family of Four) | C31: Conventional; Food System | D31: Conventional; Food System | E31: Game (captured; empty I/O filled in) | F31: Industrial food supply for four people. | G31: 0 | I31: =IF(H31="",G31,MIN(G31,H31)) -> 0 | J31: 0 | K31: 0 | L31: 0 | M31: 1 | R31: 0 | S31: =COUNTIFS(Flows!$B$2:$B$1500,$B31,Flows!$C$2:$C$1500,"Input") -> 2 | T31: =COUNTIFS(Flows!$B$2:$B$1500,$B31,Flows!$C$2:$C$1500,"Output") -> 2 | U31: N/A | V31: N/A | W31: low
A32: S031 | B32: Food Waste | C32: Compost | D32: Food-Waste | E32: Game (captured) | F32: Weekly scrap pickup from neighbors and a cafe. | G32: 0 | I32: =IF(H32="",G32,MIN(G32,H32)) -> 0 | J32: 0 | K32: 0.5 | L32: 0 | M32: 1 | R32: 0 | S32: =COUNTIFS(Flows!$B$2:$B$1500,$B32,Flows!$C$2:$C$1500,"Input") -> 2 | T32: =COUNTIFS(Flows!$B$2:$B$1500,$B32,Flows!$C$2:$C$1500,"Output") -> 2 | U32: Transportation | V32: Food waste | W32: low
A33: S032 | B33: IBC Tank (food grade) | C33: Water-System; Storage | D33: Water-System; Storage | E33: Game (captured) | F33: 275-gal food-grade tote. | G33: 150 | I33: =IF(H33="",G33,MIN(G33,H33)) -> 150 | J33: 1 | K33: 0.05 | L33: 16 | M33: 10 | R33: 0 | S33: =COUNTIFS(Flows!$B$2:$B$1500,$B33,Flows!$C$2:$C$1500,"Input") -> 1 | T33: =COUNTIFS(Flows!$B$2:$B$1500,$B33,Flows!$C$2:$C$1500,"Output") -> 1 | U33: N/A | V33: Storage space | W33: medium | X33: Output changed to Water storage.
A34: S033 | B34: Permaculture Food Forest (1/4 acre) | C34: Food System; Plants | D34: Food System; Plants | E34: Game (captured) | F34: Layered fruit, nut, and perennial planting at maturity. | G34: 8000 | H34: 2500 | I34: =IF(H34="",G34,MIN(G34,H34)) -> 2500 | J34: 120 | K34: 3 | L34: 10890 | M34: 40 | R34: 0 | S34: =COUNTIFS(Flows!$B$2:$B$1500,$B34,Flows!$C$2:$C$1500,"Input") -> 5 | T34: =COUNTIFS(Flows!$B$2:$B$1500,$B34,Flows!$C$2:$C$1500,"Output") -> 4 | U34: Seedlings; Water; Compost; Pollination; Labor | V34: Wellbeing; Pollinator flowers; Vegetables fruit fiber herbs | W34: low | X34: Yields are for a mature forest (year 7+).
A35: S034 | B35: Composting Outhouse | C35: Sanitation | D35: Sanitation | E35: Game (captured) | F35: Two-chamber composting outhouse. | G35: 1500 | H35: 500 | I35: =IF(H35="",G35,MIN(G35,H35)) -> 500 | J35: 30 | K35: 0.5 | L35: 30 | M35: 20 | R35: 1 | S35: =COUNTIFS(Flows!$B$2:$B$1500,$B35,Flows!$C$2:$C$1500,"Input") -> 3 | T35: =COUNTIFS(Flows!$B$2:$B$1500,$B35,Flows!$C$2:$C$1500,"Output") -> 2 | U35: Organic waste | V35: Sanitation | W35: medium | X35: Sized for two people.
A36: S035 | B36: Compost Piles | C36: Compost; Garden; Sanitation | D36: Compost; Garden; Sanitation | E36: Game (captured) | F36: Three-bin hot compost system. | G36: 100 | H36: 0 | I36: =IF(H36="",G36,MIN(G36,H36)) -> 0 | J36: 4 | K36: 1 | L36: 50 | M36: 10 | R36: 1 | S36: =COUNTIFS(Flows!$B$2:$B$1500,$B36,Flows!$C$2:$C$1500,"Input") -> 5 | T36: =COUNTIFS(Flows!$B$2:$B$1500,$B36,Flows!$C$2:$C$1500,"Output") -> 1 | U36: Water; Green biomass; Carbon; Biochar | V36: Compost | W36: medium
A37: S036 | B37: Compost Roller | C37: Compost; Tools | D37: Compost; Tools | E37: Game (captured) | F37: Tumbling compost drum. | G37: 250 | H37: 80 | I37: =IF(H37="",G37,MIN(G37,H37)) -> 80 | J37: 1 | K37: 0.5 | L37: 10 | M37: 8 | R37: 0 | S37: =COUNTIFS(Flows!$B$2:$B$1500,$B37,Flows!$C$2:$C$1500,"Input") -> 4 | T37: =COUNTIFS(Flows!$B$2:$B$1500,$B37,Flows!$C$2:$C$1500,"Output") -> 1 | U37: Labor; Water; Green biomass; Carbon | V37: Compost | W37: low
A38: S037 | B38: Compost Toilet | C38: Sanitation; Compost | D38: Sanitation; Toilet; Compost | E38: Game (captured) | F38: Self-contained urine-diverting toilet (one person). | G38: 1000 | H38: 300 | I38: =IF(H38="",G38,MIN(G38,H38)) -> 300 | J38: 4 | K38: 0.5 | L38: 10 | M38: 15 | R38: 0 | S38: =COUNTIFS(Flows!$B$2:$B$1500,$B38,Flows!$C$2:$C$1500,"Input") -> 4 | T38: =COUNTIFS(Flows!$B$2:$B$1500,$B38,Flows!$C$2:$C$1500,"Output") -> 3 | U38: Organic waste | V38: Sanitation; Liquid fertilizer; Compost | W38: medium
A39: S038 | B39: Throne Composting Toilet | C39: Sanitation | D39: Sanitation; Toilet | E39: Game (captured) | F39: Premium composting toilet (one person). | G39: 1400 | I39: =IF(H39="",G39,MIN(G39,H39)) -> 1400 | J39: 4 | K39: 0.5 | L39: 10 | M39: 15 | R39: 0 | S39: =COUNTIFS(Flows!$B$2:$B$1500,$B39,Flows!$C$2:$C$1500,"Input") -> 4 | T39: =COUNTIFS(Flows!$B$2:$B$1500,$B39,Flows!$C$2:$C$1500,"Output") -> 2 | U39: Organic waste | V39: Sanitation | W39: low
A40: S039 | B40: GoSun Solar Oven | C40: Cooking; Solar | D40: Cooking; Solar | E40: Game (captured) | F40: Evacuated-tube solar cooker. | G40: 350 | H40: 100 | I40: =IF(H40="",G40,MIN(G40,H40)) -> 100 | J40: 0.25 | K40: 0.1 | L40: 4 | M40: 8 | R40: 0 | S40: =COUNTIFS(Flows!$B$2:$B$1500,$B40,Flows!$C$2:$C$1500,"Input") -> 2 | T40: =COUNTIFS(Flows!$B$2:$B$1500,$B40,Flows!$C$2:$C$1500,"Output") -> 1 | U40: Sunlight | V40: Cooking fuel | W40: medium
A41: S040 | B41: Solar Cabin | C41: Shelter; Solar | D41: Shelter | E41: Game (captured) | F41: Well-insulated 400 sq ft cabin with a 1 kW array and passive solar glazing. | G41: 60000 | H41: 30000 | I41: =IF(H41="",G41,MIN(G41,H41)) -> 30000 | J41: 800 | K41: 0.5 | L41: 450 | M41: 40 | N41: 400 | O41: 0.2 | R41: 0 | S41: =COUNTIFS(Flows!$B$2:$B$1500,$B41,Flows!$C$2:$C$1500,"Input") -> 4 | T41: =COUNTIFS(Flows!$B$2:$B$1500,$B41,Flows!$C$2:$C$1500,"Output") -> 4 | U41: Sunlight; Labor | V41: Heat; Electricity; Roofing area; Shelter | W41: low
A42: S041 | B42: Solar Electric Fencing System | C42: Livestock; Solar | D42: Livestock; Energy | E42: Game (captured; empty I/O filled in) | F42: Solar energizer with ~1 acre of polywire. | G42: 450 | H42: 250 | I42: =IF(H42="",G42,MIN(G42,H42)) -> 250 | J42: 8 | K42: 0.5 | L42: 0 | M42: 10 | R42: 0 | S42: =COUNTIFS(Flows!$B$2:$B$1500,$B42,Flows!$C$2:$C$1500,"Input") -> 2 | T42: =COUNTIFS(Flows!$B$2:$B$1500,$B42,Flows!$C$2:$C$1500,"Output") -> 2 | U42: N/A | V42: N/A | W42: low | X42: Gates goats, sheep, and horses via Fenced paddock.
A43: S042 | B43: Solar Golf Cart | C43: Solar; Transportation | D43: Solar; Transportation | E43: Game (captured) | F43: Electric cart with roof panel. | G43: 9000 | I43: =IF(H43="",G43,MIN(G43,H43)) -> 9000 | J43: 2 | K43: 0.2 | L43: 40 | M43: 12 | R43: 0 | S43: =COUNTIFS(Flows!$B$2:$B$1500,$B43,Flows!$C$2:$C$1500,"Input") -> 3 | T43: =COUNTIFS(Flows!$B$2:$B$1500,$B43,Flows!$C$2:$C$1500,"Output") -> 1 | U43: Sunlight; Labor | V43: Transportation | W43: low
A44: S043 | B44: Butterfly Pea Flower | C44: Plants | D44: Plants | E44: Game (captured; empty I/O filled in) | F44: Nitrogen-fixing flowering vine (tea flowers). | G44: 15 | H44: 5 | I44: =IF(H44="",G44,MIN(G44,H44)) -> 5 | J44: 0.5 | K44: 0.1 | L44: 10 | M44: 2 | R44: 0 | S44: =COUNTIFS(Flows!$B$2:$B$1500,$B44,Flows!$C$2:$C$1500,"Input") -> 3 | T44: =COUNTIFS(Flows!$B$2:$B$1500,$B44,Flows!$C$2:$C$1500,"Output") -> 3 | U44: N/A | V44: N/A | W44: low
A45: S044 | B45: Calendula Flower | C45: Plants; Biodiversity | D45: Plants; Biodiversity | E45: Game (captured; empty I/O filled in) | F45: Medicinal flower that draws beneficial insects. | G45: 5 | H45: 3 | I45: =IF(H45="",G45,MIN(G45,H45)) -> 3 | J45: 0.25 | K45: 0.1 | L45: 10 | M45: 1 | R45: 0 | S45: =COUNTIFS(Flows!$B$2:$B$1500,$B45,Flows!$C$2:$C$1500,"Input") -> 3 | T45: =COUNTIFS(Flows!$B$2:$B$1500,$B45,Flows!$C$2:$C$1500,"Output") -> 3 | U45: N/A | V45: N/A | W45: low
A46: S045 | B46: Comfrey | C46: Plants | D46: Plants; Medicinal | E46: Game (captured) | F46: Deep-rooted dynamic accumulator for chop-and-drop. | G46: 20 | H46: 5 | I46: =IF(H46="",G46,MIN(G46,H46)) -> 5 | J46: 0.5 | K46: 0.05 | L46: 9 | M46: 20 | R46: 0 | S46: =COUNTIFS(Flows!$B$2:$B$1500,$B46,Flows!$C$2:$C$1500,"Input") -> 3 | T46: =COUNTIFS(Flows!$B$2:$B$1500,$B46,Flows!$C$2:$C$1500,"Output") -> 3 | U46: Seedlings; Water | V46: Pollinator flowers; Wellbeing; Green biomass | W46: low
A47: S046 | B47: Elderberry Bush | C47: Plants | D47: Plants | E47: Game (captured; empty I/O filled in) | F47: Medicinal berry shrub. | G47: 25 | H47: 10 | I47: =IF(H47="",G47,MIN(G47,H47)) -> 10 | J47: 1 | K47: 0.05 | L47: 36 | M47: 20 | R47: 0 | S47: =COUNTIFS(Flows!$B$2:$B$1500,$B47,Flows!$C$2:$C$1500,"Input") -> 3 | T47: =COUNTIFS(Flows!$B$2:$B$1500,$B47,Flows!$C$2:$C$1500,"Output") -> 2 | U47: N/A | V47: N/A | W47: low
A48: S047 | B48: Hardwood Tree | C48: Plants; Biomass | D48: Plants; Biomass | E48: Game (captured) | F48: Maple/ash-type hardwood, mature. | G48: 60 | H48: 15 | I48: =IF(H48="",G48,MIN(G48,H48)) -> 15 | J48: 2 | K48: 0.05 | L48: 400 | M48: 80 | R48: 0 | S48: =COUNTIFS(Flows!$B$2:$B$1500,$B48,Flows!$C$2:$C$1500,"Input") -> 3 | T48: =COUNTIFS(Flows!$B$2:$B$1500,$B48,Flows!$C$2:$C$1500,"Output") -> 3 | U48: Labor | V48: Wellbeing; Woody biomass | W48: low
A49: S048 | B49: Organic Liquid Anaerobic Fertilizer | C49: Compost | D49: Fertilizer; Storage | E49: Game (captured) | F49: Fermented plant-and-manure tea in a sealed barrel. | G49: 60 | H49: 20 | I49: =IF(H49="",G49,MIN(G49,H49)) -> 20 | J49: 1 | K49: 0.25 | L49: 6 | M49: 5 | R49: 0 | S49: =COUNTIFS(Flows!$B$2:$B$1500,$B49,Flows!$C$2:$C$1500,"Input") -> 4 | T49: =COUNTIFS(Flows!$B$2:$B$1500,$B49,Flows!$C$2:$C$1500,"Output") -> 1 | U49: Water; Green biomass; Manure | V49: Liquid fertilizer | W49: low
A50: S049 | B50: Toolshed Workshop | C50: Storage; Tools | D50: Storage; Tools | E50: Game (captured) | F50: 10x12 shed with a workbench. | G50: 4000 | H50: 1500 | I50: =IF(H50="",G50,MIN(G50,H50)) -> 1500 | J50: 60 | K50: 0.5 | L50: 120 | M50: 30 | R50: 0 | S50: =COUNTIFS(Flows!$B$2:$B$1500,$B50,Flows!$C$2:$C$1500,"Input") -> 2 | T50: =COUNTIFS(Flows!$B$2:$B$1500,$B50,Flows!$C$2:$C$1500,"Output") -> 3 | U50: Waste lumber | V50: Roofing area; Storage space | W50: low
A51: S050 | B51: Duck | C51: Livestock; Fowl | D51: Livestock; Foul | E51: Game (captured) | F51: A single laying duck (slug control too). | G51: 30 | I51: =IF(H51="",G51,MIN(G51,H51)) -> 30 | J51: 0.5 | K51: 0.2 | L51: 15 | M51: 8 | R51: 0 | S51: =COUNTIFS(Flows!$B$2:$B$1500,$B51,Flows!$C$2:$C$1500,"Input") -> 4 | T51: =COUNTIFS(Flows!$B$2:$B$1500,$B51,Flows!$C$2:$C$1500,"Output") -> 3 | U51: Green biomass; Water; Chicken feed | V51: Manure; Food | W51: low | X51: Food output entered as Eggs.
A52: S051 | B52: Turkey | C52: Fowl; Livestock | D52: Foul; Livestock | E52: Game (captured) | F52: Heritage turkey raised 26 weeks for meat. | G52: 15 | I52: =IF(H52="",G52,MIN(G52,H52)) -> 15 | J52: 1 | K52: 0.3 | L52: 25 | M52: 0.5 | R52: 0 | S52: =COUNTIFS(Flows!$B$2:$B$1500,$B52,Flows!$C$2:$C$1500,"Input") -> 6 | T52: =COUNTIFS(Flows!$B$2:$B$1500,$B52,Flows!$C$2:$C$1500,"Output") -> 2 | U52: Green feed; Grubs; Water; Chicken feed; Food waste | V52: Food; Manure | W52: low | X52: Green feed merged into Green biomass; Food entered as Meat (~18 lbs dressed).
A53: S052 | B53: Pollinators | C53: Biodiversity; Insects | D53: Biodiversity | E53: Game (captured) | F53: Wild native bees and butterflies attracted to the site. | G53: 0 | I53: =IF(H53="",G53,MIN(G53,H53)) -> 0 | J53: 0 | K53: 0 | L53: 0 | M53: 1 | R53: 0 | S53: =COUNTIFS(Flows!$B$2:$B$1500,$B53,Flows!$C$2:$C$1500,"Input") -> 1 | T53: =COUNTIFS(Flows!$B$2:$B$1500,$B53,Flows!$C$2:$C$1500,"Output") -> 1 | U53: Pollinator flowers | V53: Pollination | W53: low
A54: S053 | B54: Sunflowers | C54: Plants; Biodiversity | D54: Plant; Biodiversity | E54: Game (captured) | F54: Patch of ~5 seed sunflowers. | G54: 10 | H54: 3 | I54: =IF(H54="",G54,MIN(G54,H54)) -> 3 | J54: 0.5 | K54: 0.1 | L54: 20 | M54: 0.5 | R54: 0 | S54: =COUNTIFS(Flows!$B$2:$B$1500,$B54,Flows!$C$2:$C$1500,"Input") -> 4 | T54: =COUNTIFS(Flows!$B$2:$B$1500,$B54,Flows!$C$2:$C$1500,"Output") -> 3 | U54: Seeds; Water; Pollination | V54: Seeds; Pollinator flowers | W54: low
A55: S054 | B55: Yarrow | C55: Plants; Biodiversity | D55: Biodiversity; Plant | E55: Game (captured; empty I/O filled in) | F55: Medicinal perennial that hosts predatory insects. | G55: 8 | H55: 3 | I55: =IF(H55="",G55,MIN(G55,H55)) -> 3 | J55: 0.25 | K55: 0.05 | L55: 4 | M55: 5 | R55: 0 | S55: =COUNTIFS(Flows!$B$2:$B$1500,$B55,Flows!$C$2:$C$1500,"Input") -> 3 | T55: =COUNTIFS(Flows!$B$2:$B$1500,$B55,Flows!$C$2:$C$1500,"Output") -> 3 | U55: N/A | V55: N/A | W55: low
A56: S055 | B56: Teepee | C56: Shelter; Canvas | D56: Shelter; Canvas | E56: Game (captured) | F56: 18-ft canvas tipi on lodge poles. | G56: 2500 | H56: 700 | I56: =IF(H56="",G56,MIN(G56,H56)) -> 700 | J56: 8 | K56: 0.5 | L56: 260 | M56: 8 | N56: 250 | O56: 1 | R56: 0 | S56: =COUNTIFS(Flows!$B$2:$B$1500,$B56,Flows!$C$2:$C$1500,"Input") -> 4 | T56: =COUNTIFS(Flows!$B$2:$B$1500,$B56,Flows!$C$2:$C$1500,"Output") -> 1 | U56: Labor | V56: Shelter | W56: low
A57: S056 | B57: Yurt | C57: Shelter; Canvas | D57: Shelter; Canvas | E57: Game (captured) | F57: 20-ft insulated yurt on a platform. | G57: 18000 | H57: 6000 | I57: =IF(H57="",G57,MIN(G57,H57)) -> 6000 | J57: 40 | K57: 0.5 | L57: 320 | M57: 20 | N57: 314 | O57: 0.6 | R57: 0 | S57: =COUNTIFS(Flows!$B$2:$B$1500,$B57,Flows!$C$2:$C$1500,"Input") -> 3 | T57: =COUNTIFS(Flows!$B$2:$B$1500,$B57,Flows!$C$2:$C$1500,"Output") -> 2 | U57: N/A | V57: Shelter | W57: medium
A58: S057 | B58: Broadfork | C58: Tools | D58: Tools | E58: Game (captured) | F58: Hand tool that loosens soil without tilling. | G58: 180 | H58: 60 | I58: =IF(H58="",G58,MIN(G58,H58)) -> 60 | J58: 0 | K58: 0.5 | L58: 0 | M58: 20 | R58: 0 | S58: =COUNTIFS(Flows!$B$2:$B$1500,$B58,Flows!$C$2:$C$1500,"Input") -> 2 | T58: =COUNTIFS(Flows!$B$2:$B$1500,$B58,Flows!$C$2:$C$1500,"Output") -> 2 | U58: Labor | V58: Soil; Wellbeing | W58: low
A59: S058 | B59: Permaculture Library | C59: Tools | D59: Tools | E59: Game (captured) | F59: Reference books and courses. | G59: 400 | H59: 100 | I59: =IF(H59="",G59,MIN(G59,H59)) -> 100 | J59: 2 | K59: 1 | L59: 10 | M59: 20 | R59: 0 | S59: =COUNTIFS(Flows!$B$2:$B$1500,$B59,Flows!$C$2:$C$1500,"Input") -> 1 | T59: =COUNTIFS(Flows!$B$2:$B$1500,$B59,Flows!$C$2:$C$1500,"Output") -> 1 | U59: Labor | V59: Wellbeing | W59: low
A60: S059 | B60: Concentrated Sunlight Oven | C60: Cooking; Solar | D60: Solar; Energy; Cooking | E60: Game (captured) | F60: Parabolic solar cooker. | G60: 600 | H60: 150 | I60: =IF(H60="",G60,MIN(G60,H60)) -> 150 | J60: 1 | K60: 0.25 | L60: 10 | M60: 10 | R60: 0 | S60: =COUNTIFS(Flows!$B$2:$B$1500,$B60,Flows!$C$2:$C$1500,"Input") -> 2 | T60: =COUNTIFS(Flows!$B$2:$B$1500,$B60,Flows!$C$2:$C$1500,"Output") -> 1 | U60: Sunlight; Labor | V60: Cooking fuel | W60: low
A61: S060 | B61: Methane BioGas Generator | C61: Energy; Cooking; Sanitation; Compost | D61: Energy; Fertilizer; Cooking; Sanitation | E61: Game (captured) | F61: Household digester (HomeBiogas-class) with toilet kit. | G61: 1000 | H61: 400 | I61: =IF(H61="",G61,MIN(G61,H61)) -> 400 | J61: 12 | K61: 1 | L61: 40 | M61: 10 | R61: 0 | S61: =COUNTIFS(Flows!$B$2:$B$1500,$B61,Flows!$C$2:$C$1500,"Input") -> 5 | T61: =COUNTIFS(Flows!$B$2:$B$1500,$B61,Flows!$C$2:$C$1500,"Output") -> 3 | U61: Water; Manure; Labor; Water; Food waste; Manure; Organic waste | V61: Sanitation; Cooking fuel; Liquid fertilizer | W61: low | X61: Duplicate Water and Manure pills merged.
A62: S061 | B62: GoSun Cooler | C62: Cooling; Food System | D62: Energy; Food System; Cooling | E62: Game (captured) | F62: Solar-ready 12V compressor cooler. | G62: 900 | I62: =IF(H62="",G62,MIN(G62,H62)) -> 900 | J62: 0.25 | K62: 0.05 | L62: 4 | M62: 8 | R62: 0 | S62: =COUNTIFS(Flows!$B$2:$B$1500,$B62,Flows!$C$2:$C$1500,"Input") -> 2 | T62: =COUNTIFS(Flows!$B$2:$B$1500,$B62,Flows!$C$2:$C$1500,"Output") -> 1 | U62: Electricity | V62: Cooling | W62: low | X62: Chills food, not rooms: output changed to Food storage.
A63: S062 | B63: GoSun Fan | C63: Cooling | D63: Energy; Cooling | E63: Game (captured) | F63: Small USB/solar fan. | G63: 60 | I63: =IF(H63="",G63,MIN(G63,H63)) -> 60 | J63: 0 | K63: 0 | L63: 0 | M63: 5 | R63: 0 | S63: =COUNTIFS(Flows!$B$2:$B$1500,$B63,Flows!$C$2:$C$1500,"Input") -> 1 | T63: =COUNTIFS(Flows!$B$2:$B$1500,$B63,Flows!$C$2:$C$1500,"Output") -> 1 | U63: Electricity | V63: Cooling | W63: low | X63: Fans move air rather than remove heat; comfort-equivalent BTU.
A64: S063 | B64: Small AC Unit (5000 BTU) | C64: Cooling | D64: Cooling; Energy | E64: Game (captured) | F64: Window air conditioner, ~8 hrs/day in season (annual average). | G64: 250 | I64: =IF(H64="",G64,MIN(G64,H64)) -> 250 | J64: 1 | K64: 0.05 | L64: 3 | M64: 8 | R64: 0 | S64: =COUNTIFS(Flows!$B$2:$B$1500,$B64,Flows!$C$2:$C$1500,"Input") -> 2 | T64: =COUNTIFS(Flows!$B$2:$B$1500,$B64,Flows!$C$2:$C$1500,"Output") -> 2 | U64: Electricity | V64: Wellbeing; Cooling | W64: medium
A65: S064 | B65: LED Light | C65: Energy; Tools | D65: Energy; Tool | E65: Game (captured) | F65: 10 W LED fixture, ~6 hrs/day. | G65: 20 | I65: =IF(H65="",G65,MIN(G65,H65)) -> 20 | J65: 0 | K65: 0 | L65: 0 | M65: 15 | R65: 0 | S65: =COUNTIFS(Flows!$B$2:$B$1500,$B65,Flows!$C$2:$C$1500,"Input") -> 1 | T65: =COUNTIFS(Flows!$B$2:$B$1500,$B65,Flows!$C$2:$C$1500,"Output") -> 1 | U65: Electricity | V65: Wellbeing | W65: high
A66: S065 | B66: Oak Tree | C66: Plants; Biomass | D66: Plant; Biomass | E66: Game (captured; empty I/O filled in) | F66: Mature oak; acorns, leaves, and prunings. | G66: 40 | H66: 10 | I66: =IF(H66="",G66,MIN(G66,H66)) -> 10 | J66: 2 | K66: 0.05 | L66: 600 | M66: 150 | R66: 1 | S66: =COUNTIFS(Flows!$B$2:$B$1500,$B66,Flows!$C$2:$C$1500,"Input") -> 3 | T66: =COUNTIFS(Flows!$B$2:$B$1500,$B66,Flows!$C$2:$C$1500,"Output") -> 4 | U66: N/A | V66: N/A | W66: low | X66: Acorns need leaching before eating.
A67: S066 | B67: Rocket Mass Heater | C67: Heating | D67: Heating; Biomass | E67: Game (captured) | F67: Cob-bench rocket heater with thermal mass. | G67: 2500 | H67: 600 | I67: =IF(H67="",G67,MIN(G67,H67)) -> 600 | J67: 60 | K67: 0.5 | L67: 30 | M67: 30 | R67: 0 | S67: =COUNTIFS(Flows!$B$2:$B$1500,$B67,Flows!$C$2:$C$1500,"Input") -> 2 | T67: =COUNTIFS(Flows!$B$2:$B$1500,$B67,Flows!$C$2:$C$1500,"Output") -> 1 | U67: Woody biomass | V67: Heat | W67: medium
A68: S067 | B68: Tiny Wood Stove | C68: Heating; Cooking | D68: Energy; Biomass; Heating | E68: Game (captured) | F68: Small cast-iron stove for tiny spaces. | G68: 900 | I68: =IF(H68="",G68,MIN(G68,H68)) -> 900 | J68: 6 | K68: 0.25 | L68: 6 | M68: 20 | R68: 0 | S68: =COUNTIFS(Flows!$B$2:$B$1500,$B68,Flows!$C$2:$C$1500,"Input") -> 2 | T68: =COUNTIFS(Flows!$B$2:$B$1500,$B68,Flows!$C$2:$C$1500,"Output") -> 2 | U68: Woody biomass | V68: Cooking fuel; Heat | W68: medium
A69: S068 | B69: Biochar Kiln Firepit | C69: Biomass; Compost; Heating | D69: Energy; Compost | E69: Game (captured) | F69: Flame-cap pit that makes char while you sit by the fire. | G69: 250 | H69: 80 | I69: =IF(H69="",G69,MIN(G69,H69)) -> 80 | J69: 3 | K69: 1 | L69: 20 | M69: 10 | R69: 0 | S69: =COUNTIFS(Flows!$B$2:$B$1500,$B69,Flows!$C$2:$C$1500,"Input") -> 3 | T69: =COUNTIFS(Flows!$B$2:$B$1500,$B69,Flows!$C$2:$C$1500,"Output") -> 3 | U69: Water; Woody biomass | V69: Heat; Liquid fertilizer; Biochar | W69: low
A70: S069 | B70: Land Title ($50k) | C70: Land | D70: (none) | E70: Game (captured; empty I/O filled in) | F70: One acre bought outright. | G70: 50000 | I70: =IF(H70="",G70,MIN(G70,H70)) -> 50000 | J70: 40 | K70: 0 | L70: 0 | M70: 100 | R70: 1 | S70: =COUNTIFS(Flows!$B$2:$B$1500,$B70,Flows!$C$2:$C$1500,"Input") -> 0 | T70: =COUNTIFS(Flows!$B$2:$B$1500,$B70,Flows!$C$2:$C$1500,"Output") -> 1 | U70: N/A | V70: N/A | W70: low | X70: Use either Land Title or the Mortgage, not both.
A71: S070 | B71: 30 Year Mortgage and Interest | C71: Land | D71: Land | E71: Game (captured) | F71: Financed acre: 20% down, 7% APR. | G71: 10000 | I71: =IF(H71="",G71,MIN(G71,H71)) -> 10000 | J71: 20 | K71: 0 | L71: 0 | M71: 30 | R71: 0 | S71: =COUNTIFS(Flows!$B$2:$B$1500,$B71,Flows!$C$2:$C$1500,"Input") -> 1 | T71: =COUNTIFS(Flows!$B$2:$B$1500,$B71,Flows!$C$2:$C$1500,"Output") -> 1 | U71: Capital | V71: N/A | W71: low | X71: Purchase cost = down payment. Payment on a $40k loan.
A72: S071 | B72: Sunlight | C72: Land | D72: Land | E72: Game (captured) | F72: Solar resource of the site. | G72: 0 | I72: =IF(H72="",G72,MIN(G72,H72)) -> 0 | J72: 0 | K72: 0 | L72: 0 | M72: 100 | R72: 1 | S72: =COUNTIFS(Flows!$B$2:$B$1500,$B72,Flows!$C$2:$C$1500,"Input") -> 0 | T72: =COUNTIFS(Flows!$B$2:$B$1500,$B72,Flows!$C$2:$C$1500,"Output") -> 1 | U72: N/A | V72: Heat | W72: low | X72: Now outputs Sunlight (the game shows Heat). Set by Assumptions.
A73: S072 | B73: Bird House | C73: Biodiversity | D73: Wildlife | E73: Game (captured) | F73: Bluebird nest box. | G73: 30 | H73: 10 | I73: =IF(H73="",G73,MIN(G73,H73)) -> 10 | J73: 1 | K73: 0.05 | L73: 1 | M73: 10 | R73: 0 | S73: =COUNTIFS(Flows!$B$2:$B$1500,$B73,Flows!$C$2:$C$1500,"Input") -> 2 | T73: =COUNTIFS(Flows!$B$2:$B$1500,$B73,Flows!$C$2:$C$1500,"Output") -> 2 | U73: Waste lumber | V73: Wellbeing | W73: low
A74: S073 | B74: Blue Birds | C74: Biodiversity | D74: Wildlife | E74: Game (captured) | F74: Nesting pair of eastern/mountain bluebirds. | G74: 0 | I74: =IF(H74="",G74,MIN(G74,H74)) -> 0 | J74: 0 | K74: 0 | L74: 0 | M74: 5 | R74: 0 | S74: =COUNTIFS(Flows!$B$2:$B$1500,$B74,Flows!$C$2:$C$1500,"Input") -> 3 | T74: =COUNTIFS(Flows!$B$2:$B$1500,$B74,Flows!$C$2:$C$1500,"Output") -> 2 | U74: Grubs; Pollinator flowers | V74: Wellbeing | W74: low
A75: S074 | B75: Human Being | C75: Household | E75: Game (seen in design list; I/O by Claude) | F75: One person. Their inputs are the needs the checklist measures. | G75: 0 | I75: =IF(H75="",G75,MIN(G75,H75)) -> 0 | J75: 0 | K75: 0 | L75: 0 | M75: 80 | R75: 1 | S75: =COUNTIFS(Flows!$B$2:$B$1500,$B75,Flows!$C$2:$C$1500,"Input") -> 9 | T75: =COUNTIFS(Flows!$B$2:$B$1500,$B75,Flows!$C$2:$C$1500,"Output") -> 4 | W75: medium | X75: 2,000 kcal/day; ~0.7 gal/day drinking; 20 gal/day other water; 3 kWh/day; 150 miles/wk. Heat/cooling needs come from shelters.
A76: S075 | B76: Chicken Coop (12 hens) | C76: Livestock; Fowl | E76: Game (seen in design list; I/O by Claude) | F76: Coop and run with 12 laying hens. | G76: 2500 | H76: 800 | I76: =IF(H76="",G76,MIN(G76,H76)) -> 800 | J76: 20 | K76: 2 | L76: 150 | M76: 15 | R76: 1 | S76: =COUNTIFS(Flows!$B$2:$B$1500,$B76,Flows!$C$2:$C$1500,"Input") -> 7 | T76: =COUNTIFS(Flows!$B$2:$B$1500,$B76,Flows!$C$2:$C$1500,"Output") -> 3 | W76: medium
A77: S076 | B77: Cargo Bike | C77: Transportation | E77: Game (seen in design list; I/O by Claude) | F77: Longtail cargo bike for errands. | G77: 2500 | H77: 800 | I77: =IF(H77="",G77,MIN(G77,H77)) -> 800 | J77: 2 | K77: 0.2 | L77: 15 | M77: 10 | R77: 1 | S77: =COUNTIFS(Flows!$B$2:$B$1500,$B77,Flows!$C$2:$C$1500,"Input") -> 3 | T77: =COUNTIFS(Flows!$B$2:$B$1500,$B77,Flows!$C$2:$C$1500,"Output") -> 2 | W77: low
A78: S077 | B78: Poplar Tree | C78: Plants; Biomass | E78: Game (seen in design list; I/O by Claude) | F78: Fast-growing poplar; shade and firewood. | G78: 20 | H78: 5 | I78: =IF(H78="",G78,MIN(G78,H78)) -> 5 | J78: 1 | K78: 0.02 | L78: 300 | M78: 30 | R78: 1 | S78: =COUNTIFS(Flows!$B$2:$B$1500,$B78,Flows!$C$2:$C$1500,"Input") -> 3 | T78: =COUNTIFS(Flows!$B$2:$B$1500,$B78,Flows!$C$2:$C$1500,"Output") -> 3 | W78: low | X78: Cooling counts only if planted beside a shelter.
A79: S078 | B79: Raised Beds (24 sq ft) | C79: Garden; Food System | E79: Game (card seen; quantities recalibrated) | F79: A 4x6 raised vegetable bed. | G79: 150 | H79: 50 | I79: =IF(H79="",G79,MIN(G79,H79)) -> 50 | J79: 2 | K79: 0.5 | L79: 32 | M79: 10 | R79: 1 | S79: =COUNTIFS(Flows!$B$2:$B$1500,$B79,Flows!$C$2:$C$1500,"Input") -> 8 | T79: =COUNTIFS(Flows!$B$2:$B$1500,$B79,Flows!$C$2:$C$1500,"Output") -> 1 | U79: Labor; Water; Liquid fertilizer; Seeds | V79: Vegetables fruit fiber herbs | W79: medium | X79: Game card says 8 lbs/week and 100 gal/week. Realistic intensive yield is ~0.75 lb/sq ft/season (18 lbs) and ~1 in/week of water (15 gal).
A80: S079 | B80: Well | C80: Water-System | E80: Game (seen in design list; I/O by Claude) | F80: Drilled 200-ft well with a solar DC pump. | G80: 15000 | I80: =IF(H80="",G80,MIN(G80,H80)) -> 15000 | J80: 16 | K80: 0.1 | L80: 10 | M80: 30 | R80: 1 | S80: =COUNTIFS(Flows!$B$2:$B$1500,$B80,Flows!$C$2:$C$1500,"Input") -> 2 | T80: =COUNTIFS(Flows!$B$2:$B$1500,$B80,Flows!$C$2:$C$1500,"Output") -> 1 | W80: low | X80: Output is what the pump can deliver, not unlimited.
A81: S080 | B81: Tiny House on Wheels | C81: Shelter | E81: New (Claude) | F81: 24-ft tiny house on a trailer. | G81: 85000 | H81: 35000 | I81: =IF(H81="",G81,MIN(G81,H81)) -> 35000 | J81: 600 | K81: 0.5 | L81: 300 | M81: 30 | N81: 250 | O81: 0.25 | R81: 0 | S81: =COUNTIFS(Flows!$B$2:$B$1500,$B81,Flows!$C$2:$C$1500,"Input") -> 4 | T81: =COUNTIFS(Flows!$B$2:$B$1500,$B81,Flows!$C$2:$C$1500,"Output") -> 2 | W81: low
A82: S081 | B82: Earthship | C82: Shelter | E82: New (Claude) | F82: Tire-wall, earth-bermed home with built-in cisterns and a greenhouse face. | G82: 300000 | H82: 120000 | I82: =IF(H82="",G82,MIN(G82,H82)) -> 120000 | J82: 3000 | K82: 1.5 | L82: 1400 | M82: 100 | N82: 1200 | O82: 0.08 | R82: 0 | S82: =COUNTIFS(Flows!$B$2:$B$1500,$B82,Flows!$C$2:$C$1500,"Input") -> 5 | T82: =COUNTIFS(Flows!$B$2:$B$1500,$B82,Flows!$C$2:$C$1500,"Output") -> 5 | W82: low
A83: S082 | B83: Cob House | C83: Shelter | E83: New (Claude) | F83: Hand-built earthen home with thick thermal-mass walls. | G83: 90000 | H83: 25000 | I83: =IF(H83="",G83,MIN(G83,H83)) -> 25000 | J83: 2500 | K83: 0.5 | L83: 700 | M83: 100 | N83: 600 | O83: 0.22 | R83: 0 | S83: =COUNTIFS(Flows!$B$2:$B$1500,$B83,Flows!$C$2:$C$1500,"Input") -> 4 | T83: =COUNTIFS(Flows!$B$2:$B$1500,$B83,Flows!$C$2:$C$1500,"Output") -> 2 | W83: low
A84: S083 | B84: Straw Bale House | C84: Shelter | E84: New (Claude) | F84: Super-insulated straw bale walls with plaster. | G84: 200000 | H84: 70000 | I84: =IF(H84="",G84,MIN(G84,H84)) -> 70000 | J84: 2000 | K84: 1 | L84: 1100 | M84: 80 | N84: 1000 | O84: 0.12 | R84: 0 | S84: =COUNTIFS(Flows!$B$2:$B$1500,$B84,Flows!$C$2:$C$1500,"Input") -> 4 | T84: =COUNTIFS(Flows!$B$2:$B$1500,$B84,Flows!$C$2:$C$1500,"Output") -> 2 | W84: low | X84: ~300 bales of straw as Carbon.
A85: S084 | B85: Log Cabin Kit | C85: Shelter | E85: New (Claude) | F85: Milled log cabin kit. | G85: 150000 | H85: 60000 | I85: =IF(H85="",G85,MIN(G85,H85)) -> 60000 | J85: 1500 | K85: 1 | L85: 800 | M85: 80 | N85: 700 | O85: 0.28 | R85: 0 | S85: =COUNTIFS(Flows!$B$2:$B$1500,$B85,Flows!$C$2:$C$1500,"Input") -> 3 | T85: =COUNTIFS(Flows!$B$2:$B$1500,$B85,Flows!$C$2:$C$1500,"Output") -> 2 | W85: low
A86: S085 | B86: Shipping Container Home | C86: Shelter | E86: New (Claude) | F86: One insulated 40-ft container. | G86: 60000 | H86: 30000 | I86: =IF(H86="",G86,MIN(G86,H86)) -> 30000 | J86: 400 | K86: 0.5 | L86: 330 | M86: 40 | N86: 320 | O86: 0.3 | R86: 0 | S86: =COUNTIFS(Flows!$B$2:$B$1500,$B86,Flows!$C$2:$C$1500,"Input") -> 3 | T86: =COUNTIFS(Flows!$B$2:$B$1500,$B86,Flows!$C$2:$C$1500,"Output") -> 2 | W86: low
A87: S086 | B87: Geodesic Dome | C87: Shelter | E87: New (Claude) | F87: Kit dome home; efficient shape, awkward to gutter. | G87: 90000 | H87: 40000 | I87: =IF(H87="",G87,MIN(G87,H87)) -> 40000 | J87: 1000 | K87: 1 | L87: 750 | M87: 50 | N87: 700 | O87: 0.2 | R87: 0 | S87: =COUNTIFS(Flows!$B$2:$B$1500,$B87,Flows!$C$2:$C$1500,"Input") -> 3 | T87: =COUNTIFS(Flows!$B$2:$B$1500,$B87,Flows!$C$2:$C$1500,"Output") -> 2 | W87: low
A88: S087 | B88: Canvas Wall Tent + Stove Jack | C88: Shelter; Canvas | E88: New (Claude) | F88: 14x16 wall tent ready for a wood stove. | G88: 1500 | H88: 600 | I88: =IF(H88="",G88,MIN(G88,H88)) -> 600 | J88: 4 | K88: 0.25 | L88: 230 | M88: 8 | N88: 224 | O88: 1.3 | R88: 0 | S88: =COUNTIFS(Flows!$B$2:$B$1500,$B88,Flows!$C$2:$C$1500,"Input") -> 3 | T88: =COUNTIFS(Flows!$B$2:$B$1500,$B88,Flows!$C$2:$C$1500,"Output") -> 1 | W88: medium
A89: S088 | B89: Earthbag Dome | C89: Shelter | E89: New (Claude) | F89: Superadobe dome of stacked earth-filled bags. | G89: 12000 | H89: 3000 | I89: =IF(H89="",G89,MIN(G89,H89)) -> 3000 | J89: 800 | K89: 0.25 | L89: 260 | M89: 60 | N89: 200 | O89: 0.25 | R89: 0 | S89: =COUNTIFS(Flows!$B$2:$B$1500,$B89,Flows!$C$2:$C$1500,"Input") -> 4 | T89: =COUNTIFS(Flows!$B$2:$B$1500,$B89,Flows!$C$2:$C$1500,"Output") -> 2 | W89: low
A90: S089 | B90: Hammock + Tarp Camp | C90: Shelter; Canvas | E90: New (Claude) | F90: Hammock with a rain tarp. | G90: 250 | H90: 80 | I90: =IF(H90="",G90,MIN(G90,H90)) -> 80 | J90: 1 | K90: 0.1 | L90: 60 | M90: 3 | N90: 40 | O90: 3 | R90: 0 | S90: =COUNTIFS(Flows!$B$2:$B$1500,$B90,Flows!$C$2:$C$1500,"Input") -> 3 | T90: =COUNTIFS(Flows!$B$2:$B$1500,$B90,Flows!$C$2:$C$1500,"Output") -> 1 | W90: low | X90: Almost no insulation: huge heat need in winter.
A91: S090 | B91: Passive House (Certified) | C91: Shelter | E91: New (Claude) | F91: Airtight super-insulated home with heat-recovery ventilation. | G91: 525000 | I91: =IF(H91="",G91,MIN(G91,H91)) -> 525000 | J91: 0 | K91: 1 | L91: 1600 | M91: 80 | N91: 1500 | O91: 0.05 | R91: 0 | S91: =COUNTIFS(Flows!$B$2:$B$1500,$B91,Flows!$C$2:$C$1500,"Input") -> 4 | T91: =COUNTIFS(Flows!$B$2:$B$1500,$B91,Flows!$C$2:$C$1500,"Output") -> 2 | W91: medium
A92: S091 | B92: Treehouse | C92: Shelter | E92: New (Claude) | F92: Framed treehouse, 250 sq ft. | G92: 15000 | H92: 5000 | I92: =IF(H92="",G92,MIN(G92,H92)) -> 5000 | J92: 200 | K92: 0.5 | L92: 150 | M92: 25 | N92: 250 | O92: 0.45 | R92: 0 | S92: =COUNTIFS(Flows!$B$2:$B$1500,$B92,Flows!$C$2:$C$1500,"Input") -> 3 | T92: =COUNTIFS(Flows!$B$2:$B$1500,$B92,Flows!$C$2:$C$1500,"Output") -> 3 | W92: low | X92: The game lists "1000 BTU daily cooling"; here cooling is a load the treehouse needs, computed from climate.
A93: S092 | B93: LiFePO4 Battery Bank (10 kWh) | C93: Energy; Storage | E93: New (Claude) | F93: Lithium iron phosphate bank, 90% usable. | G93: 3500 | H93: 2500 | I93: =IF(H93="",G93,MIN(G93,H93)) -> 2500 | J93: 4 | K93: 0.05 | L93: 6 | M93: 12 | R93: 0 | S93: =COUNTIFS(Flows!$B$2:$B$1500,$B93,Flows!$C$2:$C$1500,"Input") -> 2 | T93: =COUNTIFS(Flows!$B$2:$B$1500,$B93,Flows!$C$2:$C$1500,"Output") -> 2 | W93: medium
A94: S093 | B94: Small Wind Turbine (1.5 kW) | C94: Energy | E94: New (Claude) | F94: Tower-mounted small wind turbine. | G94: 6000 | H94: 3500 | I94: =IF(H94="",G94,MIN(G94,H94)) -> 3500 | J94: 24 | K94: 0.25 | L94: 100 | M94: 20 | R94: 0 | S94: =COUNTIFS(Flows!$B$2:$B$1500,$B94,Flows!$C$2:$C$1500,"Input") -> 2 | T94: =COUNTIFS(Flows!$B$2:$B$1500,$B94,Flows!$C$2:$C$1500,"Output") -> 1 | W94: low
A95: S094 | B95: Micro-Hydro Turbine (500 W) | C95: Energy; Water-System | E95: New (Claude) | F95: Run-of-stream turbine; needs Stream Frontage. | G95: 4500 | H95: 2000 | I95: =IF(H95="",G95,MIN(G95,H95)) -> 2000 | J95: 40 | K95: 0.5 | L95: 20 | M95: 20 | R95: 0 | S95: =COUNTIFS(Flows!$B$2:$B$1500,$B95,Flows!$C$2:$C$1500,"Input") -> 2 | T95: =COUNTIFS(Flows!$B$2:$B$1500,$B95,Flows!$C$2:$C$1500,"Output") -> 1 | W95: low
A96: S095 | B96: Portable Gas Generator (3.5 kW) | C96: Energy; Conventional | E96: New (Claude) | F96: Backup gasoline generator. | G96: 900 | I96: =IF(H96="",G96,MIN(G96,H96)) -> 900 | J96: 1 | K96: 0.25 | L96: 6 | M96: 8 | R96: 0 | S96: =COUNTIFS(Flows!$B$2:$B$1500,$B96,Flows!$C$2:$C$1500,"Input") -> 2 | T96: =COUNTIFS(Flows!$B$2:$B$1500,$B96,Flows!$C$2:$C$1500,"Output") -> 1 | W96: medium
A97: S096 | B97: Propane Generator (7 kW) | C97: Energy | E97: New (Claude) | F97: Standby propane generator. | G97: 5000 | I97: =IF(H97="",G97,MIN(G97,H97)) -> 5000 | J97: 8 | K97: 0.25 | L97: 10 | M97: 20 | R97: 0 | S97: =COUNTIFS(Flows!$B$2:$B$1500,$B97,Flows!$C$2:$C$1500,"Input") -> 2 | T97: =COUNTIFS(Flows!$B$2:$B$1500,$B97,Flows!$C$2:$C$1500,"Output") -> 1 | W97: low
A98: S097 | B98: Solar Charge Controller + Inverter (3 kW) | C98: Energy | E98: New (Claude) | F98: MPPT controller and inverter; converts DC to household AC. | G98: 1500 | H98: 1100 | I98: =IF(H98="",G98,MIN(G98,H98)) -> 1100 | J98: 6 | K98: 0.05 | L98: 2 | M98: 12 | R98: 0 | S98: =COUNTIFS(Flows!$B$2:$B$1500,$B98,Flows!$C$2:$C$1500,"Input") -> 2 | T98: =COUNTIFS(Flows!$B$2:$B$1500,$B98,Flows!$C$2:$C$1500,"Output") -> 1 | W98: low | X98: Balance-of-system: small conversion loss.
A99: S098 | B99: Portable Power Station (1 kWh) | C99: Energy | E99: New (Claude) | F99: Battery box with built-in inverter. | G99: 800 | I99: =IF(H99="",G99,MIN(G99,H99)) -> 800 | J99: 0.25 | K99: 0.05 | L99: 1 | M99: 8 | R99: 0 | S99: =COUNTIFS(Flows!$B$2:$B$1500,$B99,Flows!$C$2:$C$1500,"Input") -> 2 | T99: =COUNTIFS(Flows!$B$2:$B$1500,$B99,Flows!$C$2:$C$1500,"Output") -> 2 | W99: low
A100: S099 | B100: Rooftop Solar Array (6 kW) | C100: Energy; Solar | E100: New (Claude) | F100: Roof-mounted 6 kW array. | G100: 18000 | H100: 9000 | I100: =IF(H100="",G100,MIN(G100,H100)) -> 9000 | J100: 60 | K100: 0.1 | L100: 350 | M100: 25 | R100: 0 | S100: =COUNTIFS(Flows!$B$2:$B$1500,$B100,Flows!$C$2:$C$1500,"Input") -> 2 | T100: =COUNTIFS(Flows!$B$2:$B$1500,$B100,Flows!$C$2:$C$1500,"Output") -> 1 | W100: medium
...

Sheet Flows
A1: Flow ID | B1: System | C1: Direction | D1: Resource | E1: Qty per period | F1: Unit | G1: Period | H1: Weekly equivalent (per unit) | I1: Count in design | J1: Weekly total (design) | K1: Needs Checklist row | L1: Contribution to need | M1: Key | N1: Notes
A2: F0001 | B2: 2kwh Lead Acid Battery | C2: Input | D2: Labor | E2: 0.1 | F2: =IFERROR(INDEX(Resources!$B$2:$B$64,MATCH($D2,Resources!$A$2:$A$64,0)),"?") -> hours | G2: Weekly | H2: =E2*INDEX(Assumptions!$D$17:$D$23,MATCH(G2,Assumptions!$B$17:$B$23,0)) -> 0.1 | I2: =IFERROR(INDEX(Systems!$R$2:$R$179,MATCH($B2,Systems!$B$2:$B$179,0)),0) -> 0 | J2: =H2*I2 -> 0 | K2: =IFERROR(IF(INDEX(Resources!$D$2:$D$64,MATCH($D2,Resources!$A$2:$A$64,0))="","",INDEX(Resources!$D$2:$D$64,MATCH($D2,Resources!$A$2:$A$64,0))),"") -> Est. Required Labor | L2: =IF(K2="","",J2*INDEX(Resources!$E$2:$E$64,MATCH($D2,Resources!$A$2:$A$64,0))) -> 0 | M2: =B2&"|"&D2&"|"&C2 -> 2kwh Lead Acid Battery|Labor|Input | N2: Weekly upkeep hours (Systems column K).
A3: F0002 | B3: 2kwh Lead Acid Battery | C3: Input | D3: Electricity | E3: 8.75 | F3: =IFERROR(INDEX(Resources!$B$2:$B$64,MATCH($D3,Resources!$A$2:$A$64,0)),"?") -> kWh | G3: Weekly | H3: =E3*INDEX(Assumptions!$D$17:$D$23,MATCH(G3,Assumptions!$B$17:$B$23,0)) -> 8.75 | I3: =IFERROR(INDEX(Systems!$R$2:$R$179,MATCH($B3,Systems!$B$2:$B$179,0)),0) -> 0 | J3: =H3*I3 -> 0 | K3: =IFERROR(IF(INDEX(Resources!$D$2:$D$64,MATCH($D3,Resources!$A$2:$A$64,0))="","",INDEX(Resources!$D$2:$D$64,MATCH($D3,Resources!$A$2:$A$64,0))),"") -> Electricity | L3: =IF(K3="","",J3*INDEX(Resources!$E$2:$E$64,MATCH($D3,Resources!$A$2:$A$64,0))) -> 0 | M3: =B3&"|"&D3&"|"&C3 -> 2kwh Lead Acid Battery|Electricity|Input
A4: F0003 | B4: 2kwh Lead Acid Battery | C4: Output | D4: Electricity | E4: 7 | F4: =IFERROR(INDEX(Resources!$B$2:$B$64,MATCH($D4,Resources!$A$2:$A$64,0)),"?") -> kWh | G4: Weekly | H4: =E4*INDEX(Assumptions!$D$17:$D$23,MATCH(G4,Assumptions!$B$17:$B$23,0)) -> 7 | I4: =IFERROR(INDEX(Systems!$R$2:$R$179,MATCH($B4,Systems!$B$2:$B$179,0)),0) -> 0 | J4: =H4*I4 -> 0 | K4: =IFERROR(IF(INDEX(Resources!$D$2:$D$64,MATCH($D4,Resources!$A$2:$A$64,0))="","",INDEX(Resources!$D$2:$D$64,MATCH($D4,Resources!$A$2:$A$64,0))),"") -> Electricity | L4: =IF(K4="","",J4*INDEX(Resources!$E$2:$E$64,MATCH($D4,Resources!$A$2:$A$64,0))) -> 0 | M4: =B4&"|"&D4&"|"&C4 -> 2kwh Lead Acid Battery|Electricity|Output
A5: F0004 | B5: 2kwh Lead Acid Battery | C5: Output | D5: Battery storage | E5: 1 | F5: =IFERROR(INDEX(Resources!$B$2:$B$64,MATCH($D5,Resources!$A$2:$A$64,0)),"?") -> kWh | G5: Capacity | H5: =E5*INDEX(Assumptions!$D$17:$D$23,MATCH(G5,Assumptions!$B$17:$B$23,0)) -> 1 | I5: =IFERROR(INDEX(Systems!$R$2:$R$179,MATCH($B5,Systems!$B$2:$B$179,0)),0) -> 0 | J5: =H5*I5 -> 0 | K5: =IFERROR(IF(INDEX(Resources!$D$2:$D$64,MATCH($D5,Resources!$A$2:$A$64,0))="","",INDEX(Resources!$D$2:$D$64,MATCH($D5,Resources!$A$2:$A$64,0))),"") | L5: =IF(K5="","",J5*INDEX(Resources!$E$2:$E$64,MATCH($D5,Resources!$A$2:$A$64,0))) | M5: =B5&"|"&D5&"|"&C5 -> 2kwh Lead Acid Battery|Battery storage|Output
A6: F0005 | B6: 500W Photovoltaic Panels | C6: Input | D6: Labor | E6: 0.05 | F6: =IFERROR(INDEX(Resources!$B$2:$B$64,MATCH($D6,Resources!$A$2:$A$64,0)),"?") -> hours | G6: Weekly | H6: =E6*INDEX(Assumptions!$D$17:$D$23,MATCH(G6,Assumptions!$B$17:$B$23,0)) -> 0.05 | I6: =IFERROR(INDEX(Systems!$R$2:$R$179,MATCH($B6,Systems!$B$2:$B$179,0)),0) -> 1 | J6: =H6*I6 -> 0.05 | K6: =IFERROR(IF(INDEX(Resources!$D$2:$D$64,MATCH($D6,Resources!$A$2:$A$64,0))="","",INDEX(Resources!$D$2:$D$64,MATCH($D6,Resources!$A$2:$A$64,0))),"") -> Est. Required Labor | L6: =IF(K6="","",J6*INDEX(Resources!$E$2:$E$64,MATCH($D6,Resources!$A$2:$A$64,0))) -> 0.05 | M6: =B6&"|"&D6&"|"&C6 -> 500W Photovoltaic Panels|Labor|Input | N6: Weekly upkeep hours (Systems column K).
A7: F0006 | B7: 500W Photovoltaic Panels | C7: Input | D7: Sunlight | E7: =Assumptions!$C$6*7 -> 35 | F7: =IFERROR(INDEX(Resources!$B$2:$B$64,MATCH($D7,Resources!$A$2:$A$64,0)),"?") -> sun-hours | G7: Weekly | H7: =E7*INDEX(Assumptions!$D$17:$D$23,MATCH(G7,Assumptions!$B$17:$B$23,0)) -> 35 | I7: =IFERROR(INDEX(Systems!$R$2:$R$179,MATCH($B7,Systems!$B$2:$B$179,0)),0) -> 1 | J7: =H7*I7 -> 35 | K7: =IFERROR(IF(INDEX(Resources!$D$2:$D$64,MATCH($D7,Resources!$A$2:$A$64,0))="","",INDEX(Resources!$D$2:$D$64,MATCH($D7,Resources!$A$2:$A$64,0))),"") | L7: =IF(K7="","",J7*INDEX(Resources!$E$2:$E$64,MATCH($D7,Resources!$A$2:$A$64,0))) | M7: =B7&"|"&D7&"|"&C7 -> 500W Photovoltaic Panels|Sunlight|Input | N7: Sun-hours per week from Assumptions.
A8: F0007 | B8: 500W Photovoltaic Panels | C8: Output | D8: Electricity | E8: =0.5*Assumptions!$C$6*7*Assumptions!$C$7 -> 14 | F8: =IFERROR(INDEX(Resources!$B$2:$B$64,MATCH($D8,Resources!$A$2:$A$64,0)),"?") -> kWh | G8: Weekly | H8: =E8*INDEX(Assumptions!$D$17:$D$23,MATCH(G8,Assumptions!$B$17:$B$23,0)) -> 14 | I8: =IFERROR(INDEX(Systems!$R$2:$R$179,MATCH($B8,Systems!$B$2:$B$179,0)),0) -> 1 | J8: =H8*I8 -> 14 | K8: =IFERROR(IF(INDEX(Resources!$D$2:$D$64,MATCH($D8,Resources!$A$2:$A$64,0))="","",INDEX(Resources!$D$2:$D$64,MATCH($D8,Resources!$A$2:$A$64,0))),"") -> Electricity | L8: =IF(K8="","",J8*INDEX(Resources!$E$2:$E$64,MATCH($D8,Resources!$A$2:$A$64,0))) -> 14 | M8: =B8&"|"&D8&"|"&C8 -> 500W Photovoltaic Panels|Electricity|Output | N8: 0.5 kW rating x sun-hours x derate.
A9: F0008 | B9: All Power Labs CHP | C9: Input | D9: Labor | E9: 4 | F9: =IFERROR(INDEX(Resources!$B$2:$B$64,MATCH($D9,Resources!$A$2:$A$64,0)),"?") -> hours | G9: Weekly | H9: =E9*INDEX(Assumptions!$D$17:$D$23,MATCH(G9,Assumptions!$B$17:$B$23,0)) -> 4 | I9: =IFERROR(INDEX(Systems!$R$2:$R$179,MATCH($B9,Systems!$B$2:$B$179,0)),0) -> 0 | J9: =H9*I9 -> 0 | K9: =IFERROR(IF(INDEX(Resources!$D$2:$D$64,MATCH($D9,Resources!$A$2:$A$64,0))="","",INDEX(Resources!$D$2:$D$64,MATCH($D9,Resources!$A$2:$A$64,0))),"") -> Est. Required Labor | L9: =IF(K9="","",J9*INDEX(Resources!$E$2:$E$64,MATCH($D9,Resources!$A$2:$A$64,0))) -> 0 | M9: =B9&"|"&D9&"|"&C9 -> All Power Labs CHP|Labor|Input | N9: Weekly upkeep hours (Systems column K).
A10: F0009 | B10: All Power Labs CHP | C10: Input | D10: Wood pellets | E10: 370 | F10: =IFERROR(INDEX(Resources!$B$2:$B$64,MATCH($D10,Resources!$A$2:$A$64,0)),"?") -> lbs | G10: Weekly | H10: =E10*INDEX(Assumptions!$D$17:$D$23,MATCH(G10,Assumptions!$B$17:$B$23,0)) -> 370 | I10: =IFERROR(INDEX(Systems!$R$2:$R$179,MATCH($B10,Systems!$B$2:$B$179,0)),0) -> 0 | J10: =H10*I10 -> 0 | K10: =IFERROR(IF(INDEX(Resources!$D$2:$D$64,MATCH($D10,Resources!$A$2:$A$64,0))="","",INDEX(Resources!$D$2:$D$64,MATCH($D10,Resources!$A$2:$A$64,0))),"") | L10: =IF(K10="","",J10*INDEX(Resources!$E$2:$E$64,MATCH($D10,Resources!$A$2:$A$64,0))) | M10: =B10&"|"&D10&"|"&C10 -> All Power Labs CHP|Wood pellets|Input
A11: F0010 | B11: All Power Labs CHP | C11: Output | D11: Electricity | E11: 140 | F11: =IFERROR(INDEX(Resources!$B$2:$B$64,MATCH($D11,Resources!$A$2:$A$64,0)),"?") -> kWh | G11: Weekly | H11: =E11*INDEX(Assumptions!$D$17:$D$23,MATCH(G11,Assumptions!$B$17:$B$23,0)) -> 140 | I11: =IFERROR(INDEX(Systems!$R$2:$R$179,MATCH($B11,Systems!$B$2:$B$179,0)),0) -> 0 | J11: =H11*I11 -> 0 | K11: =IFERROR(IF(INDEX(Resources!$D$2:$D$64,MATCH($D11,Resources!$A$2:$A$64,0))="","",INDEX(Resources!$D$2:$D$64,MATCH($D11,Resources!$A$2:$A$64,0))),"") -> Electricity | L11: =IF(K11="","",J11*INDEX(Resources!$E$2:$E$64,MATCH($D11,Resources!$A$2:$A$64,0))) -> 0 | M11: =B11&"|"&D11&"|"&C11 -> All Power Labs CHP|Electricity|Output
A12: F0011 | B12: All Power Labs CHP | C12: Output | D12: Heat | E12: 950000 | F12: =IFERROR(INDEX(Resources!$B$2:$B$64,MATCH($D12,Resources!$A$2:$A$64,0)),"?") -> BTU | G12: Weekly | H12: =E12*INDEX(Assumptions!$D$17:$D$23,MATCH(G12,Assumptions!$B$17:$B$23,0)) -> 950000 | I12: =IFERROR(INDEX(Systems!$R$2:$R$179,MATCH($B12,Systems!$B$2:$B$179,0)),0) -> 0 | J12: =H12*I12 -> 0 | K12: =IFERROR(IF(INDEX(Resources!$D$2:$D$64,MATCH($D12,Resources!$A$2:$A$64,0))="","",INDEX(Resources!$D$2:$D$64,MATCH($D12,Resources!$A$2:$A$64,0))),"") -> Heated shelter | L12: =IF(K12="","",J12*INDEX(Resources!$E$2:$E$64,MATCH($D12,Resources!$A$2:$A$64,0))) -> 0 | M12: =B12&"|"&D12&"|"&C12 -> All Power Labs CHP|Heat|Output
A13: F0012 | B13: All Power Labs CHP | C13: Output | D13: Biochar | E13: 10 | F13: =IFERROR(INDEX(Resources!$B$2:$B$64,MATCH($D13,Resources!$A$2:$A$64,0)),"?") -> lbs | G13: Weekly | H13: =E13*INDEX(Assumptions!$D$17:$D$23,MATCH(G13,Assumptions!$B$17:$B$23,0)) -> 10 | I13: =IFERROR(INDEX(Systems!$R$2:$R$179,MATCH($B13,Systems!$B$2:$B$179,0)),0) -> 0 | J13: =H13*I13 -> 0 | K13: =IFERROR(IF(INDEX(Resources!$D$2:$D$64,MATCH($D13,Resources!$A$2:$A$64,0))="","",INDEX(Resources!$D$2:$D$64,MATCH($D13,Resources!$A$2:$A$64,0))),"") | L13: =IF(K13="","",J13*INDEX(Resources!$E$2:$E$64,MATCH($D13,Resources!$A$2:$A$64,0))) | M13: =B13&"|"&D13&"|"&C13 -> All Power Labs CHP|Biochar|Output
A14: F0013 | B14: Biochar | C14: Input | D14: Labor | E14: 2 | F14: =IFERROR(INDEX(Resources!$B$2:$B$64,MATCH($D14,Resources!$A$2:$A$64,0)),"?") -> hours | G14: Weekly | H14: =E14*INDEX(Assumptions!$D$17:$D$23,MATCH(G14,Assumptions!$B$17:$B$23,0)) -> 2 | I14: =IFERROR(INDEX(Systems!$R$2:$R$179,MATCH($B14,Systems!$B$2:$B$179,0)),0) -> 0 | J14: =H14*I14 -> 0 | K14: =IFERROR(IF(INDEX(Resources!$D$2:$D$64,MATCH($D14,Resources!$A$2:$A$64,0))="","",INDEX(Resources!$D$2:$D$64,MATCH($D14,Resources!$A$2:$A$64,0))),"") -> Est. Required Labor | L14: =IF(K14="","",J14*INDEX(Resources!$E$2:$E$64,MATCH($D14,Resources!$A$2:$A$64,0))) -> 0 | M14: =B14&"|"&D14&"|"&C14 -> Biochar|Labor|Input | N14: Weekly upkeep hours (Systems column K).
A15: F0014 | B15: Biochar | C15: Input | D15: Woody biomass | E15: 100 | F15: =IFERROR(INDEX(Resources!$B$2:$B$64,MATCH($D15,Resources!$A$2:$A$64,0)),"?") -> lbs | G15: Weekly | H15: =E15*INDEX(Assumptions!$D$17:$D$23,MATCH(G15,Assumptions!$B$17:$B$23,0)) -> 100 | I15: =IFERROR(INDEX(Systems!$R$2:$R$179,MATCH($B15,Systems!$B$2:$B$179,0)),0) -> 0 | J15: =H15*I15 -> 0 | K15: =IFERROR(IF(INDEX(Resources!$D$2:$D$64,MATCH($D15,Resources!$A$2:$A$64,0))="","",INDEX(Resources!$D$2:$D$64,MATCH($D15,Resources!$A$2:$A$64,0))),"") | L15: =IF(K15="","",J15*INDEX(Resources!$E$2:$E$64,MATCH($D15,Resources!$A$2:$A$64,0))) | M15: =B15&"|"&D15&"|"&C15 -> Biochar|Woody biomass|Input
A16: F0015 | B16: Biochar | C16: Input | D16: Water | E16: 20 | F16: =IFERROR(INDEX(Resources!$B$2:$B$64,MATCH($D16,Resources!$A$2:$A$64,0)),"?") -> gal | G16: Weekly | H16: =E16*INDEX(Assumptions!$D$17:$D$23,MATCH(G16,Assumptions!$B$17:$B$23,0)) -> 20 | I16: =IFERROR(INDEX(Systems!$R$2:$R$179,MATCH($B16,Systems!$B$2:$B$179,0)),0) -> 0 | J16: =H16*I16 -> 0 | K16: =IFERROR(IF(INDEX(Resources!$D$2:$D$64,MATCH($D16,Resources!$A$2:$A$64,0))="","",INDEX(Resources!$D$2:$D$64,MATCH($D16,Resources!$A$2:$A$64,0))),"") -> Water | L16: =IF(K16="","",J16*INDEX(Resources!$E$2:$E$64,MATCH($D16,Resources!$A$2:$A$64,0))) -> 0 | M16: =B16&"|"&D16&"|"&C16 -> Biochar|Water|Input
A17: F0016 | B17: Biochar | C17: Output | D17: Biochar | E17: 15 | F17: =IFERROR(INDEX(Resources!$B$2:$B$64,MATCH($D17,Resources!$A$2:$A$64,0)),"?") -> lbs | G17: Weekly | H17: =E17*INDEX(Assumptions!$D$17:$D$23,MATCH(G17,Assumptions!$B$17:$B$23,0)) -> 15 | I17: =IFERROR(INDEX(Systems!$R$2:$R$179,MATCH($B17,Systems!$B$2:$B$179,0)),0) -> 0 | J17: =H17*I17 -> 0 | K17: =IFERROR(IF(INDEX(Resources!$D$2:$D$64,MATCH($D17,Resources!$A$2:$A$64,0))="","",INDEX(Resources!$D$2:$D$64,MATCH($D17,Resources!$A$2:$A$64,0))),"") | L17: =IF(K17="","",J17*INDEX(Resources!$E$2:$E$64,MATCH($D17,Resources!$A$2:$A$64,0))) | M17: =B17&"|"&D17&"|"&C17 -> Biochar|Biochar|Output
A18: F0017 | B18: Biochar Double Barrel Retort | C18: Input | D18: Labor | E18: 2 | F18: =IFERROR(INDEX(Resources!$B$2:$B$64,MATCH($D18,Resources!$A$2:$A$64,0)),"?") -> hours | G18: Weekly | H18: =E18*INDEX(Assumptions!$D$17:$D$23,MATCH(G18,Assumptions!$B$17:$B$23,0)) -> 2 | I18: =IFERROR(INDEX(Systems!$R$2:$R$179,MATCH($B18,Systems!$B$2:$B$179,0)),0) -> 0 | J18: =H18*I18 -> 0 | K18: =IFERROR(IF(INDEX(Resources!$D$2:$D$64,MATCH($D18,Resources!$A$2:$A$64,0))="","",INDEX(Resources!$D$2:$D$64,MATCH($D18,Resources!$A$2:$A$64,0))),"") -> Est. Required Labor | L18: =IF(K18="","",J18*INDEX(Resources!$E$2:$E$64,MATCH($D18,Resources!$A$2:$A$64,0))) -> 0 | M18: =B18&"|"&D18&"|"&C18 -> Biochar Double Barrel Retort|Labor|Input | N18: Weekly upkeep hours (Systems column K).
A19: F0018 | B19: Biochar Double Barrel Retort | C19: Input | D19: Wood chips | E19: 60 | F19: =IFERROR(INDEX(Resources!$B$2:$B$64,MATCH($D19,Resources!$A$2:$A$64,0)),"?") -> lbs | G19: Weekly | H19: =E19*INDEX(Assumptions!$D$17:$D$23,MATCH(G19,Assumptions!$B$17:$B$23,0)) -> 60 | I19: =IFERROR(INDEX(Systems!$R$2:$R$179,MATCH($B19,Systems!$B$2:$B$179,0)),0) -> 0 | J19: =H19*I19 -> 0 | K19: =IFERROR(IF(INDEX(Resources!$D$2:$D$64,MATCH($D19,Resources!$A$2:$A$64,0))="","",INDEX(Resources!$D$2:$D$64,MATCH($D19,Resources!$A$2:$A$64,0))),"") | L19: =IF(K19="","",J19*INDEX(Resources!$E$2:$E$64,MATCH($D19,Resources!$A$2:$A$64,0))) | M19: =B19&"|"&D19&"|"&C19 -> Biochar Double Barrel Retort|Wood chips|Input
A20: F0019 | B20: Biochar Double Barrel Retort | C20: Input | D20: Woody biomass | E20: 40 | F20: =IFERROR(INDEX(Resources!$B$2:$B$64,MATCH($D20,Resources!$A$2:$A$64,0)),"?") -> lbs | G20: Weekly | H20: =E20*INDEX(Assumptions!$D$17:$D$23,MATCH(G20,Assumptions!$B$17:$B$23,0)) -> 40 | I20: =IFERROR(INDEX(Systems!$R$2:$R$179,MATCH($B20,Systems!$B$2:$B$179,0)),0) -> 0 | J20: =H20*I20 -> 0 | K20: =IFERROR(IF(INDEX(Resources!$D$2:$D$64,MATCH($D20,Resources!$A$2:$A$64,0))="","",INDEX(Resources!$D$2:$D$64,MATCH($D20,Resources!$A$2:$A$64,0))),"") | L20: =IF(K20="","",J20*INDEX(Resources!$E$2:$E$64,MATCH($D20,Resources!$A$2:$A$64,0))) | M20: =B20&"|"&D20&"|"&C20 -> Biochar Double Barrel Retort|Woody biomass|Input
A21: F0020 | B21: Biochar Double Barrel Retort | C21: Input | D21: Waste lumber | E21: 20 | F21: =IFERROR(INDEX(Resources!$B$2:$B$64,MATCH($D21,Resources!$A$2:$A$64,0)),"?") -> lbs | G21: Weekly | H21: =E21*INDEX(Assumptions!$D$17:$D$23,MATCH(G21,Assumptions!$B$17:$B$23,0)) -> 20 | I21: =IFERROR(INDEX(Systems!$R$2:$R$179,MATCH($B21,Systems!$B$2:$B$179,0)),0) -> 0 | J21: =H21*I21 -> 0 | K21: =IFERROR(IF(INDEX(Resources!$D$2:$D$64,MATCH($D21,Resources!$A$2:$A$64,0))="","",INDEX(Resources!$D$2:$D$64,MATCH($D21,Resources!$A$2:$A$64,0))),"") | L21: =IF(K21="","",J21*INDEX(Resources!$E$2:$E$64,MATCH($D21,Resources!$A$2:$A$64,0))) | M21: =B21&"|"&D21&"|"&C21 -> Biochar Double Barrel Retort|Waste lumber|Input
A22: F0021 | B22: Biochar Double Barrel Retort | C22: Output | D22: Heat | E22: 60000 | F22: =IFERROR(INDEX(Resources!$B$2:$B$64,MATCH($D22,Resources!$A$2:$A$64,0)),"?") -> BTU | G22: Weekly | H22: =E22*INDEX(Assumptions!$D$17:$D$23,MATCH(G22,Assumptions!$B$17:$B$23,0)) -> 60000 | I22: =IFERROR(INDEX(Systems!$R$2:$R$179,MATCH($B22,Systems!$B$2:$B$179,0)),0) -> 0 | J22: =H22*I22 -> 0 | K22: =IFERROR(IF(INDEX(Resources!$D$2:$D$64,MATCH($D22,Resources!$A$2:$A$64,0))="","",INDEX(Resources!$D$2:$D$64,MATCH($D22,Resources!$A$2:$A$64,0))),"") -> Heated shelter | L22: =IF(K22="","",J22*INDEX(Resources!$E$2:$E$64,MATCH($D22,Resources!$A$2:$A$64,0))) -> 0 | M22: =B22&"|"&D22&"|"&C22 -> Biochar Double Barrel Retort|Heat|Output
A23: F0022 | B23: Biochar Double Barrel Retort | C23: Output | D23: Biochar | E23: 20 | F23: =IFERROR(INDEX(Resources!$B$2:$B$64,MATCH($D23,Resources!$A$2:$A$64,0)),"?") -> lbs | G23: Weekly | H23: =E23*INDEX(Assumptions!$D$17:$D$23,MATCH(G23,Assumptions!$B$17:$B$23,0)) -> 20 | I23: =IFERROR(INDEX(Systems!$R$2:$R$179,MATCH($B23,Systems!$B$2:$B$179,0)),0) -> 0 | J23: =H23*I23 -> 0 | K23: =IFERROR(IF(INDEX(Resources!$D$2:$D$64,MATCH($D23,Resources!$A$2:$A$64,0))="","",INDEX(Resources!$D$2:$D$64,MATCH($D23,Resources!$A$2:$A$64,0))),"") | L23: =IF(K23="","",J23*INDEX(Resources!$E$2:$E$64,MATCH($D23,Resources!$A$2:$A$64,0))) | M23: =B23&"|"&D23&"|"&C23 -> Biochar Double Barrel Retort|Biochar|Output
A24: F0023 | B24: A-Frame House | C24: Input | D24: Labor | E24: 1 | F24: =IFERROR(INDEX(Resources!$B$2:$B$64,MATCH($D24,Resources!$A$2:$A$64,0)),"?") -> hours | G24: Weekly | H24: =E24*INDEX(Assumptions!$D$17:$D$23,MATCH(G24,Assumptions!$B$17:$B$23,0)) -> 1 | I24: =IFERROR(INDEX(Systems!$R$2:$R$179,MATCH($B24,Systems!$B$2:$B$179,0)),0) -> 0 | J24: =H24*I24 -> 0 | K24: =IFERROR(IF(INDEX(Resources!$D$2:$D$64,MATCH($D24,Resources!$A$2:$A$64,0))="","",INDEX(Resources!$D$2:$D$64,MATCH($D24,Resources!$A$2:$A$64,0))),"") -> Est. Required Labor | L24: =IF(K24="","",J24*INDEX(Resources!$E$2:$E$64,MATCH($D24,Resources!$A$2:$A$64,0))) -> 0 | M24: =B24&"|"&D24&"|"&C24 -> A-Frame House|Labor|Input | N24: Weekly upkeep hours (Systems column K).
A25: F0024 | B25: A-Frame House | C25: Input | D25: Capital | E25: 60 | F25: =IFERROR(INDEX(Resources!$B$2:$B$64,MATCH($D25,Resources!$A$2:$A$64,0)),"?") -> $ | G25: Weekly | H25: =E25*INDEX(Assumptions!$D$17:$D$23,MATCH(G25,Assumptions!$B$17:$B$23,0)) -> 60 | I25: =IFERROR(INDEX(Systems!$R$2:$R$179,MATCH($B25,Systems!$B$2:$B$179,0)),0) -> 0 | J25: =H25*I25 -> 0 | K25: =IFERROR(IF(INDEX(Resources!$D$2:$D$64,MATCH($D25,Resources!$A$2:$A$64,0))="","",INDEX(Resources!$D$2:$D$64,MATCH($D25,Resources!$A$2:$A$64,0))),"") | L25: =IF(K25="","",J25*INDEX(Resources!$E$2:$E$64,MATCH($D25,Resources!$A$2:$A$64,0))) | M25: =B25&"|"&D25&"|"&C25 -> A-Frame House|Capital|Input
A26: F0025 | B26: A-Frame House | C26: Output | D26: Shelter | E26: 800 | F26: =IFERROR(INDEX(Resources!$B$2:$B$64,MATCH($D26,Resources!$A$2:$A$64,0)),"?") -> sq ft | G26: Capacity | H26: =E26*INDEX(Assumptions!$D$17:$D$23,MATCH(G26,Assumptions!$B$17:$B$23,0)) -> 800 | I26: =IFERROR(INDEX(Systems!$R$2:$R$179,MATCH($B26,Systems!$B$2:$B$179,0)),0) -> 0 | J26: =H26*I26 -> 0 | K26: =IFERROR(IF(INDEX(Resources!$D$2:$D$64,MATCH($D26,Resources!$A$2:$A$64,0))="","",INDEX(Resources!$D$2:$D$64,MATCH($D26,Resources!$A$2:$A$64,0))),"") -> Shelter | L26: =IF(K26="","",J26*INDEX(Resources!$E$2:$E$64,MATCH($D26,Resources!$A$2:$A$64,0))) -> 0 | M26: =B26&"|"&D26&"|"&C26 -> A-Frame House|Shelter|Output
A27: F0026 | B27: A-Frame House | C27: Output | D27: Roofing area | E27: 1100 | F27: =IFERROR(INDEX(Resources!$B$2:$B$64,MATCH($D27,Resources!$A$2:$A$64,0)),"?") -> sq ft | G27: Capacity | H27: =E27*INDEX(Assumptions!$D$17:$D$23,MATCH(G27,Assumptions!$B$17:$B$23,0)) -> 1100 | I27: =IFERROR(INDEX(Systems!$R$2:$R$179,MATCH($B27,Systems!$B$2:$B$179,0)),0) -> 0 | J27: =H27*I27 -> 0 | K27: =IFERROR(IF(INDEX(Resources!$D$2:$D$64,MATCH($D27,Resources!$A$2:$A$64,0))="","",INDEX(Resources!$D$2:$D$64,MATCH($D27,Resources!$A$2:$A$64,0))),"") | L27: =IF(K27="","",J27*INDEX(Resources!$E$2:$E$64,MATCH($D27,Resources!$A$2:$A$64,0))) | M27: =B27&"|"&D27&"|"&C27 -> A-Frame House|Roofing area|Output
A28: F0027 | B28: A-Frame House | C28: Input | D28: Heat | E28: =INDEX(Systems!$N$2:$N$179,MATCH($B28,Systems!$B$2:$B$179,0))*INDEX(Systems!$O$2:$O$179,MATCH($B28,Systems!$B$2:$B$179,0))*Assumptions!$C$4*24/52 -> 664615.38 | F28: =IFERROR(INDEX(Resources!$B$2:$B$64,MATCH($D28,Resources!$A$2:$A$64,0)),"?") -> BTU | G28: Weekly | H28: =E28*INDEX(Assumptions!$D$17:$D$23,MATCH(G28,Assumptions!$B$17:$B$23,0)) -> 664615.38 | I28: =IFERROR(INDEX(Systems!$R$2:$R$179,MATCH($B28,Systems!$B$2:$B$179,0)),0) -> 0 | J28: =H28*I28 -> 0 | K28: =IFERROR(IF(INDEX(Resources!$D$2:$D$64,MATCH($D28,Resources!$A$2:$A$64,0))="","",INDEX(Resources!$D$2:$D$64,MATCH($D28,Resources!$A$2:$A$64,0))),"") -> Heated shelter | L28: =IF(K28="","",J28*INDEX(Resources!$E$2:$E$64,MATCH($D28,Resources!$A$2:$A$64,0))) -> 0 | M28: =B28&"|"&D28&"|"&C28 -> A-Frame House|Heat|Input | N28: Heating load = area x heat-loss factor x HDD x 24 / 52.
A29: F0028 | B29: A-Frame House | C29: Input | D29: Cooling | E29: =INDEX(Systems!$N$2:$N$179,MATCH($B29,Systems!$B$2:$B$179,0))*INDEX(Systems!$O$2:$O$179,MATCH($B29,Systems!$B$2:$B$179,0))*Assumptions!$C$5*24/52 -> 88615.385 | F29: =IFERROR(INDEX(Resources!$B$2:$B$64,MATCH($D29,Resources!$A$2:$A$64,0)),"?") -> BTU | G29: Weekly | H29: =E29*INDEX(Assumptions!$D$17:$D$23,MATCH(G29,Assumptions!$B$17:$B$23,0)) -> 88615.385 | I29: =IFERROR(INDEX(Systems!$R$2:$R$179,MATCH($B29,Systems!$B$2:$B$179,0)),0) -> 0 | J29: =H29*I29 -> 0 | K29: =IFERROR(IF(INDEX(Resources!$D$2:$D$64,MATCH($D29,Resources!$A$2:$A$64,0))="","",INDEX(Resources!$D$2:$D$64,MATCH($D29,Resources!$A$2:$A$64,0))),"") -> Cooled shelter | L29: =IF(K29="","",J29*INDEX(Resources!$E$2:$E$64,MATCH($D29,Resources!$A$2:$A$64,0))) -> 0 | M29: =B29&"|"&D29&"|"&C29 -> A-Frame House|Cooling|Input | N29: Cooling load = area x heat-loss factor x CDD x 24 / 52.
A30: F0029 | B30: Average Suburban Home | C30: Input | D30: Labor | E30: 2 | F30: =IFERROR(INDEX(Resources!$B$2:$B$64,MATCH($D30,Resources!$A$2:$A$64,0)),"?") -> hours | G30: Weekly | H30: =E30*INDEX(Assumptions!$D$17:$D$23,MATCH(G30,Assumptions!$B$17:$B$23,0)) -> 2 | I30: =IFERROR(INDEX(Systems!$R$2:$R$179,MATCH($B30,Systems!$B$2:$B$179,0)),0) -> 0 | J30: =H30*I30 -> 0 | K30: =IFERROR(IF(INDEX(Resources!$D$2:$D$64,MATCH($D30,Resources!$A$2:$A$64,0))="","",INDEX(Resources!$D$2:$D$64,MATCH($D30,Resources!$A$2:$A$64,0))),"") -> Est. Required Labor | L30: =IF(K30="","",J30*INDEX(Resources!$E$2:$E$64,MATCH($D30,Resources!$A$2:$A$64,0))) -> 0 | M30: =B30&"|"&D30&"|"&C30 -> Average Suburban Home|Labor|Input | N30: Weekly upkeep hours (Systems column K).
A31: F0030 | B31: Average Suburban Home | C31: Input | D31: Capital | E31: 250 | F31: =IFERROR(INDEX(Resources!$B$2:$B$64,MATCH($D31,Resources!$A$2:$A$64,0)),"?") -> $ | G31: Weekly | H31: =E31*INDEX(Assumptions!$D$17:$D$23,MATCH(G31,Assumptions!$B$17:$B$23,0)) -> 250 | I31: =IFERROR(INDEX(Systems!$R$2:$R$179,MATCH($B31,Systems!$B$2:$B$179,0)),0) -> 0 | J31: =H31*I31 -> 0 | K31: =IFERROR(IF(INDEX(Resources!$D$2:$D$64,MATCH($D31,Resources!$A$2:$A$64,0))="","",INDEX(Resources!$D$2:$D$64,MATCH($D31,Resources!$A$2:$A$64,0))),"") | L31: =IF(K31="","",J31*INDEX(Resources!$E$2:$E$64,MATCH($D31,Resources!$A$2:$A$64,0))) | M31: =B31&"|"&D31&"|"&C31 -> Average Suburban Home|Capital|Input
A32: F0031 | B32: Average Suburban Home | C32: Output | D32: Shelter | E32: 2000 | F32: =IFERROR(INDEX(Resources!$B$2:$B$64,MATCH($D32,Resources!$A$2:$A$64,0)),"?") -> sq ft | G32: Capacity | H32: =E32*INDEX(Assumptions!$D$17:$D$23,MATCH(G32,Assumptions!$B$17:$B$23,0)) -> 2000 | I32: =IFERROR(INDEX(Systems!$R$2:$R$179,MATCH($B32,Systems!$B$2:$B$179,0)),0) -> 0 | J32: =H32*I32 -> 0 | K32: =IFERROR(IF(INDEX(Resources!$D$2:$D$64,MATCH($D32,Resources!$A$2:$A$64,0))="","",INDEX(Resources!$D$2:$D$64,MATCH($D32,Resources!$A$2:$A$64,0))),"") -> Shelter | L32: =IF(K32="","",J32*INDEX(Resources!$E$2:$E$64,MATCH($D32,Resources!$A$2:$A$64,0))) -> 0 | M32: =B32&"|"&D32&"|"&C32 -> Average Suburban Home|Shelter|Output
A33: F0032 | B33: Average Suburban Home | C33: Output | D33: Roofing area | E33: 2200 | F33: =IFERROR(INDEX(Resources!$B$2:$B$64,MATCH($D33,Resources!$A$2:$A$64,0)),"?") -> sq ft | G33: Capacity | H33: =E33*INDEX(Assumptions!$D$17:$D$23,MATCH(G33,Assumptions!$B$17:$B$23,0)) -> 2200 | I33: =IFERROR(INDEX(Systems!$R$2:$R$179,MATCH($B33,Systems!$B$2:$B$179,0)),0) -> 0 | J33: =H33*I33 -> 0 | K33: =IFERROR(IF(INDEX(Resources!$D$2:$D$64,MATCH($D33,Resources!$A$2:$A$64,0))="","",INDEX(Resources!$D$2:$D$64,MATCH($D33,Resources!$A$2:$A$64,0))),"") | L33: =IF(K33="","",J33*INDEX(Resources!$E$2:$E$64,MATCH($D33,Resources!$A$2:$A$64,0))) | M33: =B33&"|"&D33&"|"&C33 -> Average Suburban Home|Roofing area|Output
A34: F0033 | B34: Average Suburban Home | C34: Output | D34: Water | E34: 600 | F34: =IFERROR(INDEX(Resources!$B$2:$B$64,MATCH($D34,Resources!$A$2:$A$64,0)),"?") -> gal | G34: Weekly | H34: =E34*INDEX(Assumptions!$D$17:$D$23,MATCH(G34,Assumptions!$B$17:$B$23,0)) -> 600 | I34: =IFERROR(INDEX(Systems!$R$2:$R$179,MATCH($B34,Systems!$B$2:$B$179,0)),0) -> 0 | J34: =H34*I34 -> 0 | K34: =IFERROR(IF(INDEX(Resources!$D$2:$D$64,MATCH($D34,Resources!$A$2:$A$64,0))="","",INDEX(Resources!$D$2:$D$64,MATCH($D34,Resources!$A$2:$A$64,0))),"") -> Water | L34: =IF(K34="","",J34*INDEX(Resources!$E$2:$E$64,MATCH($D34,Resources!$A$2:$A$64,0))) -> 0 | M34: =B34&"|"&D34&"|"&C34 -> Average Suburban Home|Water|Output
A35: F0034 | B35: Average Suburban Home | C35: Output | D35: Drinking water | E35: 20 | F35: =IFERROR(INDEX(Resources!$B$2:$B$64,MATCH($D35,Resources!$A$2:$A$64,0)),"?") -> gal | G35: Weekly | H35: =E35*INDEX(Assumptions!$D$17:$D$23,MATCH(G35,Assumptions!$B$17:$B$23,0)) -> 20 | I35: =IFERROR(INDEX(Systems!$R$2:$R$179,MATCH($B35,Systems!$B$2:$B$179,0)),0) -> 0 | J35: =H35*I35 -> 0 | K35: =IFERROR(IF(INDEX(Resources!$D$2:$D$64,MATCH($D35,Resources!$A$2:$A$64,0))="","",INDEX(Resources!$D$2:$D$64,MATCH($D35,Resources!$A$2:$A$64,0))),"") -> Drinking water | L35: =IF(K35="","",J35*INDEX(Resources!$E$2:$E$64,MATCH($D35,Resources!$A$2:$A$64,0))) -> 0 | M35: =B35&"|"&D35&"|"&C35 -> Average Suburban Home|Drinking water|Output
A36: F0035 | B36: Average Suburban Home | C36: Output | D36: Hot water | E36: 150 | F36: =IFERROR(INDEX(Resources!$B$2:$B$64,MATCH($D36,Resources!$A$2:$A$64,0)),"?") -> gal | G36: Weekly | H36: =E36*INDEX(Assumptions!$D$17:$D$23,MATCH(G36,Assumptions!$B$17:$B$23,0)) -> 150 | I36: =IFERROR(INDEX(Systems!$R$2:$R$179,MATCH($B36,Systems!$B$2:$B$179,0)),0) -> 0 | J36: =H36*I36 -> 0 | K36: =IFERROR(IF(INDEX(Resources!$D$2:$D$64,MATCH($D36,Resources!$A$2:$A$64,0))="","",INDEX(Resources!$D$2:$D$64,MATCH($D36,Resources!$A$2:$A$64,0))),"") | L36: =IF(K36="","",J36*INDEX(Resources!$E$2:$E$64,MATCH($D36,Resources!$A$2:$A$64,0))) | M36: =B36&"|"&D36&"|"&C36 -> Average Suburban Home|Hot water|Output
A37: F0036 | B37: Average Suburban Home | C37: Output | D37: Sanitation | E37: 35 | F37: =IFERROR(INDEX(Resources!$B$2:$B$64,MATCH($D37,Resources!$A$2:$A$64,0)),"?") -> lbs | G37: Weekly | H37: =E37*INDEX(Assumptions!$D$17:$D$23,MATCH(G37,Assumptions!$B$17:$B$23,0)) -> 35 | I37: =IFERROR(INDEX(Systems!$R$2:$R$179,MATCH($B37,Systems!$B$2:$B$179,0)),0) -> 0 | J37: =H37*I37 -> 0 | K37: =IFERROR(IF(INDEX(Resources!$D$2:$D$64,MATCH($D37,Resources!$A$2:$A$64,0))="","",INDEX(Resources!$D$2:$D$64,MATCH($D37,Resources!$A$2:$A$64,0))),"") -> Sanitation | L37: =IF(K37="","",J37*INDEX(Resources!$E$2:$E$64,MATCH($D37,Resources!$A$2:$A$64,0))) -> 0 | M37: =B37&"|"&D37&"|"&C37 -> Average Suburban Home|Sanitation|Output
A38: F0037 | B38: Average Suburban Home | C38: Input | D38: Heat | E38: =INDEX(Systems!$N$2:$N$179,MATCH($B38,Systems!$B$2:$B$179,0))*INDEX(Systems!$O$2:$O$179,MATCH($B38,Systems!$B$2:$B$179,0))*Assumptions!$C$4*24/52 -> 1384615.4 | F38: =IFERROR(INDEX(Resources!$B$2:$B$64,MATCH($D38,Resources!$A$2:$A$64,0)),"?") -> BTU | G38: Weekly | H38: =E38*INDEX(Assumptions!$D$17:$D$23,MATCH(G38,Assumptions!$B$17:$B$23,0)) -> 1384615.4 | I38: =IFERROR(INDEX(Systems!$R$2:$R$179,MATCH($B38,Systems!$B$2:$B$179,0)),0) -> 0 | J38: =H38*I38 -> 0 | K38: =IFERROR(IF(INDEX(Resources!$D$2:$D$64,MATCH($D38,Resources!$A$2:$A$64,0))="","",INDEX(Resources!$D$2:$D$64,MATCH($D38,Resources!$A$2:$A$64,0))),"") -> Heated shelter | L38: =IF(K38="","",J38*INDEX(Resources!$E$2:$E$64,MATCH($D38,Resources!$A$2:$A$64,0))) -> 0 | M38: =B38&"|"&D38&"|"&C38 -> Average Suburban Home|Heat|Input | N38: Heating load = area x heat-loss factor x HDD x 24 / 52.
A39: F0038 | B39: Average Suburban Home | C39: Input | D39: Cooling | E39: =INDEX(Systems!$N$2:$N$179,MATCH($B39,Systems!$B$2:$B$179,0))*INDEX(Systems!$O$2:$O$179,MATCH($B39,Systems!$B$2:$B$179,0))*Assumptions!$C$5*24/52 -> 184615.38 | F39: =IFERROR(INDEX(Resources!$B$2:$B$64,MATCH($D39,Resources!$A$2:$A$64,0)),"?") -> BTU | G39: Weekly | H39: =E39*INDEX(Assumptions!$D$17:$D$23,MATCH(G39,Assumptions!$B$17:$B$23,0)) -> 184615.38 | I39: =IFERROR(INDEX(Systems!$R$2:$R$179,MATCH($B39,Systems!$B$2:$B$179,0)),0) -> 0 | J39: =H39*I39 -> 0 | K39: =IFERROR(IF(INDEX(Resources!$D$2:$D$64,MATCH($D39,Resources!$A$2:$A$64,0))="","",INDEX(Resources!$D$2:$D$64,MATCH($D39,Resources!$A$2:$A$64,0))),"") -> Cooled shelter | L39: =IF(K39="","",J39*INDEX(Resources!$E$2:$E$64,MATCH($D39,Resources!$A$2:$A$64,0))) -> 0 | M39: =B39&"|"&D39&"|"&C39 -> Average Suburban Home|Cooling|Input | N39: Cooling load = area x heat-loss factor x CDD x 24 / 52.
A40: F0039 | B40: Bell Tent | C40: Input | D40: Labor | E40: 0.25 | F40: =IFERROR(INDEX(Resources!$B$2:$B$64,MATCH($D40,Resources!$A$2:$A$64,0)),"?") -> hours | G40: Weekly | H40: =E40*INDEX(Assumptions!$D$17:$D$23,MATCH(G40,Assumptions!$B$17:$B$23,0)) -> 0.25 | I40: =IFERROR(INDEX(Systems!$R$2:$R$179,MATCH($B40,Systems!$B$2:$B$179,0)),0) -> 1 | J40: =H40*I40 -> 0.25 | K40: =IFERROR(IF(INDEX(Resources!$D$2:$D$64,MATCH($D40,Resources!$A$2:$A$64,0))="","",INDEX(Resources!$D$2:$D$64,MATCH($D40,Resources!$A$2:$A$64,0))),"") -> Est. Required Labor | L40: =IF(K40="","",J40*INDEX(Resources!$E$2:$E$64,MATCH($D40,Resources!$A$2:$A$64,0))) -> 0.25 | M40: =B40&"|"&D40&"|"&C40 -> Bell Tent|Labor|Input | N40: Weekly upkeep hours (Systems column K).
A41: F0040 | B41: Bell Tent | C41: Output | D41: Shelter | E41: 210 | F41: =IFERROR(INDEX(Resources!$B$2:$B$64,MATCH($D41,Resources!$A$2:$A$64,0)),"?") -> sq ft | G41: Capacity | H41: =E41*INDEX(Assumptions!$D$17:$D$23,MATCH(G41,Assumptions!$B$17:$B$23,0)) -> 210 | I41: =IFERROR(INDEX(Systems!$R$2:$R$179,MATCH($B41,Systems!$B$2:$B$179,0)),0) -> 1 | J41: =H41*I41 -> 210 | K41: =IFERROR(IF(INDEX(Resources!$D$2:$D$64,MATCH($D41,Resources!$A$2:$A$64,0))="","",INDEX(Resources!$D$2:$D$64,MATCH($D41,Resources!$A$2:$A$64,0))),"") -> Shelter | L41: =IF(K41="","",J41*INDEX(Resources!$E$2:$E$64,MATCH($D41,Resources!$A$2:$A$64,0))) -> 210 | M41: =B41&"|"&D41&"|"&C41 -> Bell Tent|Shelter|Output
A42: F0041 | B42: Bell Tent | C42: Input | D42: Heat | E42: =INDEX(Systems!$N$2:$N$179,MATCH($B42,Systems!$B$2:$B$179,0))*INDEX(Systems!$O$2:$O$179,MATCH($B42,Systems!$B$2:$B$179,0))*Assumptions!$C$4*24/52 -> 697846.15 | F42: =IFERROR(INDEX(Resources!$B$2:$B$64,MATCH($D42,Resources!$A$2:$A$64,0)),"?") -> BTU | G42: Weekly | H42: =E42*INDEX(Assumptions!$D$17:$D$23,MATCH(G42,Assumptions!$B$17:$B$23,0)) -> 697846.15 | I42: =IFERROR(INDEX(Systems!$R$2:$R$179,MATCH($B42,Systems!$B$2:$B$179,0)),0) -> 1 | J42: =H42*I42 -> 697846.15 | K42: =IFERROR(IF(INDEX(Resources!$D$2:$D$64,MATCH($D42,Resources!$A$2:$A$64,0))="","",INDEX(Resources!$D$2:$D$64,MATCH($D42,Resources!$A$2:$A$64,0))),"") -> Heated shelter | L42: =IF(K42="","",J42*INDEX(Resources!$E$2:$E$64,MATCH($D42,Resources!$A$2:$A$64,0))) -> 697846.15 | M42: =B42&"|"&D42&"|"&C42 -> Bell Tent|Heat|Input | N42: Heating load = area x heat-loss factor x HDD x 24 / 52.
A43: F0042 | B43: Bell Tent | C43: Input | D43: Cooling | E43: =INDEX(Systems!$N$2:$N$179,MATCH($B43,Systems!$B$2:$B$179,0))*INDEX(Systems!$O$2:$O$179,MATCH($B43,Systems!$B$2:$B$179,0))*Assumptions!$C$5*24/52 -> 93046.154 | F43: =IFERROR(INDEX(Resources!$B$2:$B$64,MATCH($D43,Resources!$A$2:$A$64,0)),"?") -> BTU | G43: Weekly | H43: =E43*INDEX(Assumptions!$D$17:$D$23,MATCH(G43,Assumptions!$B$17:$B$23,0)) -> 93046.154 | I43: =IFERROR(INDEX(Systems!$R$2:$R$179,MATCH($B43,Systems!$B$2:$B$179,0)),0) -> 1 | J43: =H43*I43 -> 93046.154 | K43: =IFERROR(IF(INDEX(Resources!$D$2:$D$64,MATCH($D43,Resources!$A$2:$A$64,0))="","",INDEX(Resources!$D$2:$D$64,MATCH($D43,Resources!$A$2:$A$64,0))),"") -> Cooled shelter | L43: =IF(K43="","",J43*INDEX(Resources!$E$2:$E$64,MATCH($D43,Resources!$A$2:$A$64,0))) -> 93046.154 | M43: =B43&"|"&D43&"|"&C43 -> Bell Tent|Cooling|Input | N43: Cooling load = area x heat-loss factor x CDD x 24 / 52.
A44: F0043 | B44: Camp 365 Off-Grid Camper | C44: Input | D44: Labor | E44: 0.5 | F44: =IFERROR(INDEX(Resources!$B$2:$B$64,MATCH($D44,Resources!$A$2:$A$64,0)),"?") -> hours | G44: Weekly | H44: =E44*INDEX(Assumptions!$D$17:$D$23,MATCH(G44,Assumptions!$B$17:$B$23,0)) -> 0.5 | I44: =IFERROR(INDEX(Systems!$R$2:$R$179,MATCH($B44,Systems!$B$2:$B$179,0)),0) -> 0 | J44: =H44*I44 -> 0 | K44: =IFERROR(IF(INDEX(Resources!$D$2:$D$64,MATCH($D44,Resources!$A$2:$A$64,0))="","",INDEX(Resources!$D$2:$D$64,MATCH($D44,Resources!$A$2:$A$64,0))),"") -> Est. Required Labor | L44: =IF(K44="","",J44*INDEX(Resources!$E$2:$E$64,MATCH($D44,Resources!$A$2:$A$64,0))) -> 0 | M44: =B44&"|"&D44&"|"&C44 -> Camp 365 Off-Grid Camper|Labor|Input | N44: Weekly upkeep hours (Systems column K).
A45: F0044 | B45: Camp 365 Off-Grid Camper | C45: Input | D45: Capital | E45: 25 | F45: =IFERROR(INDEX(Resources!$B$2:$B$64,MATCH($D45,Resources!$A$2:$A$64,0)),"?") -> $ | G45: Weekly | H45: =E45*INDEX(Assumptions!$D$17:$D$23,MATCH(G45,Assumptions!$B$17:$B$23,0)) -> 25 | I45: =IFERROR(INDEX(Systems!$R$2:$R$179,MATCH($B45,Systems!$B$2:$B$179,0)),0) -> 0 | J45: =H45*I45 -> 0 | K45: =IFERROR(IF(INDEX(Resources!$D$2:$D$64,MATCH($D45,Resources!$A$2:$A$64,0))="","",INDEX(Resources!$D$2:$D$64,MATCH($D45,Resources!$A$2:$A$64,0))),"") | L45: =IF(K45="","",J45*INDEX(Resources!$E$2:$E$64,MATCH($D45,Resources!$A$2:$A$64,0))) | M45: =B45&"|"&D45&"|"&C45 -> Camp 365 Off-Grid Camper|Capital|Input
A46: F0045 | B46: Camp 365 Off-Grid Camper | C46: Output | D46: Shelter | E46: 150 | F46: =IFERROR(INDEX(Resources!$B$2:$B$64,MATCH($D46,Resources!$A$2:$A$64,0)),"?") -> sq ft | G46: Capacity | H46: =E46*INDEX(Assumptions!$D$17:$D$23,MATCH(G46,Assumptions!$B$17:$B$23,0)) -> 150 | I46: =IFERROR(INDEX(Systems!$R$2:$R$179,MATCH($B46,Systems!$B$2:$B$179,0)),0) -> 0 | J46: =H46*I46 -> 0 | K46: =IFERROR(IF(INDEX(Resources!$D$2:$D$64,MATCH($D46,Resources!$A$2:$A$64,0))="","",INDEX(Resources!$D$2:$D$64,MATCH($D46,Resources!$A$2:$A$64,0))),"") -> Shelter | L46: =IF(K46="","",J46*INDEX(Resources!$E$2:$E$64,MATCH($D46,Resources!$A$2:$A$64,0))) -> 0 | M46: =B46&"|"&D46&"|"&C46 -> Camp 365 Off-Grid Camper|Shelter|Output
A47: F0046 | B47: Camp 365 Off-Grid Camper | C47: Output | D47: Roofing area | E47: 150 | F47: =IFERROR(INDEX(Resources!$B$2:$B$64,MATCH($D47,Resources!$A$2:$A$64,0)),"?") -> sq ft | G47: Capacity | H47: =E47*INDEX(Assumptions!$D$17:$D$23,MATCH(G47,Assumptions!$B$17:$B$23,0)) -> 150 | I47: =IFERROR(INDEX(Systems!$R$2:$R$179,MATCH($B47,Systems!$B$2:$B$179,0)),0) -> 0 | J47: =H47*I47 -> 0 | K47: =IFERROR(IF(INDEX(Resources!$D$2:$D$64,MATCH($D47,Resources!$A$2:$A$64,0))="","",INDEX(Resources!$D$2:$D$64,MATCH($D47,Resources!$A$2:$A$64,0))),"") | L47: =IF(K47="","",J47*INDEX(Resources!$E$2:$E$64,MATCH($D47,Resources!$A$2:$A$64,0))) | M47: =B47&"|"&D47&"|"&C47 -> Camp 365 Off-Grid Camper|Roofing area|Output
A48: F0047 | B48: Camp 365 Off-Grid Camper | C48: Input | D48: Heat | E48: =INDEX(Systems!$N$2:$N$179,MATCH($B48,Systems!$B$2:$B$179,0))*INDEX(Systems!$O$2:$O$179,MATCH($B48,Systems!$B$2:$B$179,0))*Assumptions!$C$4*24/52 -> 249230.77 | F48: =IFERROR(INDEX(Resources!$B$2:$B$64,MATCH($D48,Resources!$A$2:$A$64,0)),"?") -> BTU | G48: Weekly | H48: =E48*INDEX(Assumptions!$D$17:$D$23,MATCH(G48,Assumptions!$B$17:$B$23,0)) -> 249230.77 | I48: =IFERROR(INDEX(Systems!$R$2:$R$179,MATCH($B48,Systems!$B$2:$B$179,0)),0) -> 0 | J48: =H48*I48 -> 0 | K48: =IFERROR(IF(INDEX(Resources!$D$2:$D$64,MATCH($D48,Resources!$A$2:$A$64,0))="","",INDEX(Resources!$D$2:$D$64,MATCH($D48,Resources!$A$2:$A$64,0))),"") -> Heated shelter | L48: =IF(K48="","",J48*INDEX(Resources!$E$2:$E$64,MATCH($D48,Resources!$A$2:$A$64,0))) -> 0 | M48: =B48&"|"&D48&"|"&C48 -> Camp 365 Off-Grid Camper|Heat|Input | N48: Heating load = area x heat-loss factor x HDD x 24 / 52.
A49: F0048 | B49: Camp 365 Off-Grid Camper | C49: Input | D49: Cooling | E49: =INDEX(Systems!$N$2:$N$179,MATCH($B49,Systems!$B$2:$B$179,0))*INDEX(Systems!$O$2:$O$179,MATCH($B49,Systems!$B$2:$B$179,0))*Assumptions!$C$5*24/52 -> 33230.769 | F49: =IFERROR(INDEX(Resources!$B$2:$B$64,MATCH($D49,Resources!$A$2:$A$64,0)),"?") -> BTU | G49: Weekly | H49: =E49*INDEX(Assumptions!$D$17:$D$23,MATCH(G49,Assumptions!$B$17:$B$23,0)) -> 33230.769 | I49: =IFERROR(INDEX(Systems!$R$2:$R$179,MATCH($B49,Systems!$B$2:$B$179,0)),0) -> 0 | J49: =H49*I49 -> 0 | K49: =IFERROR(IF(INDEX(Resources!$D$2:$D$64,MATCH($D49,Resources!$A$2:$A$64,0))="","",INDEX(Resources!$D$2:$D$64,MATCH($D49,Resources!$A$2:$A$64,0))),"") -> Cooled shelter | L49: =IF(K49="","",J49*INDEX(Resources!$E$2:$E$64,MATCH($D49,Resources!$A$2:$A$64,0))) -> 0 | M49: =B49&"|"&D49&"|"&C49 -> Camp 365 Off-Grid Camper|Cooling|Input | N49: Cooling load = area x heat-loss factor x CDD x 24 / 52.
A50: F0049 | B50: Camper Van | C50: Input | D50: Labor | E50: 1 | F50: =IFERROR(INDEX(Resources!$B$2:$B$64,MATCH($D50,Resources!$A$2:$A$64,0)),"?") -> hours | G50: Weekly | H50: =E50*INDEX(Assumptions!$D$17:$D$23,MATCH(G50,Assumptions!$B$17:$B$23,0)) -> 1 | I50: =IFERROR(INDEX(Systems!$R$2:$R$179,MATCH($B50,Systems!$B$2:$B$179,0)),0) -> 0 | J50: =H50*I50 -> 0 | K50: =IFERROR(IF(INDEX(Resources!$D$2:$D$64,MATCH($D50,Resources!$A$2:$A$64,0))="","",INDEX(Resources!$D$2:$D$64,MATCH($D50,Resources!$A$2:$A$64,0))),"") -> Est. Required Labor | L50: =IF(K50="","",J50*INDEX(Resources!$E$2:$E$64,MATCH($D50,Resources!$A$2:$A$64,0))) -> 0 | M50: =B50&"|"&D50&"|"&C50 -> Camper Van|Labor|Input | N50: Weekly upkeep hours (Systems column K).
A51: F0050 | B51: Camper Van | C51: Input | D51: Capital | E51: 40 | F51: =IFERROR(INDEX(Resources!$B$2:$B$64,MATCH($D51,Resources!$A$2:$A$64,0)),"?") -> $ | G51: Weekly | H51: =E51*INDEX(Assumptions!$D$17:$D$23,MATCH(G51,Assumptions!$B$17:$B$23,0)) -> 40 | I51: =IFERROR(INDEX(Systems!$R$2:$R$179,MATCH($B51,Systems!$B$2:$B$179,0)),0) -> 0 | J51: =H51*I51 -> 0 | K51: =IFERROR(IF(INDEX(Resources!$D$2:$D$64,MATCH($D51,Resources!$A$2:$A$64,0))="","",INDEX(Resources!$D$2:$D$64,MATCH($D51,Resources!$A$2:$A$64,0))),"") | L51: =IF(K51="","",J51*INDEX(Resources!$E$2:$E$64,MATCH($D51,Resources!$A$2:$A$64,0))) | M51: =B51&"|"&D51&"|"&C51 -> Camper Van|Capital|Input
A52: F0051 | B52: Camper Van | C52: Input | D52: Gasoline | E52: 12 | F52: =IFERROR(INDEX(Resources!$B$2:$B$64,MATCH($D52,Resources!$A$2:$A$64,0)),"?") -> gal | G52: Weekly | H52: =E52*INDEX(Assumptions!$D$17:$D$23,MATCH(G52,Assumptions!$B$17:$B$23,0)) -> 12 | I52: =IFERROR(INDEX(Systems!$R$2:$R$179,MATCH($B52,Systems!$B$2:$B$179,0)),0) -> 0 | J52: =H52*I52 -> 0 | K52: =IFERROR(IF(INDEX(Resources!$D$2:$D$64,MATCH($D52,Resources!$A$2:$A$64,0))="","",INDEX(Resources!$D$2:$D$64,MATCH($D52,Resources!$A$2:$A$64,0))),"") | L52: =IF(K52="","",J52*INDEX(Resources!$E$2:$E$64,MATCH($D52,Resources!$A$2:$A$64,0))) | M52: =B52&"|"&D52&"|"&C52 -> Camper Van|Gasoline|Input
A53: F0052 | B53: Camper Van | C53: Output | D53: Shelter | E53: 60 | F53: =IFERROR(INDEX(Resources!$B$2:$B$64,MATCH($D53,Resources!$A$2:$A$64,0)),"?") -> sq ft | G53: Capacity | H53: =E53*INDEX(Assumptions!$D$17:$D$23,MATCH(G53,Assumptions!$B$17:$B$23,0)) -> 60 | I53: =IFERROR(INDEX(Systems!$R$2:$R$179,MATCH($B53,Systems!$B$2:$B$179,0)),0) -> 0 | J53: =H53*I53 -> 0 | K53: =IFERROR(IF(INDEX(Resources!$D$2:$D$64,MATCH($D53,Resources!$A$2:$A$64,0))="","",INDEX(Resources!$D$2:$D$64,MATCH($D53,Resources!$A$2:$A$64,0))),"") -> Shelter | L53: =IF(K53="","",J53*INDEX(Resources!$E$2:$E$64,MATCH($D53,Resources!$A$2:$A$64,0))) -> 0 | M53: =B53&"|"&D53&"|"&C53 -> Camper Van|Shelter|Output
A54: F0053 | B54: Camper Van | C54: Output | D54: Transportation | E54: 200 | F54: =IFERROR(INDEX(Resources!$B$2:$B$64,MATCH($D54,Resources!$A$2:$A$64,0)),"?") -> miles | G54: Weekly | H54: =E54*INDEX(Assumptions!$D$17:$D$23,MATCH(G54,Assumptions!$B$17:$B$23,0)) -> 200 | I54: =IFERROR(INDEX(Systems!$R$2:$R$179,MATCH($B54,Systems!$B$2:$B$179,0)),0) -> 0 | J54: =H54*I54 -> 0 | K54: =IFERROR(IF(INDEX(Resources!$D$2:$D$64,MATCH($D54,Resources!$A$2:$A$64,0))="","",INDEX(Resources!$D$2:$D$64,MATCH($D54,Resources!$A$2:$A$64,0))),"") -> Transportation | L54: =IF(K54="","",J54*INDEX(Resources!$E$2:$E$64,MATCH($D54,Resources!$A$2:$A$64,0))) -> 0 | M54: =B54&"|"&D54&"|"&C54 -> Camper Van|Transportation|Output
A55: F0054 | B55: Camper Van | C55: Input | D55: Heat | E55: =INDEX(Systems!$N$2:$N$179,MATCH($B55,Systems!$B$2:$B$179,0))*INDEX(Systems!$O$2:$O$179,MATCH($B55,Systems!$B$2:$B$179,0))*Assumptions!$C$4*24/52 -> 132923.08 | F55: =IFERROR(INDEX(Resources!$B$2:$B$64,MATCH($D55,Resources!$A$2:$A$64,0)),"?") -> BTU | G55: Weekly | H55: =E55*INDEX(Assumptions!$D$17:$D$23,MATCH(G55,Assumptions!$B$17:$B$23,0)) -> 132923.08 | I55: =IFERROR(INDEX(Systems!$R$2:$R$179,MATCH($B55,Systems!$B$2:$B$179,0)),0) -> 0 | J55: =H55*I55 -> 0 | K55: =IFERROR(IF(INDEX(Resources!$D$2:$D$64,MATCH($D55,Resources!$A$2:$A$64,0))="","",INDEX(Resources!$D$2:$D$64,MATCH($D55,Resources!$A$2:$A$64,0))),"") -> Heated shelter | L55: =IF(K55="","",J55*INDEX(Resources!$E$2:$E$64,MATCH($D55,Resources!$A$2:$A$64,0))) -> 0 | M55: =B55&"|"&D55&"|"&C55 -> Camper Van|Heat|Input | N55: Heating load = area x heat-loss factor x HDD x 24 / 52.
A56: F0055 | B56: Camper Van | C56: Input | D56: Cooling | E56: =INDEX(Systems!$N$2:$N$179,MATCH($B56,Systems!$B$2:$B$179,0))*INDEX(Systems!$O$2:$O$179,MATCH($B56,Systems!$B$2:$B$179,0))*Assumptions!$C$5*24/52 -> 17723.077 | F56: =IFERROR(INDEX(Resources!$B$2:$B$64,MATCH($D56,Resources!$A$2:$A$64,0)),"?") -> BTU | G56: Weekly | H56: =E56*INDEX(Assumptions!$D$17:$D$23,MATCH(G56,Assumptions!$B$17:$B$23,0)) -> 17723.077 | I56: =IFERROR(INDEX(Systems!$R$2:$R$179,MATCH($B56,Systems!$B$2:$B$179,0)),0) -> 0 | J56: =H56*I56 -> 0 | K56: =IFERROR(IF(INDEX(Resources!$D$2:$D$64,MATCH($D56,Resources!$A$2:$A$64,0))="","",INDEX(Resources!$D$2:$D$64,MATCH($D56,Resources!$A$2:$A$64,0))),"") -> Cooled shelter | L56: =IF(K56="","",J56*INDEX(Resources!$E$2:$E$64,MATCH($D56,Resources!$A$2:$A$64,0))) -> 0 | M56: =B56&"|"&D56&"|"&C56 -> Camper Van|Cooling|Input | N56: Cooling load = area x heat-loss factor x CDD x 24 / 52.
A57: F0056 | B57: Green Biomass | C57: Input | D57: Labor | E57: 1.5 | F57: =IFERROR(INDEX(Resources!$B$2:$B$64,MATCH($D57,Resources!$A$2:$A$64,0)),"?") -> hours | G57: Weekly | H57: =E57*INDEX(Assumptions!$D$17:$D$23,MATCH(G57,Assumptions!$B$17:$B$23,0)) -> 1.5 | I57: =IFERROR(INDEX(Systems!$R$2:$R$179,MATCH($B57,Systems!$B$2:$B$179,0)),0) -> 0 | J57: =H57*I57 -> 0 | K57: =IFERROR(IF(INDEX(Resources!$D$2:$D$64,MATCH($D57,Resources!$A$2:$A$64,0))="","",INDEX(Resources!$D$2:$D$64,MATCH($D57,Resources!$A$2:$A$64,0))),"") -> Est. Required Labor | L57: =IF(K57="","",J57*INDEX(Resources!$E$2:$E$64,MATCH($D57,Resources!$A$2:$A$64,0))) -> 0 | M57: =B57&"|"&D57&"|"&C57 -> Green Biomass|Labor|Input | N57: Weekly upkeep hours (Systems column K).
A58: F0057 | B58: Green Biomass | C58: Input | D58: Water | E58: 125 | F58: =IFERROR(INDEX(Resources!$B$2:$B$64,MATCH($D58,Resources!$A$2:$A$64,0)),"?") -> gal | G58: Weekly | H58: =E58*INDEX(Assumptions!$D$17:$D$23,MATCH(G58,Assumptions!$B$17:$B$23,0)) -> 125 | I58: =IFERROR(INDEX(Systems!$R$2:$R$179,MATCH($B58,Systems!$B$2:$B$179,0)),0) -> 0 | J58: =H58*I58 -> 0 | K58: =IFERROR(IF(INDEX(Resources!$D$2:$D$64,MATCH($D58,Resources!$A$2:$A$64,0))="","",INDEX(Resources!$D$2:$D$64,MATCH($D58,Resources!$A$2:$A$64,0))),"") -> Water | L58: =IF(K58="","",J58*INDEX(Resources!$E$2:$E$64,MATCH($D58,Resources!$A$2:$A$64,0))) -> 0 | M58: =B58&"|"&D58&"|"&C58 -> Green Biomass|Water|Input
A59: F0058 | B59: Green Biomass | C59: Input | D59: Sunlight | E59: =Assumptions!$C$6*7 -> 35 | F59: =IFERROR(INDEX(Resources!$B$2:$B$64,MATCH($D59,Resources!$A$2:$A$64,0)),"?") -> sun-hours | G59: Weekly | H59: =E59*INDEX(Assumptions!$D$17:$D$23,MATCH(G59,Assumptions!$B$17:$B$23,0)) -> 35 | I59: =IFERROR(INDEX(Systems!$R$2:$R$179,MATCH($B59,Systems!$B$2:$B$179,0)),0) -> 0 | J59: =H59*I59 -> 0 | K59: =IFERROR(IF(INDEX(Resources!$D$2:$D$64,MATCH($D59,Resources!$A$2:$A$64,0))="","",INDEX(Resources!$D$2:$D$64,MATCH($D59,Resources!$A$2:$A$64,0))),"") | L59: =IF(K59="","",J59*INDEX(Resources!$E$2:$E$64,MATCH($D59,Resources!$A$2:$A$64,0))) | M59: =B59&"|"&D59&"|"&C59 -> Green Biomass|Sunlight|Input | N59: Sun-hours per week from Assumptions.
A60: F0059 | B60: Green Biomass | C60: Output | D60: Green biomass | E60: 15 | F60: =IFERROR(INDEX(Resources!$B$2:$B$64,MATCH($D60,Resources!$A$2:$A$64,0)),"?") -> lbs | G60: Weekly | H60: =E60*INDEX(Assumptions!$D$17:$D$23,MATCH(G60,Assumptions!$B$17:$B$23,0)) -> 15 | I60: =IFERROR(INDEX(Systems!$R$2:$R$179,MATCH($B60,Systems!$B$2:$B$179,0)),0) -> 0 | J60: =H60*I60 -> 0 | K60: =IFERROR(IF(INDEX(Resources!$D$2:$D$64,MATCH($D60,Resources!$A$2:$A$64,0))="","",INDEX(Resources!$D$2:$D$64,MATCH($D60,Resources!$A$2:$A$64,0))),"") | L60: =IF(K60="","",J60*INDEX(Resources!$E$2:$E$64,MATCH($D60,Resources!$A$2:$A$64,0))) | M60: =B60&"|"&D60&"|"&C60 -> Green Biomass|Green biomass|Output
A61: F0060 | B61: Woody Biomass | C61: Input | D61: Labor | E61: 3 | F61: =IFERROR(INDEX(Resources!$B$2:$B$64,MATCH($D61,Resources!$A$2:$A$64,0)),"?") -> hours | G61: Weekly | H61: =E61*INDEX(Assumptions!$D$17:$D$23,MATCH(G61,Assumptions!$B$17:$B$23,0)) -> 3 | I61: =IFERROR(INDEX(Systems!$R$2:$R$179,MATCH($B61,Systems!$B$2:$B$179,0)),0) -> 0 | J61: =H61*I61 -> 0 | K61: =IFERROR(IF(INDEX(Resources!$D$2:$D$64,MATCH($D61,Resources!$A$2:$A$64,0))="","",INDEX(Resources!$D$2:$D$64,MATCH($D61,Resources!$A$2:$A$64,0))),"") -> Est. Required Labor | L61: =IF(K61="","",J61*INDEX(Resources!$E$2:$E$64,MATCH($D61,Resources!$A$2:$A$64,0))) -> 0 | M61: =B61&"|"&D61&"|"&C61 -> Woody Biomass|Labor|Input | N61: Weekly upkeep hours (Systems column K).
A62: F0061 | B62: Woody Biomass | C62: Output | D62: Woody biomass | E62: 100 | F62: =IFERROR(INDEX(Resources!$B$2:$B$64,MATCH($D62,Resources!$A$2:$A$64,0)),"?") -> lbs | G62: Weekly | H62: =E62*INDEX(Assumptions!$D$17:$D$23,MATCH(G62,Assumptions!$B$17:$B$23,0)) -> 100 | I62: =IFERROR(INDEX(Systems!$R$2:$R$179,MATCH($B62,Systems!$B$2:$B$179,0)),0) -> 0 | J62: =H62*I62 -> 0 | K62: =IFERROR(IF(INDEX(Resources!$D$2:$D$64,MATCH($D62,Resources!$A$2:$A$64,0))="","",INDEX(Resources!$D$2:$D$64,MATCH($D62,Resources!$A$2:$A$64,0))),"") | L62: =IF(K62="","",J62*INDEX(Resources!$E$2:$E$64,MATCH($D62,Resources!$A$2:$A$64,0))) | M62: =B62&"|"&D62&"|"&C62 -> Woody Biomass|Woody biomass|Output
A63: F0062 | B63: Firepit | C63: Input | D63: Labor | E63: 0.5 | F63: =IFERROR(INDEX(Resources!$B$2:$B$64,MATCH($D63,Resources!$A$2:$A$64,0)),"?") -> hours | G63: Weekly | H63: =E63*INDEX(Assumptions!$D$17:$D$23,MATCH(G63,Assumptions!$B$17:$B$23,0)) -> 0.5 | I63: =IFERROR(INDEX(Systems!$R$2:$R$179,MATCH($B63,Systems!$B$2:$B$179,0)),0) -> 0 | J63: =H63*I63 -> 0 | K63: =IFERROR(IF(INDEX(Resources!$D$2:$D$64,MATCH($D63,Resources!$A$2:$A$64,0))="","",INDEX(Resources!$D$2:$D$64,MATCH($D63,Resources!$A$2:$A$64,0))),"") -> Est. Required Labor | L63: =IF(K63="","",J63*INDEX(Resources!$E$2:$E$64,MATCH($D63,Resources!$A$2:$A$64,0))) -> 0 | M63: =B63&"|"&D63&"|"&C63 -> Firepit|Labor|Input | N63: Weekly upkeep hours (Systems column K).
A64: F0063 | B64: Firepit | C64: Input | D64: Woody biomass | E64: 40 | F64: =IFERROR(INDEX(Resources!$B$2:$B$64,MATCH($D64,Resources!$A$2:$A$64,0)),"?") -> lbs | G64: Weekly | H64: =E64*INDEX(Assumptions!$D$17:$D$23,MATCH(G64,Assumptions!$B$17:$B$23,0)) -> 40 | I64: =IFERROR(INDEX(Systems!$R$2:$R$179,MATCH($B64,Systems!$B$2:$B$179,0)),0) -> 0 | J64: =H64*I64 -> 0 | K64: =IFERROR(IF(INDEX(Resources!$D$2:$D$64,MATCH($D64,Resources!$A$2:$A$64,0))="","",INDEX(Resources!$D$2:$D$64,MATCH($D64,Resources!$A$2:$A$64,0))),"") | L64: =IF(K64="","",J64*INDEX(Resources!$E$2:$E$64,MATCH($D64,Resources!$A$2:$A$64,0))) | M64: =B64&"|"&D64&"|"&C64 -> Firepit|Woody biomass|Input
A65: F0064 | B65: Firepit | C65: Output | D65: Cooking fuel | E65: 7 | F65: =IFERROR(INDEX(Resources!$B$2:$B$64,MATCH($D65,Resources!$A$2:$A$64,0)),"?") -> hours | G65: Weekly | H65: =E65*INDEX(Assumptions!$D$17:$D$23,MATCH(G65,Assumptions!$B$17:$B$23,0)) -> 7 | I65: =IFERROR(INDEX(Systems!$R$2:$R$179,MATCH($B65,Systems!$B$2:$B$179,0)),0) -> 0 | J65: =H65*I65 -> 0 | K65: =IFERROR(IF(INDEX(Resources!$D$2:$D$64,MATCH($D65,Resources!$A$2:$A$64,0))="","",INDEX(Resources!$D$2:$D$64,MATCH($D65,Resources!$A$2:$A$64,0))),"") -> Cooking fuel | L65: =IF(K65="","",J65*INDEX(Resources!$E$2:$E$64,MATCH($D65,Resources!$A$2:$A$64,0))) -> 0 | M65: =B65&"|"&D65&"|"&C65 -> Firepit|Cooking fuel|Output
A66: F0065 | B66: Firepit | C66: Output | D66: Heat | E66: 20000 | F66: =IFERROR(INDEX(Resources!$B$2:$B$64,MATCH($D66,Resources!$A$2:$A$64,0)),"?") -> BTU | G66: Weekly | H66: =E66*INDEX(Assumptions!$D$17:$D$23,MATCH(G66,Assumptions!$B$17:$B$23,0)) -> 20000 | I66: =IFERROR(INDEX(Systems!$R$2:$R$179,MATCH($B66,Systems!$B$2:$B$179,0)),0) -> 0 | J66: =H66*I66 -> 0 | K66: =IFERROR(IF(INDEX(Resources!$D$2:$D$64,MATCH($D66,Resources!$A$2:$A$64,0))="","",INDEX(Resources!$D$2:$D$64,MATCH($D66,Resources!$A$2:$A$64,0))),"") -> Heated shelter | L66: =IF(K66="","",J66*INDEX(Resources!$E$2:$E$64,MATCH($D66,Resources!$A$2:$A$64,0))) -> 0 | M66: =B66&"|"&D66&"|"&C66 -> Firepit|Heat|Output
A67: F0066 | B67: Firepit | C67: Output | D67: Wellbeing | E67: 5 | F67: =IFERROR(INDEX(Resources!$B$2:$B$64,MATCH($D67,Resources!$A$2:$A$64,0)),"?") -> points | G67: Weekly | H67: =E67*INDEX(Assumptions!$D$17:$D$23,MATCH(G67,Assumptions!$B$17:$B$23,0)) -> 5 | I67: =IFERROR(INDEX(Systems!$R$2:$R$179,MATCH($B67,Systems!$B$2:$B$179,0)),0) -> 0 | J67: =H67*I67 -> 0 | K67: =IFERROR(IF(INDEX(Resources!$D$2:$D$64,MATCH($D67,Resources!$A$2:$A$64,0))="","",INDEX(Resources!$D$2:$D$64,MATCH($D67,Resources!$A$2:$A$64,0))),"") | L67: =IF(K67="","",J67*INDEX(Resources!$E$2:$E$64,MATCH($D67,Resources!$A$2:$A$64,0))) | M67: =B67&"|"&D67&"|"&C67 -> Firepit|Wellbeing|Output
A68: F0067 | B68: Livestock Guardian Dog | C68: Input | D68: Labor | E68: 3.5 | F68: =IFERROR(INDEX(Resources!$B$2:$B$64,MATCH($D68,Resources!$A$2:$A$64,0)),"?") -> hours | G68: Weekly | H68: =E68*INDEX(Assumptions!$D$17:$D$23,MATCH(G68,Assumptions!$B$17:$B$23,0)) -> 3.5 | I68: =IFERROR(INDEX(Systems!$R$2:$R$179,MATCH($B68,Systems!$B$2:$B$179,0)),0) -> 0 | J68: =H68*I68 -> 0 | K68: =IFERROR(IF(INDEX(Resources!$D$2:$D$64,MATCH($D68,Resources!$A$2:$A$64,0))="","",INDEX(Resources!$D$2:$D$64,MATCH($D68,Resources!$A$2:$A$64,0))),"") -> Est. Required Labor | L68: =IF(K68="","",J68*INDEX(Resources!$E$2:$E$64,MATCH($D68,Resources!$A$2:$A$64,0))) -> 0 | M68: =B68&"|"&D68&"|"&C68 -> Livestock Guardian Dog|Labor|Input | N68: Weekly upkeep hours (Systems column K).
A69: F0068 | B69: Livestock Guardian Dog | C69: Input | D69: Water | E69: 7 | F69: =IFERROR(INDEX(Resources!$B$2:$B$64,MATCH($D69,Resources!$A$2:$A$64,0)),"?") -> gal | G69: Weekly | H69: =E69*INDEX(Assumptions!$D$17:$D$23,MATCH(G69,Assumptions!$B$17:$B$23,0)) -> 7 | I69: =IFERROR(INDEX(Systems!$R$2:$R$179,MATCH($B69,Systems!$B$2:$B$179,0)),0) -> 0 | J69: =H69*I69 -> 0 | K69: =IFERROR(IF(INDEX(Resources!$D$2:$D$64,MATCH($D69,Resources!$A$2:$A$64,0))="","",INDEX(Resources!$D$2:$D$64,MATCH($D69,Resources!$A$2:$A$64,0))),"") -> Water | L69: =IF(K69="","",J69*INDEX(Resources!$E$2:$E$64,MATCH($D69,Resources!$A$2:$A$64,0))) -> 0 | M69: =B69&"|"&D69&"|"&C69 -> Livestock Guardian Dog|Water|Input
A70: F0069 | B70: Livestock Guardian Dog | C70: Input | D70: Food | E70: 10500 | F70: =IFERROR(INDEX(Resources!$B$2:$B$64,MATCH($D70,Resources!$A$2:$A$64,0)),"?") -> kcal | G70: Weekly | H70: =E70*INDEX(Assumptions!$D$17:$D$23,MATCH(G70,Assumptions!$B$17:$B$23,0)) -> 10500 | I70: =IFERROR(INDEX(Systems!$R$2:$R$179,MATCH($B70,Systems!$B$2:$B$179,0)),0) -> 0 | J70: =H70*I70 -> 0 | K70: =IFERROR(IF(INDEX(Resources!$D$2:$D$64,MATCH($D70,Resources!$A$2:$A$64,0))="","",INDEX(Resources!$D$2:$D$64,MATCH($D70,Resources!$A$2:$A$64,0))),"") -> Food | L70: =IF(K70="","",J70*INDEX(Resources!$E$2:$E$64,MATCH($D70,Resources!$A$2:$A$64,0))) -> 0 | M70: =B70&"|"&D70&"|"&C70 -> Livestock Guardian Dog|Food|Input
A71: F0070 | B71: Livestock Guardian Dog | C71: Output | D71: Organic waste | E71: 7 | F71: =IFERROR(INDEX(Resources!$B$2:$B$64,MATCH($D71,Resources!$A$2:$A$64,0)),"?") -> lbs | G71: Weekly | H71: =E71*INDEX(Assumptions!$D$17:$D$23,MATCH(G71,Assumptions!$B$17:$B$23,0)) -> 7 | I71: =IFERROR(INDEX(Systems!$R$2:$R$179,MATCH($B71,Systems!$B$2:$B$179,0)),0) -> 0 | J71: =H71*I71 -> 0 | K71: =IFERROR(IF(INDEX(Resources!$D$2:$D$64,MATCH($D71,Resources!$A$2:$A$64,0))="","",INDEX(Resources!$D$2:$D$64,MATCH($D71,Resources!$A$2:$A$64,0))),"") | L71: =IF(K71="","",J71*INDEX(Resources!$E$2:$E$64,MATCH($D71,Resources!$A$2:$A$64,0))) | M71: =B71&"|"&D71&"|"&C71 -> Livestock Guardian Dog|Organic waste|Output
A72: F0071 | B72: Livestock Guardian Dog | C72: Output | D72: Wellbeing | E72: 10 | F72: =IFERROR(INDEX(Resources!$B$2:$B$64,MATCH($D72,Resources!$A$2:$A$64,0)),"?") -> points | G72: Weekly | H72: =E72*INDEX(Assumptions!$D$17:$D$23,MATCH(G72,Assumptions!$B$17:$B$23,0)) -> 10 | I72: =IFERROR(INDEX(Systems!$R$2:$R$179,MATCH($B72,Systems!$B$2:$B$179,0)),0) -> 0 | J72: =H72*I72 -> 0 | K72: =IFERROR(IF(INDEX(Resources!$D$2:$D$64,MATCH($D72,Resources!$A$2:$A$64,0))="","",INDEX(Resources!$D$2:$D$64,MATCH($D72,Resources!$A$2:$A$64,0))),"") | L72: =IF(K72="","",J72*INDEX(Resources!$E$2:$E$64,MATCH($D72,Resources!$A$2:$A$64,0))) | M72: =B72&"|"&D72&"|"&C72 -> Livestock Guardian Dog|Wellbeing|Output
A73: F0072 | B73: Livestock Guardian Dog | C73: Output | D73: Pest control | E73: 1 | F73: =IFERROR(INDEX(Resources!$B$2:$B$64,MATCH($D73,Resources!$A$2:$A$64,0)),"?") -> units | G73: Capacity | H73: =E73*INDEX(Assumptions!$D$17:$D$23,MATCH(G73,Assumptions!$B$17:$B$23,0)) -> 1 | I73: =IFERROR(INDEX(Systems!$R$2:$R$179,MATCH($B73,Systems!$B$2:$B$179,0)),0) -> 0 | J73: =H73*I73 -> 0 | K73: =IFERROR(IF(INDEX(Resources!$D$2:$D$64,MATCH($D73,Resources!$A$2:$A$64,0))="","",INDEX(Resources!$D$2:$D$64,MATCH($D73,Resources!$A$2:$A$64,0))),"") | L73: =IF(K73="","",J73*INDEX(Resources!$E$2:$E$64,MATCH($D73,Resources!$A$2:$A$64,0))) | M73: =B73&"|"&D73&"|"&C73 -> Livestock Guardian Dog|Pest control|Output
A74: F0073 | B74: Baby Chicks | C74: Input | D74: Labor | E74: 1 | F74: =IFERROR(INDEX(Resources!$B$2:$B$64,MATCH($D74,Resources!$A$2:$A$64,0)),"?") -> hours | G74: Weekly | H74: =E74*INDEX(Assumptions!$D$17:$D$23,MATCH(G74,Assumptions!$B$17:$B$23,0)) -> 1 | I74: =IFERROR(INDEX(Systems!$R$2:$R$179,MATCH($B74,Systems!$B$2:$B$179,0)),0) -> 0 | J74: =H74*I74 -> 0 | K74: =IFERROR(IF(INDEX(Resources!$D$2:$D$64,MATCH($D74,Resources!$A$2:$A$64,0))="","",INDEX(Resources!$D$2:$D$64,MATCH($D74,Resources!$A$2:$A$64,0))),"") -> Est. Required Labor | L74: =IF(K74="","",J74*INDEX(Resources!$E$2:$E$64,MATCH($D74,Resources!$A$2:$A$64,0))) -> 0 | M74: =B74&"|"&D74&"|"&C74 -> Baby Chicks|Labor|Input | N74: Weekly upkeep hours (Systems column K).
A75: F0074 | B75: Baby Chicks | C75: Input | D75: Water | E75: 2 | F75: =IFERROR(INDEX(Resources!$B$2:$B$64,MATCH($D75,Resources!$A$2:$A$64,0)),"?") -> gal | G75: Weekly | H75: =E75*INDEX(Assumptions!$D$17:$D$23,MATCH(G75,Assumptions!$B$17:$B$23,0)) -> 2 | I75: =IFERROR(INDEX(Systems!$R$2:$R$179,MATCH($B75,Systems!$B$2:$B$179,0)),0) -> 0 | J75: =H75*I75 -> 0 | K75: =IFERROR(IF(INDEX(Resources!$D$2:$D$64,MATCH($D75,Resources!$A$2:$A$64,0))="","",INDEX(Resources!$D$2:$D$64,MATCH($D75,Resources!$A$2:$A$64,0))),"") -> Water | L75: =IF(K75="","",J75*INDEX(Resources!$E$2:$E$64,MATCH($D75,Resources!$A$2:$A$64,0))) -> 0 | M75: =B75&"|"&D75&"|"&C75 -> Baby Chicks|Water|Input
A76: F0075 | B76: Baby Chicks | C76: Input | D76: Chicken feed | E76: 10 | F76: =IFERROR(INDEX(Resources!$B$2:$B$64,MATCH($D76,Resources!$A$2:$A$64,0)),"?") -> lbs | G76: Weekly | H76: =E76*INDEX(Assumptions!$D$17:$D$23,MATCH(G76,Assumptions!$B$17:$B$23,0)) -> 10 | I76: =IFERROR(INDEX(Systems!$R$2:$R$179,MATCH($B76,Systems!$B$2:$B$179,0)),0) -> 0 | J76: =H76*I76 -> 0 | K76: =IFERROR(IF(INDEX(Resources!$D$2:$D$64,MATCH($D76,Resources!$A$2:$A$64,0))="","",INDEX(Resources!$D$2:$D$64,MATCH($D76,Resources!$A$2:$A$64,0))),"") | L76: =IF(K76="","",J76*INDEX(Resources!$E$2:$E$64,MATCH($D76,Resources!$A$2:$A$64,0))) | M76: =B76&"|"&D76&"|"&C76 -> Baby Chicks|Chicken feed|Input
A77: F0076 | B77: Baby Chicks | C77: Output | D77: Manure | E77: 3 | F77: =IFERROR(INDEX(Resources!$B$2:$B$64,MATCH($D77,Resources!$A$2:$A$64,0)),"?") -> lbs | G77: Weekly | H77: =E77*INDEX(Assumptions!$D$17:$D$23,MATCH(G77,Assumptions!$B$17:$B$23,0)) -> 3 | I77: =IFERROR(INDEX(Systems!$R$2:$R$179,MATCH($B77,Systems!$B$2:$B$179,0)),0) -> 0 | J77: =H77*I77 -> 0 | K77: =IFERROR(IF(INDEX(Resources!$D$2:$D$64,MATCH($D77,Resources!$A$2:$A$64,0))="","",INDEX(Resources!$D$2:$D$64,MATCH($D77,Resources!$A$2:$A$64,0))),"") | L77: =IF(K77="","",J77*INDEX(Resources!$E$2:$E$64,MATCH($D77,Resources!$A$2:$A$64,0))) | M77: =B77&"|"&D77&"|"&C77 -> Baby Chicks|Manure|Output
A78: F0077 | B78: Beehive + Bee Colony | C78: Input | D78: Labor | E78: 0.5 | F78: =IFERROR(INDEX(Resources!$B$2:$B$64,MATCH($D78,Resources!$A$2:$A$64,0)),"?") -> hours | G78: Weekly | H78: =E78*INDEX(Assumptions!$D$17:$D$23,MATCH(G78,Assumptions!$B$17:$B$23,0)) -> 0.5 | I78: =IFERROR(INDEX(Systems!$R$2:$R$179,MATCH($B78,Systems!$B$2:$B$179,0)),0) -> 0 | J78: =H78*I78 -> 0 | K78: =IFERROR(IF(INDEX(Resources!$D$2:$D$64,MATCH($D78,Resources!$A$2:$A$64,0))="","",INDEX(Resources!$D$2:$D$64,MATCH($D78,Resources!$A$2:$A$64,0))),"") -> Est. Required Labor | L78: =IF(K78="","",J78*INDEX(Resources!$E$2:$E$64,MATCH($D78,Resources!$A$2:$A$64,0))) -> 0 | M78: =B78&"|"&D78&"|"&C78 -> Beehive + Bee Colony|Labor|Input | N78: Weekly upkeep hours (Systems column K).
A79: F0078 | B79: Beehive + Bee Colony | C79: Input | D79: Pollinator flowers | E79: 500 | F79: =IFERROR(INDEX(Resources!$B$2:$B$64,MATCH($D79,Resources!$A$2:$A$64,0)),"?") -> sq ft | G79: Capacity | H79: =E79*INDEX(Assumptions!$D$17:$D$23,MATCH(G79,Assumptions!$B$17:$B$23,0)) -> 500 | I79: =IFERROR(INDEX(Systems!$R$2:$R$179,MATCH($B79,Systems!$B$2:$B$179,0)),0) -> 0 | J79: =H79*I79 -> 0 | K79: =IFERROR(IF(INDEX(Resources!$D$2:$D$64,MATCH($D79,Resources!$A$2:$A$64,0))="","",INDEX(Resources!$D$2:$D$64,MATCH($D79,Resources!$A$2:$A$64,0))),"") | L79: =IF(K79="","",J79*INDEX(Resources!$E$2:$E$64,MATCH($D79,Resources!$A$2:$A$64,0))) | M79: =B79&"|"&D79&"|"&C79 -> Beehive + Bee Colony|Pollinator flowers|Input
A80: F0079 | B80: Beehive + Bee Colony | C80: Input | D80: Water | E80: 1.5 | F80: =IFERROR(INDEX(Resources!$B$2:$B$64,MATCH($D80,Resources!$A$2:$A$64,0)),"?") -> gal | G80: Weekly | H80: =E80*INDEX(Assumptions!$D$17:$D$23,MATCH(G80,Assumptions!$B$17:$B$23,0)) -> 1.5 | I80: =IFERROR(INDEX(Systems!$R$2:$R$179,MATCH($B80,Systems!$B$2:$B$179,0)),0) -> 0 | J80: =H80*I80 -> 0 | K80: =IFERROR(IF(INDEX(Resources!$D$2:$D$64,MATCH($D80,Resources!$A$2:$A$64,0))="","",INDEX(Resources!$D$2:$D$64,MATCH($D80,Resources!$A$2:$A$64,0))),"") -> Water | L80: =IF(K80="","",J80*INDEX(Resources!$E$2:$E$64,MATCH($D80,Resources!$A$2:$A$64,0))) -> 0 | M80: =B80&"|"&D80&"|"&C80 -> Beehive + Bee Colony|Water|Input
A81: F0080 | B81: Beehive + Bee Colony | C81: Output | D81: Honey | E81: 40 | F81: =IFERROR(INDEX(Resources!$B$2:$B$64,MATCH($D81,Resources!$A$2:$A$64,0)),"?") -> lbs | G81: Yearly | H81: =E81*INDEX(Assumptions!$D$17:$D$23,MATCH(G81,Assumptions!$B$17:$B$23,0)) -> 0.76923077 | I81: =IFERROR(INDEX(Systems!$R$2:$R$179,MATCH($B81,Systems!$B$2:$B$179,0)),0) -> 0 | J81: =H81*I81 -> 0 | K81: =IFERROR(IF(INDEX(Resources!$D$2:$D$64,MATCH($D81,Resources!$A$2:$A$64,0))="","",INDEX(Resources!$D$2:$D$64,MATCH($D81,Resources!$A$2:$A$64,0))),"") -> Food | L81: =IF(K81="","",J81*INDEX(Resources!$E$2:$E$64,MATCH($D81,Resources!$A$2:$A$64,0))) -> 0 | M81: =B81&"|"&D81&"|"&C81 -> Beehive + Bee Colony|Honey|Output
A82: F0081 | B82: Beehive + Bee Colony | C82: Output | D82: Pollination | E82: 4 | F82: =IFERROR(INDEX(Resources!$B$2:$B$64,MATCH($D82,Resources!$A$2:$A$64,0)),"?") -> units | G82: Capacity | H82: =E82*INDEX(Assumptions!$D$17:$D$23,MATCH(G82,Assumptions!$B$17:$B$23,0)) -> 4 | I82: =IFERROR(INDEX(Systems!$R$2:$R$179,MATCH($B82,Systems!$B$2:$B$179,0)),0) -> 0 | J82: =H82*I82 -> 0 | K82: =IFERROR(IF(INDEX(Resources!$D$2:$D$64,MATCH($D82,Resources!$A$2:$A$64,0))="","",INDEX(Resources!$D$2:$D$64,MATCH($D82,Resources!$A$2:$A$64,0))),"") | L82: =IF(K82="","",J82*INDEX(Resources!$E$2:$E$64,MATCH($D82,Resources!$A$2:$A$64,0))) | M82: =B82&"|"&D82&"|"&C82 -> Beehive + Bee Colony|Pollination|Output
A83: F0082 | B83: Black Soldier Fly Protopod (BSF) | C83: Input | D83: Labor | E83: 0.5 | F83: =IFERROR(INDEX(Resources!$B$2:$B$64,MATCH($D83,Resources!$A$2:$A$64,0)),"?") -> hours | G83: Weekly | H83: =E83*INDEX(Assumptions!$D$17:$D$23,MATCH(G83,Assumptions!$B$17:$B$23,0)) -> 0.5 | I83: =IFERROR(INDEX(Systems!$R$2:$R$179,MATCH($B83,Systems!$B$2:$B$179,0)),0) -> 0 | J83: =H83*I83 -> 0 | K83: =IFERROR(IF(INDEX(Resources!$D$2:$D$64,MATCH($D83,Resources!$A$2:$A$64,0))="","",INDEX(Resources!$D$2:$D$64,MATCH($D83,Resources!$A$2:$A$64,0))),"") -> Est. Required Labor | L83: =IF(K83="","",J83*INDEX(Resources!$E$2:$E$64,MATCH($D83,Resources!$A$2:$A$64,0))) -> 0 | M83: =B83&"|"&D83&"|"&C83 -> Black Soldier Fly Protopod (BSF)|Labor|Input | N83: Weekly upkeep hours (Systems column K).
A84: F0083 | B84: Black Soldier Fly Protopod (BSF) | C84: Input | D84: Coffee grounds | E84: 5 | F84: =IFERROR(INDEX(Resources!$B$2:$B$64,MATCH($D84,Resources!$A$2:$A$64,0)),"?") -> lbs | G84: Weekly | H84: =E84*INDEX(Assumptions!$D$17:$D$23,MATCH(G84,Assumptions!$B$17:$B$23,0)) -> 5 | I84: =IFERROR(INDEX(Systems!$R$2:$R$179,MATCH($B84,Systems!$B$2:$B$179,0)),0) -> 0 | J84: =H84*I84 -> 0 | K84: =IFERROR(IF(INDEX(Resources!$D$2:$D$64,MATCH($D84,Resources!$A$2:$A$64,0))="","",INDEX(Resources!$D$2:$D$64,MATCH($D84,Resources!$A$2:$A$64,0))),"") | L84: =IF(K84="","",J84*INDEX(Resources!$E$2:$E$64,MATCH($D84,Resources!$A$2:$A$64,0))) | M84: =B84&"|"&D84&"|"&C84 -> Black Soldier Fly Protopod (BSF)|Coffee grounds|Input
A85: F0084 | B85: Black Soldier Fly Protopod (BSF) | C85: Input | D85: Food waste | E85: 15 | F85: =IFERROR(INDEX(Resources!$B$2:$B$64,MATCH($D85,Resources!$A$2:$A$64,0)),"?") -> lbs | G85: Weekly | H85: =E85*INDEX(Assumptions!$D$17:$D$23,MATCH(G85,Assumptions!$B$17:$B$23,0)) -> 15 | I85: =IFERROR(INDEX(Systems!$R$2:$R$179,MATCH($B85,Systems!$B$2:$B$179,0)),0) -> 0 | J85: =H85*I85 -> 0 | K85: =IFERROR(IF(INDEX(Resources!$D$2:$D$64,MATCH($D85,Resources!$A$2:$A$64,0))="","",INDEX(Resources!$D$2:$D$64,MATCH($D85,Resources!$A$2:$A$64,0))),"") | L85: =IF(K85="","",J85*INDEX(Resources!$E$2:$E$64,MATCH($D85,Resources!$A$2:$A$64,0))) | M85: =B85&"|"&D85&"|"&C85 -> Black Soldier Fly Protopod (BSF)|Food waste|Input
A86: F0085 | B86: Black Soldier Fly Protopod (BSF) | C86: Output | D86: Manure | E86: 3 | F86: =IFERROR(INDEX(Resources!$B$2:$B$64,MATCH($D86,Resources!$A$2:$A$64,0)),"?") -> lbs | G86: Weekly | H86: =E86*INDEX(Assumptions!$D$17:$D$23,MATCH(G86,Assumptions!$B$17:$B$23,0)) -> 3 | I86: =IFERROR(INDEX(Systems!$R$2:$R$179,MATCH($B86,Systems!$B$2:$B$179,0)),0) -> 0 | J86: =H86*I86 -> 0 | K86: =IFERROR(IF(INDEX(Resources!$D$2:$D$64,MATCH($D86,Resources!$A$2:$A$64,0))="","",INDEX(Resources!$D$2:$D$64,MATCH($D86,Resources!$A$2:$A$64,0))),"") | L86: =IF(K86="","",J86*INDEX(Resources!$E$2:$E$64,MATCH($D86,Resources!$A$2:$A$64,0))) | M86: =B86&"|"&D86&"|"&C86 -> Black Soldier Fly Protopod (BSF)|Manure|Output
A87: F0086 | B87: Black Soldier Fly Protopod (BSF) | C87: Output | D87: Grubs | E87: 3 | F87: =IFERROR(INDEX(Resources!$B$2:$B$64,MATCH($D87,Resources!$A$2:$A$64,0)),"?") -> lbs | G87: Weekly | H87: =E87*INDEX(Assumptions!$D$17:$D$23,MATCH(G87,Assumptions!$B$17:$B$23,0)) -> 3 | I87: =IFERROR(INDEX(Systems!$R$2:$R$179,MATCH($B87,Systems!$B$2:$B$179,0)),0) -> 0 | J87: =H87*I87 -> 0 | K87: =IFERROR(IF(INDEX(Resources!$D$2:$D$64,MATCH($D87,Resources!$A$2:$A$64,0))="","",INDEX(Resources!$D$2:$D$64,MATCH($D87,Resources!$A$2:$A$64,0))),"") | L87: =IF(K87="","",J87*INDEX(Resources!$E$2:$E$64,MATCH($D87,Resources!$A$2:$A$64,0))) | M87: =B87&"|"&D87&"|"&C87 -> Black Soldier Fly Protopod (BSF)|Grubs|Output
A88: F0087 | B88: Chicken | C88: Input | D88: Labor | E88: 0.15 | F88: =IFERROR(INDEX(Resources!$B$2:$B$64,MATCH($D88,Resources!$A$2:$A$64,0)),"?") -> hours | G88: Weekly | H88: =E88*INDEX(Assumptions!$D$17:$D$23,MATCH(G88,Assumptions!$B$17:$B$23,0)) -> 0.15 | I88: =IFERROR(INDEX(Systems!$R$2:$R$179,MATCH($B88,Systems!$B$2:$B$179,0)),0) -> 0 | J88: =H88*I88 -> 0 | K88: =IFERROR(IF(INDEX(Resources!$D$2:$D$64,MATCH($D88,Resources!$A$2:$A$64,0))="","",INDEX(Resources!$D$2:$D$64,MATCH($D88,Resources!$A$2:$A$64,0))),"") -> Est. Required Labor | L88: =IF(K88="","",J88*INDEX(Resources!$E$2:$E$64,MATCH($D88,Resources!$A$2:$A$64,0))) -> 0 | M88: =B88&"|"&D88&"|"&C88 -> Chicken|Labor|Input | N88: Weekly upkeep hours (Systems column K).
A89: F0088 | B89: Chicken | C89: Input | D89: Green biomass | E89: 0.5 | F89: =IFERROR(INDEX(Resources!$B$2:$B$64,MATCH($D89,Resources!$A$2:$A$64,0)),"?") -> lbs | G89: Weekly | H89: =E89*INDEX(Assumptions!$D$17:$D$23,MATCH(G89,Assumptions!$B$17:$B$23,0)) -> 0.5 | I89: =IFERROR(INDEX(Systems!$R$2:$R$179,MATCH($B89,Systems!$B$2:$B$179,0)),0) -> 0 | J89: =H89*I89 -> 0 | K89: =IFERROR(IF(INDEX(Resources!$D$2:$D$64,MATCH($D89,Resources!$A$2:$A$64,0))="","",INDEX(Resources!$D$2:$D$64,MATCH($D89,Resources!$A$2:$A$64,0))),"") | L89: =IF(K89="","",J89*INDEX(Resources!$E$2:$E$64,MATCH($D89,Resources!$A$2:$A$64,0))) | M89: =B89&"|"&D89&"|"&C89 -> Chicken|Green biomass|Input
A90: F0089 | B90: Chicken | C90: Input | D90: Grubs | E90: 0.2 | F90: =IFERROR(INDEX(Resources!$B$2:$B$64,MATCH($D90,Resources!$A$2:$A$64,0)),"?") -> lbs | G90: Weekly | H90: =E90*INDEX(Assumptions!$D$17:$D$23,MATCH(G90,Assumptions!$B$17:$B$23,0)) -> 0.2 | I90: =IFERROR(INDEX(Systems!$R$2:$R$179,MATCH($B90,Systems!$B$2:$B$179,0)),0) -> 0 | J90: =H90*I90 -> 0 | K90: =IFERROR(IF(INDEX(Resources!$D$2:$D$64,MATCH($D90,Resources!$A$2:$A$64,0))="","",INDEX(Resources!$D$2:$D$64,MATCH($D90,Resources!$A$2:$A$64,0))),"") | L90: =IF(K90="","",J90*INDEX(Resources!$E$2:$E$64,MATCH($D90,Resources!$A$2:$A$64,0))) | M90: =B90&"|"&D90&"|"&C90 -> Chicken|Grubs|Input
A91: F0090 | B91: Chicken | C91: Input | D91: Food waste | E91: 0.3 | F91: =IFERROR(INDEX(Resources!$B$2:$B$64,MATCH($D91,Resources!$A$2:$A$64,0)),"?") -> lbs | G91: Weekly | H91: =E91*INDEX(Assumptions!$D$17:$D$23,MATCH(G91,Assumptions!$B$17:$B$23,0)) -> 0.3 | I91: =IFERROR(INDEX(Systems!$R$2:$R$179,MATCH($B91,Systems!$B$2:$B$179,0)),0) -> 0 | J91: =H91*I91 -> 0 | K91: =IFERROR(IF(INDEX(Resources!$D$2:$D$64,MATCH($D91,Resources!$A$2:$A$64,0))="","",INDEX(Resources!$D$2:$D$64,MATCH($D91,Resources!$A$2:$A$64,0))),"") | L91: =IF(K91="","",J91*INDEX(Resources!$E$2:$E$64,MATCH($D91,Resources!$A$2:$A$64,0))) | M91: =B91&"|"&D91&"|"&C91 -> Chicken|Food waste|Input
A92: F0091 | B92: Chicken | C92: Input | D92: Water | E92: 0.7 | F92: =IFERROR(INDEX(Resources!$B$2:$B$64,MATCH($D92,Resources!$A$2:$A$64,0)),"?") -> gal | G92: Weekly | H92: =E92*INDEX(Assumptions!$D$17:$D$23,MATCH(G92,Assumptions!$B$17:$B$23,0)) -> 0.7 | I92: =IFERROR(INDEX(Systems!$R$2:$R$179,MATCH($B92,Systems!$B$2:$B$179,0)),0) -> 0 | J92: =H92*I92 -> 0 | K92: =IFERROR(IF(INDEX(Resources!$D$2:$D$64,MATCH($D92,Resources!$A$2:$A$64,0))="","",INDEX(Resources!$D$2:$D$64,MATCH($D92,Resources!$A$2:$A$64,0))),"") -> Water | L92: =IF(K92="","",J92*INDEX(Resources!$E$2:$E$64,MATCH($D92,Resources!$A$2:$A$64,0))) -> 0 | M92: =B92&"|"&D92&"|"&C92 -> Chicken|Water|Input
A93: F0092 | B93: Chicken | C93: Input | D93: Chicken feed | E93: 1.5 | F93: =IFERROR(INDEX(Resources!$B$2:$B$64,MATCH($D93,Resources!$A$2:$A$64,0)),"?") -> lbs | G93: Weekly | H93: =E93*INDEX(Assumptions!$D$17:$D$23,MATCH(G93,Assumptions!$B$17:$B$23,0)) -> 1.5 | I93: =IFERROR(INDEX(Systems!$R$2:$R$179,MATCH($B93,Systems!$B$2:$B$179,0)),0) -> 0 | J93: =H93*I93 -> 0 | K93: =IFERROR(IF(INDEX(Resources!$D$2:$D$64,MATCH($D93,Resources!$A$2:$A$64,0))="","",INDEX(Resources!$D$2:$D$64,MATCH($D93,Resources!$A$2:$A$64,0))),"") | L93: =IF(K93="","",J93*INDEX(Resources!$E$2:$E$64,MATCH($D93,Resources!$A$2:$A$64,0))) | M93: =B93&"|"&D93&"|"&C93 -> Chicken|Chicken feed|Input
A94: F0093 | B94: Chicken | C94: Output | D94: Manure | E94: 1.5 | F94: =IFERROR(INDEX(Resources!$B$2:$B$64,MATCH($D94,Resources!$A$2:$A$64,0)),"?") -> lbs | G94: Weekly | H94: =E94*INDEX(Assumptions!$D$17:$D$23,MATCH(G94,Assumptions!$B$17:$B$23,0)) -> 1.5 | I94: =IFERROR(INDEX(Systems!$R$2:$R$179,MATCH($B94,Systems!$B$2:$B$179,0)),0) -> 0 | J94: =H94*I94 -> 0 | K94: =IFERROR(IF(INDEX(Resources!$D$2:$D$64,MATCH($D94,Resources!$A$2:$A$64,0))="","",INDEX(Resources!$D$2:$D$64,MATCH($D94,Resources!$A$2:$A$64,0))),"") | L94: =IF(K94="","",J94*INDEX(Resources!$E$2:$E$64,MATCH($D94,Resources!$A$2:$A$64,0))) | M94: =B94&"|"&D94&"|"&C94 -> Chicken|Manure|Output
A95: F0094 | B95: Chicken | C95: Output | D95: Eggs | E95: 4.5 | F95: =IFERROR(INDEX(Resources!$B$2:$B$64,MATCH($D95,Resources!$A$2:$A$64,0)),"?") -> eggs | G95: Weekly | H95: =E95*INDEX(Assumptions!$D$17:$D$23,MATCH(G95,Assumptions!$B$17:$B$23,0)) -> 4.5 | I95: =IFERROR(INDEX(Systems!$R$2:$R$179,MATCH($B95,Systems!$B$2:$B$179,0)),0) -> 0 | J95: =H95*I95 -> 0 | K95: =IFERROR(IF(INDEX(Resources!$D$2:$D$64,MATCH($D95,Resources!$A$2:$A$64,0))="","",INDEX(Resources!$D$2:$D$64,MATCH($D95,Resources!$A$2:$A$64,0))),"") -> Food | L95: =IF(K95="","",J95*INDEX(Resources!$E$2:$E$64,MATCH($D95,Resources!$A$2:$A$64,0))) -> 0 | M95: =B95&"|"&D95&"|"&C95 -> Chicken|Eggs|Output
A96: F0095 | B96: Aptera Electric Vehicle (Solar Charge) | C96: Input | D96: Labor | E96: 0.1 | F96: =IFERROR(INDEX(Resources!$B$2:$B$64,MATCH($D96,Resources!$A$2:$A$64,0)),"?") -> hours | G96: Weekly | H96: =E96*INDEX(Assumptions!$D$17:$D$23,MATCH(G96,Assumptions!$B$17:$B$23,0)) -> 0.1 | I96: =IFERROR(INDEX(Systems!$R$2:$R$179,MATCH($B96,Systems!$B$2:$B$179,0)),0) -> 0 | J96: =H96*I96 -> 0 | K96: =IFERROR(IF(INDEX(Resources!$D$2:$D$64,MATCH($D96,Resources!$A$2:$A$64,0))="","",INDEX(Resources!$D$2:$D$64,MATCH($D96,Resources!$A$2:$A$64,0))),"") -> Est. Required Labor | L96: =IF(K96="","",J96*INDEX(Resources!$E$2:$E$64,MATCH($D96,Resources!$A$2:$A$64,0))) -> 0 | M96: =B96&"|"&D96&"|"&C96 -> Aptera Electric Vehicle (Solar Charge)|Labor|Input | N96: Weekly upkeep hours (Systems column K).
A97: F0096 | B97: Aptera Electric Vehicle (Solar Charge) | C97: Input | D97: Sunlight | E97: =Assumptions!$C$6*7 -> 35 | F97: =IFERROR(INDEX(Resources!$B$2:$B$64,MATCH($D97,Resources!$A$2:$A$64,0)),"?") -> sun-hours | G97: Weekly | H97: =E97*INDEX(Assumptions!$D$17:$D$23,MATCH(G97,Assumptions!$B$17:$B$23,0)) -> 35 | I97: =IFERROR(INDEX(Systems!$R$2:$R$179,MATCH($B97,Systems!$B$2:$B$179,0)),0) -> 0 | J97: =H97*I97 -> 0 | K97: =IFERROR(IF(INDEX(Resources!$D$2:$D$64,MATCH($D97,Resources!$A$2:$A$64,0))="","",INDEX(Resources!$D$2:$D$64,MATCH($D97,Resources!$A$2:$A$64,0))),"") | L97: =IF(K97="","",J97*INDEX(Resources!$E$2:$E$64,MATCH($D97,Resources!$A$2:$A$64,0))) | M97: =B97&"|"&D97&"|"&C97 -> Aptera Electric Vehicle (Solar Charge)|Sunlight|Input | N97: Sun-hours per week from Assumptions.
A98: F0097 | B98: Aptera Electric Vehicle (Solar Charge) | C98: Input | D98: Capital | E98: 30 | F98: =IFERROR(INDEX(Resources!$B$2:$B$64,MATCH($D98,Resources!$A$2:$A$64,0)),"?") -> $ | G98: Weekly | H98: =E98*INDEX(Assumptions!$D$17:$D$23,MATCH(G98,Assumptions!$B$17:$B$23,0)) -> 30 | I98: =IFERROR(INDEX(Systems!$R$2:$R$179,MATCH($B98,Systems!$B$2:$B$179,0)),0) -> 0 | J98: =H98*I98 -> 0 | K98: =IFERROR(IF(INDEX(Resources!$D$2:$D$64,MATCH($D98,Resources!$A$2:$A$64,0))="","",INDEX(Resources!$D$2:$D$64,MATCH($D98,Resources!$A$2:$A$64,0))),"") | L98: =IF(K98="","",J98*INDEX(Resources!$E$2:$E$64,MATCH($D98,Resources!$A$2:$A$64,0))) | M98: =B98&"|"&D98&"|"&C98 -> Aptera Electric Vehicle (Solar Charge)|Capital|Input
A99: F0098 | B99: Aptera Electric Vehicle (Solar Charge) | C99: Input | D99: Electricity | E99: 10 | F99: =IFERROR(INDEX(Resources!$B$2:$B$64,MATCH($D99,Resources!$A$2:$A$64,0)),"?") -> kWh | G99: Weekly | H99: =E99*INDEX(Assumptions!$D$17:$D$23,MATCH(G99,Assumptions!$B$17:$B$23,0)) -> 10 | I99: =IFERROR(INDEX(Systems!$R$2:$R$179,MATCH($B99,Systems!$B$2:$B$179,0)),0) -> 0 | J99: =H99*I99 -> 0 | K99: =IFERROR(IF(INDEX(Resources!$D$2:$D$64,MATCH($D99,Resources!$A$2:$A$64,0))="","",INDEX(Resources!$D$2:$D$64,MATCH($D99,Resources!$A$2:$A$64,0))),"") -> Electricity | L99: =IF(K99="","",J99*INDEX(Resources!$E$2:$E$64,MATCH($D99,Resources!$A$2:$A$64,0))) -> 0 | M99: =B99&"|"&D99&"|"&C99 -> Aptera Electric Vehicle (Solar Charge)|Electricity|Input
A100: F0099 | B100: Aptera Electric Vehicle (Solar Charge) | C100: Output | D100: Transportation | E100: 200 | F100: =IFERROR(INDEX(Resources!$B$2:$B$64,MATCH($D100,Resources!$A$2:$A$64,0)),"?") -> miles | G100: Weekly | H100: =E100*INDEX(Assumptions!$D$17:$D$23,MATCH(G100,Assumptions!$B$17:$B$23,0)) -> 200 | I100: =IFERROR(INDEX(Systems!$R$2:$R$179,MATCH($B100,Systems!$B$2:$B$179,0)),0) -> 0 | J100: =H100*I100 -> 0 | K100: =IFERROR(IF(INDEX(Resources!$D$2:$D$64,MATCH($D100,Resources!$A$2:$A$64,0))="","",INDEX(Resources!$D$2:$D$64,MATCH($D100,Resources!$A$2:$A$64,0))),"") -> Transportation | L100: =IF(K100="","",J100*INDEX(Resources!$E$2:$E$64,MATCH($D100,Resources!$A$2:$A$64,0))) -> 0 | M100: =B100&"|"&D100&"|"&C100 -> Aptera Electric Vehicle (Solar Charge)|Transportation|Output
...

Sheet Resources
A1: Resource | B1: Unit | C1: Class | D1: Needs Checklist row | E1: Factor to checklist unit | F1: # systems producing | G1: # systems consuming | H1: Role in network | I1: Produced per week (design) | J1: Consumed per week (design) | K1: Net per week (design) | L1: Balance in design | M1: Notes
A2: Water | B2: gal | C2: Flow | D2: Water | E2: 1 | F2: =COUNTIFS(Flows!$D$2:$D$1500,$A2,Flows!$C$2:$C$1500,"Output") -> 10 | G2: =COUNTIFS(Flows!$D$2:$D$1500,$A2,Flows!$C$2:$C$1500,"Input") -> 54 | H2: =IF(C2="Ambient","Site-supplied",IF(AND(F2=0,G2=0),"Unused",IF(F2=0,"External source (no producer)",IF(G2=0,IF(D2<>"","Meets a human need","End product (no consumer)"),"Intermediate (made and used)")))) -> Intermediate (made and used) | I2: =SUMIFS(Flows!$J$2:$J$1500,Flows!$D$2:$D$1500,$A2,Flows!$C$2:$C$1500,"Output") -> 1000 | J2: =SUMIFS(Flows!$J$2:$J$1500,Flows!$D$2:$D$1500,$A2,Flows!$C$2:$C$1500,"Input") -> 151 | K2: =I2-J2 -> 849 | L2: =IF(C2="Ambient","Site-supplied",IF(AND(I2=0,J2=0),"Not in design",IF(K2<-0.0001*MAX(J2,1),"Deficit",IF(K2>0.0001*MAX(I2,1),"Surplus","Balanced")))) -> Surplus | M2: Non-potable household and irrigation water.
A3: Drinking water | B3: gal | C3: Flow | D3: Drinking water | E3: 1 | F3: =COUNTIFS(Flows!$D$2:$D$1500,$A3,Flows!$C$2:$C$1500,"Output") -> 8 | G3: =COUNTIFS(Flows!$D$2:$D$1500,$A3,Flows!$C$2:$C$1500,"Input") -> 1 | H3: =IF(C3="Ambient","Site-supplied",IF(AND(F3=0,G3=0),"Unused",IF(F3=0,"External source (no producer)",IF(G3=0,IF(D3<>"","Meets a human need","End product (no consumer)"),"Intermediate (made and used)")))) -> Intermediate (made and used) | I3: =SUMIFS(Flows!$J$2:$J$1500,Flows!$D$2:$D$1500,$A3,Flows!$C$2:$C$1500,"Output") -> 0 | J3: =SUMIFS(Flows!$J$2:$J$1500,Flows!$D$2:$D$1500,$A3,Flows!$C$2:$C$1500,"Input") -> 5 | K3: =I3-J3 -> -5 | L3: =IF(C3="Ambient","Site-supplied",IF(AND(I3=0,J3=0),"Not in design",IF(K3<-0.0001*MAX(J3,1),"Deficit",IF(K3>0.0001*MAX(I3,1),"Surplus","Balanced")))) -> Deficit | M3: Potable water for drinking and cooking.
A4: Hot water | B4: gal | C4: Flow | F4: =COUNTIFS(Flows!$D$2:$D$1500,$A4,Flows!$C$2:$C$1500,"Output") -> 3 | G4: =COUNTIFS(Flows!$D$2:$D$1500,$A4,Flows!$C$2:$C$1500,"Input") -> 1 | H4: =IF(C4="Ambient","Site-supplied",IF(AND(F4=0,G4=0),"Unused",IF(F4=0,"External source (no producer)",IF(G4=0,IF(D4<>"","Meets a human need","End product (no consumer)"),"Intermediate (made and used)")))) -> Intermediate (made and used) | I4: =SUMIFS(Flows!$J$2:$J$1500,Flows!$D$2:$D$1500,$A4,Flows!$C$2:$C$1500,"Output") -> 0 | J4: =SUMIFS(Flows!$J$2:$J$1500,Flows!$D$2:$D$1500,$A4,Flows!$C$2:$C$1500,"Input") -> 40 | K4: =I4-J4 -> -40 | L4: =IF(C4="Ambient","Site-supplied",IF(AND(I4=0,J4=0),"Not in design",IF(K4<-0.0001*MAX(J4,1),"Deficit",IF(K4>0.0001*MAX(I4,1),"Surplus","Balanced")))) -> Deficit | M4: Not a checklist row in the game; tracked in the balance only.
A5: Greywater | B5: gal | C5: Flow | F5: =COUNTIFS(Flows!$D$2:$D$1500,$A5,Flows!$C$2:$C$1500,"Output") -> 2 | G5: =COUNTIFS(Flows!$D$2:$D$1500,$A5,Flows!$C$2:$C$1500,"Input") -> 3 | H5: =IF(C5="Ambient","Site-supplied",IF(AND(F5=0,G5=0),"Unused",IF(F5=0,"External source (no producer)",IF(G5=0,IF(D5<>"","Meets a human need","End product (no consumer)"),"Intermediate (made and used)")))) -> Intermediate (made and used) | I5: =SUMIFS(Flows!$J$2:$J$1500,Flows!$D$2:$D$1500,$A5,Flows!$C$2:$C$1500,"Output") -> 100 | J5: =SUMIFS(Flows!$J$2:$J$1500,Flows!$D$2:$D$1500,$A5,Flows!$C$2:$C$1500,"Input") -> 0 | K5: =I5-J5 -> 100 | L5: =IF(C5="Ambient","Site-supplied",IF(AND(I5=0,J5=0),"Not in design",IF(K5<-0.0001*MAX(J5,1),"Deficit",IF(K5>0.0001*MAX(I5,1),"Surplus","Balanced")))) -> Surplus | M5: Used sink/shower/laundry water; reusable for irrigation.
A6: Food | B6: kcal | C6: Flow | D6: Food | E6: 1 | F6: =COUNTIFS(Flows!$D$2:$D$1500,$A6,Flows!$C$2:$C$1500,"Output") -> 3 | G6: =COUNTIFS(Flows!$D$2:$D$1500,$A6,Flows!$C$2:$C$1500,"Input") -> 6 | H6: =IF(C6="Ambient","Site-supplied",IF(AND(F6=0,G6=0),"Unused",IF(F6=0,"External source (no producer)",IF(G6=0,IF(D6<>"","Meets a human need","End product (no consumer)"),"Intermediate (made and used)")))) -> Intermediate (made and used) | I6: =SUMIFS(Flows!$J$2:$J$1500,Flows!$D$2:$D$1500,$A6,Flows!$C$2:$C$1500,"Output") -> 0 | J6: =SUMIFS(Flows!$J$2:$J$1500,Flows!$D$2:$D$1500,$A6,Flows!$C$2:$C$1500,"Input") -> 16000 | K6: =I6-J6 -> -16000 | L6: =IF(C6="Ambient","Site-supplied",IF(AND(I6=0,J6=0),"Not in design",IF(K6<-0.0001*MAX(J6,1),"Deficit",IF(K6>0.0001*MAX(I6,1),"Surplus","Balanced")))) -> Deficit | M6: Prepared or purchased food energy.
A7: Vegetables fruit fiber herbs | B7: lbs | C7: Flow | D7: Food | E7: 150 | F7: =COUNTIFS(Flows!$D$2:$D$1500,$A7,Flows!$C$2:$C$1500,"Output") -> 12 | G7: =COUNTIFS(Flows!$D$2:$D$1500,$A7,Flows!$C$2:$C$1500,"Input") -> 0 | H7: =IF(C7="Ambient","Site-supplied",IF(AND(F7=0,G7=0),"Unused",IF(F7=0,"External source (no producer)",IF(G7=0,IF(D7<>"","Meets a human need","End product (no consumer)"),"Intermediate (made and used)")))) -> Meets a human need | I7: =SUMIFS(Flows!$J$2:$J$1500,Flows!$D$2:$D$1500,$A7,Flows!$C$2:$C$1500,"Output") -> 0.34615385 | J7: =SUMIFS(Flows!$J$2:$J$1500,Flows!$D$2:$D$1500,$A7,Flows!$C$2:$C$1500,"Input") -> 0 | K7: =I7-J7 -> 0.34615385 | L7: =IF(C7="Ambient","Site-supplied",IF(AND(I7=0,J7=0),"Not in design",IF(K7<-0.0001*MAX(J7,1),"Deficit",IF(K7>0.0001*MAX(I7,1),"Surplus","Balanced")))) -> Surplus | M7: Blended produce ~150 kcal/lb (low confidence; greens ~100, fruit ~250).
A8: Root crops | B8: lbs | C8: Flow | D8: Food | E8: 350 | F8: =COUNTIFS(Flows!$D$2:$D$1500,$A8,Flows!$C$2:$C$1500,"Output") -> 1 | G8: =COUNTIFS(Flows!$D$2:$D$1500,$A8,Flows!$C$2:$C$1500,"Input") -> 1 | H8: =IF(C8="Ambient","Site-supplied",IF(AND(F8=0,G8=0),"Unused",IF(F8=0,"External source (no producer)",IF(G8=0,IF(D8<>"","Meets a human need","End product (no consumer)"),"Intermediate (made and used)")))) -> Intermediate (made and used) | I8: =SUMIFS(Flows!$J$2:$J$1500,Flows!$D$2:$D$1500,$A8,Flows!$C$2:$C$1500,"Output") -> 0 | J8: =SUMIFS(Flows!$J$2:$J$1500,Flows!$D$2:$D$1500,$A8,Flows!$C$2:$C$1500,"Input") -> 0 | K8: =I8-J8 -> 0 | L8: =IF(C8="Ambient","Site-supplied",IF(AND(I8=0,J8=0),"Not in design",IF(K8<-0.0001*MAX(J8,1),"Deficit",IF(K8>0.0001*MAX(I8,1),"Surplus","Balanced")))) -> Not in design | M8: Potatoes ~350 kcal/lb.
A9: Grain | B9: lbs | C9: Flow | D9: Food | E9: 1500 | F9: =COUNTIFS(Flows!$D$2:$D$1500,$A9,Flows!$C$2:$C$1500,"Output") -> 1 | G9: =COUNTIFS(Flows!$D$2:$D$1500,$A9,Flows!$C$2:$C$1500,"Input") -> 2 | H9: =IF(C9="Ambient","Site-supplied",IF(AND(F9=0,G9=0),"Unused",IF(F9=0,"External source (no producer)",IF(G9=0,IF(D9<>"","Meets a human need","End product (no consumer)"),"Intermediate (made and used)")))) -> Intermediate (made and used) | I9: =SUMIFS(Flows!$J$2:$J$1500,Flows!$D$2:$D$1500,$A9,Flows!$C$2:$C$1500,"Output") -> 0 | J9: =SUMIFS(Flows!$J$2:$J$1500,Flows!$D$2:$D$1500,$A9,Flows!$C$2:$C$1500,"Input") -> 0 | K9: =I9-J9 -> 0 | L9: =IF(C9="Ambient","Site-supplied",IF(AND(I9=0,J9=0),"Not in design",IF(K9<-0.0001*MAX(J9,1),"Deficit",IF(K9>0.0001*MAX(I9,1),"Surplus","Balanced")))) -> Not in design | M9: Whole wheat ~1,500 kcal/lb.
A10: Eggs | B10: eggs | C10: Flow | D10: Food | E10: 70 | F10: =COUNTIFS(Flows!$D$2:$D$1500,$A10,Flows!$C$2:$C$1500,"Output") -> 4 | G10: =COUNTIFS(Flows!$D$2:$D$1500,$A10,Flows!$C$2:$C$1500,"Input") -> 0 | H10: =IF(C10="Ambient","Site-supplied",IF(AND(F10=0,G10=0),"Unused",IF(F10=0,"External source (no producer)",IF(G10=0,IF(D10<>"","Meets a human need","End product (no consumer)"),"Intermediate (made and used)")))) -> Meets a human need | I10: =SUMIFS(Flows!$J$2:$J$1500,Flows!$D$2:$D$1500,$A10,Flows!$C$2:$C$1500,"Output") -> 55 | J10: =SUMIFS(Flows!$J$2:$J$1500,Flows!$D$2:$D$1500,$A10,Flows!$C$2:$C$1500,"Input") -> 0 | K10: =I10-J10 -> 55 | L10: =IF(C10="Ambient","Site-supplied",IF(AND(I10=0,J10=0),"Not in design",IF(K10<-0.0001*MAX(J10,1),"Deficit",IF(K10>0.0001*MAX(I10,1),"Surplus","Balanced")))) -> Surplus | M10: Large chicken egg ~70 kcal. Quail eggs entered as chicken-egg equivalents.
A11: Honey | B11: lbs | C11: Flow | D11: Food | E11: 1380 | F11: =COUNTIFS(Flows!$D$2:$D$1500,$A11,Flows!$C$2:$C$1500,"Output") -> 1 | G11: =COUNTIFS(Flows!$D$2:$D$1500,$A11,Flows!$C$2:$C$1500,"Input") -> 0 | H11: =IF(C11="Ambient","Site-supplied",IF(AND(F11=0,G11=0),"Unused",IF(F11=0,"External source (no producer)",IF(G11=0,IF(D11<>"","Meets a human need","End product (no consumer)"),"Intermediate (made and used)")))) -> Meets a human need | I11: =SUMIFS(Flows!$J$2:$J$1500,Flows!$D$2:$D$1500,$A11,Flows!$C$2:$C$1500,"Output") -> 0 | J11: =SUMIFS(Flows!$J$2:$J$1500,Flows!$D$2:$D$1500,$A11,Flows!$C$2:$C$1500,"Input") -> 0 | K11: =I11-J11 -> 0 | L11: =IF(C11="Ambient","Site-supplied",IF(AND(I11=0,J11=0),"Not in design",IF(K11<-0.0001*MAX(J11,1),"Deficit",IF(K11>0.0001*MAX(I11,1),"Surplus","Balanced")))) -> Not in design | M11: ~1,380 kcal/lb.
A12: Meat | B12: lbs | C12: Flow | D12: Food | E12: 900 | F12: =COUNTIFS(Flows!$D$2:$D$1500,$A12,Flows!$C$2:$C$1500,"Output") -> 4 | G12: =COUNTIFS(Flows!$D$2:$D$1500,$A12,Flows!$C$2:$C$1500,"Input") -> 0 | H12: =IF(C12="Ambient","Site-supplied",IF(AND(F12=0,G12=0),"Unused",IF(F12=0,"External source (no producer)",IF(G12=0,IF(D12<>"","Meets a human need","End product (no consumer)"),"Intermediate (made and used)")))) -> Meets a human need | I12: =SUMIFS(Flows!$J$2:$J$1500,Flows!$D$2:$D$1500,$A12,Flows!$C$2:$C$1500,"Output") -> 0 | J12: =SUMIFS(Flows!$J$2:$J$1500,Flows!$D$2:$D$1500,$A12,Flows!$C$2:$C$1500,"Input") -> 0 | K12: =I12-J12 -> 0 | L12: =IF(C12="Ambient","Site-supplied",IF(AND(I12=0,J12=0),"Not in design",IF(K12<-0.0001*MAX(J12,1),"Deficit",IF(K12>0.0001*MAX(I12,1),"Surplus","Balanced")))) -> Not in design | M12: Dressed poultry/rabbit/lamb blended ~900 kcal/lb.
A13: Milk | B13: gal | C13: Flow | D13: Food | E13: 2700 | F13: =COUNTIFS(Flows!$D$2:$D$1500,$A13,Flows!$C$2:$C$1500,"Output") -> 1 | G13: =COUNTIFS(Flows!$D$2:$D$1500,$A13,Flows!$C$2:$C$1500,"Input") -> 0 | H13: =IF(C13="Ambient","Site-supplied",IF(AND(F13=0,G13=0),"Unused",IF(F13=0,"External source (no producer)",IF(G13=0,IF(D13<>"","Meets a human need","End product (no consumer)"),"Intermediate (made and used)")))) -> Meets a human need | I13: =SUMIFS(Flows!$J$2:$J$1500,Flows!$D$2:$D$1500,$A13,Flows!$C$2:$C$1500,"Output") -> 0 | J13: =SUMIFS(Flows!$J$2:$J$1500,Flows!$D$2:$D$1500,$A13,Flows!$C$2:$C$1500,"Input") -> 0 | K13: =I13-J13 -> 0 | L13: =IF(C13="Ambient","Site-supplied",IF(AND(I13=0,J13=0),"Not in design",IF(K13<-0.0001*MAX(J13,1),"Deficit",IF(K13>0.0001*MAX(I13,1),"Surplus","Balanced")))) -> Not in design | M13: Whole goat milk ~2,700 kcal/gal.
A14: Fish | B14: lbs | C14: Flow | D14: Food | E14: 550 | F14: =COUNTIFS(Flows!$D$2:$D$1500,$A14,Flows!$C$2:$C$1500,"Output") -> 2 | G14: =COUNTIFS(Flows!$D$2:$D$1500,$A14,Flows!$C$2:$C$1500,"Input") -> 0 | H14: =IF(C14="Ambient","Site-supplied",IF(AND(F14=0,G14=0),"Unused",IF(F14=0,"External source (no producer)",IF(G14=0,IF(D14<>"","Meets a human need","End product (no consumer)"),"Intermediate (made and used)")))) -> Meets a human need | I14: =SUMIFS(Flows!$J$2:$J$1500,Flows!$D$2:$D$1500,$A14,Flows!$C$2:$C$1500,"Output") -> 0 | J14: =SUMIFS(Flows!$J$2:$J$1500,Flows!$D$2:$D$1500,$A14,Flows!$C$2:$C$1500,"Input") -> 0 | K14: =I14-J14 -> 0 | L14: =IF(C14="Ambient","Site-supplied",IF(AND(I14=0,J14=0),"Not in design",IF(K14<-0.0001*MAX(J14,1),"Deficit",IF(K14>0.0001*MAX(I14,1),"Surplus","Balanced")))) -> Not in design | M14: Tilapia/trout ~550 kcal/lb.
A15: Nuts | B15: lbs | C15: Flow | D15: Food | E15: 2800 | F15: =COUNTIFS(Flows!$D$2:$D$1500,$A15,Flows!$C$2:$C$1500,"Output") -> 3 | G15: =COUNTIFS(Flows!$D$2:$D$1500,$A15,Flows!$C$2:$C$1500,"Input") -> 0 | H15: =IF(C15="Ambient","Site-supplied",IF(AND(F15=0,G15=0),"Unused",IF(F15=0,"External source (no producer)",IF(G15=0,IF(D15<>"","Meets a human need","End product (no consumer)"),"Intermediate (made and used)")))) -> Meets a human need | I15: =SUMIFS(Flows!$J$2:$J$1500,Flows!$D$2:$D$1500,$A15,Flows!$C$2:$C$1500,"Output") -> 0.38461538 | J15: =SUMIFS(Flows!$J$2:$J$1500,Flows!$D$2:$D$1500,$A15,Flows!$C$2:$C$1500,"Input") -> 0 | K15: =I15-J15 -> 0.38461538 | L15: =IF(C15="Ambient","Site-supplied",IF(AND(I15=0,J15=0),"Not in design",IF(K15<-0.0001*MAX(J15,1),"Deficit",IF(K15>0.0001*MAX(I15,1),"Surplus","Balanced")))) -> Surplus | M15: Hazelnuts/acorn meal ~2,800 kcal/lb.
A16: Mushrooms | B16: lbs | C16: Flow | D16: Food | E16: 150 | F16: =COUNTIFS(Flows!$D$2:$D$1500,$A16,Flows!$C$2:$C$1500,"Output") -> 1 | G16: =COUNTIFS(Flows!$D$2:$D$1500,$A16,Flows!$C$2:$C$1500,"Input") -> 0 | H16: =IF(C16="Ambient","Site-supplied",IF(AND(F16=0,G16=0),"Unused",IF(F16=0,"External source (no producer)",IF(G16=0,IF(D16<>"","Meets a human need","End product (no consumer)"),"Intermediate (made and used)")))) -> Meets a human need | I16: =SUMIFS(Flows!$J$2:$J$1500,Flows!$D$2:$D$1500,$A16,Flows!$C$2:$C$1500,"Output") -> 0 | J16: =SUMIFS(Flows!$J$2:$J$1500,Flows!$D$2:$D$1500,$A16,Flows!$C$2:$C$1500,"Input") -> 0 | K16: =I16-J16 -> 0 | L16: =IF(C16="Ambient","Site-supplied",IF(AND(I16=0,J16=0),"Not in design",IF(K16<-0.0001*MAX(J16,1),"Deficit",IF(K16>0.0001*MAX(I16,1),"Surplus","Balanced")))) -> Not in design | M16: Fresh shiitake ~150 kcal/lb.
A17: Shelter | B17: sq ft | C17: Capacity | D17: Shelter | E17: 1 | F17: =COUNTIFS(Flows!$D$2:$D$1500,$A17,Flows!$C$2:$C$1500,"Output") -> 20 | G17: =COUNTIFS(Flows!$D$2:$D$1500,$A17,Flows!$C$2:$C$1500,"Input") -> 1 | H17: =IF(C17="Ambient","Site-supplied",IF(AND(F17=0,G17=0),"Unused",IF(F17=0,"External source (no producer)",IF(G17=0,IF(D17<>"","Meets a human need","End product (no consumer)"),"Intermediate (made and used)")))) -> Intermediate (made and used) | I17: =SUMIFS(Flows!$J$2:$J$1500,Flows!$D$2:$D$1500,$A17,Flows!$C$2:$C$1500,"Output") -> 210 | J17: =SUMIFS(Flows!$J$2:$J$1500,Flows!$D$2:$D$1500,$A17,Flows!$C$2:$C$1500,"Input") -> 200 | K17: =I17-J17 -> 10 | L17: =IF(C17="Ambient","Site-supplied",IF(AND(I17=0,J17=0),"Not in design",IF(K17<-0.0001*MAX(J17,1),"Deficit",IF(K17>0.0001*MAX(I17,1),"Surplus","Balanced")))) -> Surplus | M17: Living space. A capacity, not used up each week.
... A24: Labor | B24: hours | C24: Flow | D24: Est. Required Labor | E24: 1 | F24: =COUNTIFS(Flows!$D$2:$D$1500,$A24,Flows!$C$2:$C$1500,"Output") -> 1 | G24: =COUNTIFS(Flows!$D$2:$D$1500,$A24,Flows!$C$2:$C$1500,"Input") -> 156 | H24: =IF(C24="Ambient","Site-supplied",IF(AND(F24=0,G24=0),"Unused",IF(F24=0,"External source (no producer)",IF(G24=0,IF(D24<>"","Meets a human need","End product (no consumer)"),"Intermediate (made and used)")))) -> Intermediate (made and used) | I24: =SUMIFS(Flows!$J$2:$J$1500,Flows!$D$2:$D$1500,$A24,Flows!$C$2:$C$1500,"Output") -> 50 | J24: =SUMIFS(Flows!$J$2:$J$1500,Flows!$D$2:$D$1500,$A24,Flows!$C$2:$C$1500,"Input") -> 9.67 | K24: =I24-J24 -> 40.33 | L24: =IF(C24="Ambient","Site-supplied",IF(AND(I24=0,J24=0),"Not in design",IF(K24<-0.0001*MAX(J24,1),"Deficit",IF(K24>0.0001*MAX(I24,1),"Surplus","Balanced")))) -> Surplus | M24: Provided by Human Being; required by every system with upkeep.
A25: Capital | B25: $ | C25: Money | F25: =COUNTIFS(Flows!$D$2:$D$1500,$A25,Flows!$C$2:$C$1500,"Output") -> 3 | G25: =COUNTIFS(Flows!$D$2:$D$1500,$A25,Flows!$C$2:$C$1500,"Input") -> 20 | H25: =IF(C25="Ambient","Site-supplied",IF(AND(F25=0,G25=0),"Unused",IF(F25=0,"External source (no producer)",IF(G25=0,IF(D25<>"","Meets a human need","End product (no consumer)"),"Intermediate (made and used)")))) -> Intermediate (made and used) | I25: =SUMIFS(Flows!$J$2:$J$1500,Flows!$D$2:$D$1500,$A25,Flows!$C$2:$C$1500,"Output") -> 0 | J25: =SUMIFS(Flows!$J$2:$J$1500,Flows!$D$2:$D$1500,$A25,Flows!$C$2:$C$1500,"Input") -> 0 | K25: =I25-J25 -> 0 | L25: =IF(C25="Ambient","Site-supplied",IF(AND(I25=0,J25=0),"Not in design",IF(K25<-0.0001*MAX(J25,1),"Deficit",IF(K25>0.0001*MAX(I25,1),"Surplus","Balanced")))) -> Not in design | M25: Dollars. Produced by Average Job; spent by conventional systems.
A26: Sunlight | B26: sun-hours | C26: Ambient | F26: =COUNTIFS(Flows!$D$2:$D$1500,$A26,Flows!$C$2:$C$1500,"Output") -> 1 | G26: =COUNTIFS(Flows!$D$2:$D$1500,$A26,Flows!$C$2:$C$1500,"Input") -> 15 | H26: =IF(C26="Ambient","Site-supplied",IF(AND(F26=0,G26=0),"Unused",IF(F26=0,"External source (no producer)",IF(G26=0,IF(D26<>"","Meets a human need","End product (no consumer)"),"Intermediate (made and used)")))) -> Site-supplied | I26: =SUMIFS(Flows!$J$2:$J$1500,Flows!$D$2:$D$1500,$A26,Flows!$C$2:$C$1500,"Output") -> 35 | J26: =SUMIFS(Flows!$J$2:$J$1500,Flows!$D$2:$D$1500,$A26,Flows!$C$2:$C$1500,"Input") -> 35 | K26: =I26-J26 -> 0 | L26: =IF(C26="Ambient","Site-supplied",IF(AND(I26=0,J26=0),"Not in design",IF(K26<-0.0001*MAX(J26,1),"Deficit",IF(K26>0.0001*MAX(I26,1),"Surplus","Balanced")))) -> Site-supplied | M26: Site-supplied; not depleted by use. Set by Assumptions (peak sun hours).
A27: Rainfall | B27: inches | C27: Ambient | F27: =COUNTIFS(Flows!$D$2:$D$1500,$A27,Flows!$C$2:$C$1500,"Output") -> 1 | G27: =COUNTIFS(Flows!$D$2:$D$1500,$A27,Flows!$C$2:$C$1500,"Input") -> 5 | H27: =IF(C27="Ambient","Site-supplied",IF(AND(F27=0,G27=0),"Unused",IF(F27=0,"External source (no producer)",IF(G27=0,IF(D27<>"","Meets a human need","End product (no consumer)"),"Intermediate (made and used)")))) -> Site-supplied | I27: =SUMIFS(Flows!$J$2:$J$1500,Flows!$D$2:$D$1500,$A27,Flows!$C$2:$C$1500,"Output") -> 0.28846154 | J27: =SUMIFS(Flows!$J$2:$J$1500,Flows!$D$2:$D$1500,$A27,Flows!$C$2:$C$1500,"Input") -> 0 | K27: =I27-J27 -> 0.28846154 | L27: =IF(C27="Ambient","Site-supplied",IF(AND(I27=0,J27=0),"Not in design",IF(K27<-0.0001*MAX(J27,1),"Deficit",IF(K27>0.0001*MAX(I27,1),"Surplus","Balanced")))) -> Site-supplied | M27: Site-supplied. Set by Assumptions (annual precipitation).
A28: Wind | B28: hours | C28: Ambient | F28: =COUNTIFS(Flows!$D$2:$D$1500,$A28,Flows!$C$2:$C$1500,"Output") -> 1 | G28: =COUNTIFS(Flows!$D$2:$D$1500,$A28,Flows!$C$2:$C$1500,"Input") -> 1 | H28: =IF(C28="Ambient","Site-supplied",IF(AND(F28=0,G28=0),"Unused",IF(F28=0,"External source (no producer)",IF(G28=0,IF(D28<>"","Meets a human need","End product (no consumer)"),"Intermediate (made and used)")))) -> Site-supplied | I28: =SUMIFS(Flows!$J$2:$J$1500,Flows!$D$2:$D$1500,$A28,Flows!$C$2:$C$1500,"Output") -> 0 | J28: =SUMIFS(Flows!$J$2:$J$1500,Flows!$D$2:$D$1500,$A28,Flows!$C$2:$C$1500,"Input") -> 0 | K28: =I28-J28 -> 0 | L28: =IF(C28="Ambient","Site-supplied",IF(AND(I28=0,J28=0),"Not in design",IF(K28<-0.0001*MAX(J28,1),"Deficit",IF(K28>0.0001*MAX(I28,1),"Surplus","Balanced")))) -> Site-supplied | M28: Site-supplied hours of exposure; output set by wind capacity factor.
A29: Stream flow | B29: hours | C29: Ambient | F29: =COUNTIFS(Flows!$D$2:$D$1500,$A29,Flows!$C$2:$C$1500,"Output") -> 1 | G29: =COUNTIFS(Flows!$D$2:$D$1500,$A29,Flows!$C$2:$C$1500,"Input") -> 1 | H29: =IF(C29="Ambient","Site-supplied",IF(AND(F29=0,G29=0),"Unused",IF(F29=0,"External source (no producer)",IF(G29=0,IF(D29<>"","Meets a human need","End product (no consumer)"),"Intermediate (made and used)")))) -> Site-supplied | I29: =SUMIFS(Flows!$J$2:$J$1500,Flows!$D$2:$D$1500,$A29,Flows!$C$2:$C$1500,"Output") -> 0 | J29: =SUMIFS(Flows!$J$2:$J$1500,Flows!$D$2:$D$1500,$A29,Flows!$C$2:$C$1500,"Input") -> 0 | K29: =I29-J29 -> 0 | L29: =IF(C29="Ambient","Site-supplied",IF(AND(I29=0,J29=0),"Not in design",IF(K29<-0.0001*MAX(J29,1),"Deficit",IF(K29>0.0001*MAX(I29,1),"Surplus","Balanced")))) -> Site-supplied | M29: Site-supplied; only exists if the land has a stream.
A30: Roofing area | B30: sq ft | C30: Capacity | F30: =COUNTIFS(Flows!$D$2:$D$1500,$A30,Flows!$C$2:$C$1500,"Output") -> 16 | G30: =COUNTIFS(Flows!$D$2:$D$1500,$A30,Flows!$C$2:$C$1500,"Input") -> 1 | H30: =IF(C30="Ambient","Site-supplied",IF(AND(F30=0,G30=0),"Unused",IF(F30=0,"External source (no producer)",IF(G30=0,IF(D30<>"","Meets a human need","End product (no consumer)"),"Intermediate (made and used)")))) -> Intermediate (made and used) | I30: =SUMIFS(Flows!$J$2:$J$1500,Flows!$D$2:$D$1500,$A30,Flows!$C$2:$C$1500,"Output") -> 0 | J30: =SUMIFS(Flows!$J$2:$J$1500,Flows!$D$2:$D$1500,$A30,Flows!$C$2:$C$1500,"Input") -> 0 | K30: =I30-J30 -> 0 | L30: =IF(C30="Ambient","Site-supplied",IF(AND(I30=0,J30=0),"Not in design",IF(K30<-0.0001*MAX(J30,1),"Deficit",IF(K30>0.0001*MAX(I30,1),"Surplus","Balanced")))) -> Not in design | M30: Roof available to catch rain.
A31: Water storage | B31: gal | C31: Capacity | F31: =COUNTIFS(Flows!$D$2:$D$1500,$A31,Flows!$C$2:$C$1500,"Output") -> 6 | G31: =COUNTIFS(Flows!$D$2:$D$1500,$A31,Flows!$C$2:$C$1500,"Input") -> 0 | H31: =IF(C31="Ambient","Site-supplied",IF(AND(F31=0,G31=0),"Unused",IF(F31=0,"External source (no producer)",IF(G31=0,IF(D31<>"","Meets a human need","End product (no consumer)"),"Intermediate (made and used)")))) -> End product (no consumer) | I31: =SUMIFS(Flows!$J$2:$J$1500,Flows!$D$2:$D$1500,$A31,Flows!$C$2:$C$1500,"Output") -> 0 | J31: =SUMIFS(Flows!$J$2:$J$1500,Flows!$D$2:$D$1500,$A31,Flows!$C$2:$C$1500,"Input") -> 0 | K31: =I31-J31 -> 0 | L31: =IF(C31="Ambient","Site-supplied",IF(AND(I31=0,J31=0),"Not in design",IF(K31<-0.0001*MAX(J31,1),"Deficit",IF(K31>0.0001*MAX(I31,1),"Surplus","Balanced")))) -> Not in design | M31: Tank/pond volume. Design Summary turns it into days of autonomy.
A32: Battery storage | B32: kWh | C32: Capacity | F32: =COUNTIFS(Flows!$D$2:$D$1500,$A32,Flows!$C$2:$C$1500,"Output") -> 3 | G32: =COUNTIFS(Flows!$D$2:$D$1500,$A32,Flows!$C$2:$C$1500,"Input") -> 0 | H32: =IF(C32="Ambient","Site-supplied",IF(AND(F32=0,G32=0),"Unused",IF(F32=0,"External source (no producer)",IF(G32=0,IF(D32<>"","Meets a human need","End product (no consumer)"),"Intermediate (made and used)")))) -> End product (no consumer) | I32: =SUMIFS(Flows!$J$2:$J$1500,Flows!$D$2:$D$1500,$A32,Flows!$C$2:$C$1500,"Output") -> 0 | J32: =SUMIFS(Flows!$J$2:$J$1500,Flows!$D$2:$D$1500,$A32,Flows!$C$2:$C$1500,"Input") -> 0 | K32: =I32-J32 -> 0 | L32: =IF(C32="Ambient","Site-supplied",IF(AND(I32=0,J32=0),"Not in design",IF(K32<-0.0001*MAX(J32,1),"Deficit",IF(K32>0.0001*MAX(I32,1),"Surplus","Balanced")))) -> Not in design | M32: Usable battery capacity. Design Summary turns it into days of autonomy.
A33: Food storage | B33: cu ft | C33: Capacity | F33: =COUNTIFS(Flows!$D$2:$D$1500,$A33,Flows!$C$2:$C$1500,"Output") -> 5 | G33: =COUNTIFS(Flows!$D$2:$D$1500,$A33,Flows!$C$2:$C$1500,"Input") -> 0 | H33: =IF(C33="Ambient","Site-supplied",IF(AND(F33=0,G33=0),"Unused",IF(F33=0,"External source (no producer)",IF(G33=0,IF(D33<>"","Meets a human need","End product (no consumer)"),"Intermediate (made and used)")))) -> End product (no consumer) | I33: =SUMIFS(Flows!$J$2:$J$1500,Flows!$D$2:$D$1500,$A33,Flows!$C$2:$C$1500,"Output") -> 0 | J33: =SUMIFS(Flows!$J$2:$J$1500,Flows!$D$2:$D$1500,$A33,Flows!$C$2:$C$1500,"Input") -> 0 | K33: =I33-J33 -> 0 | L33: =IF(C33="Ambient","Site-supplied",IF(AND(I33=0,J33=0),"Not in design",IF(K33<-0.0001*MAX(J33,1),"Deficit",IF(K33>0.0001*MAX(I33,1),"Surplus","Balanced")))) -> Not in design | M33: Cellar, freezer, and shelf-stable storage.
A34: Storage space | B34: cu ft | C34: Capacity | F34: =COUNTIFS(Flows!$D$2:$D$1500,$A34,Flows!$C$2:$C$1500,"Output") -> 1 | G34: =COUNTIFS(Flows!$D$2:$D$1500,$A34,Flows!$C$2:$C$1500,"Input") -> 7 | H34: =IF(C34="Ambient","Site-supplied",IF(AND(F34=0,G34=0),"Unused",IF(F34=0,"External source (no producer)",IF(G34=0,IF(D34<>"","Meets a human need","End product (no consumer)"),"Intermediate (made and used)")))) -> Intermediate (made and used) | I34: =SUMIFS(Flows!$J$2:$J$1500,Flows!$D$2:$D$1500,$A34,Flows!$C$2:$C$1500,"Output") -> 0 | J34: =SUMIFS(Flows!$J$2:$J$1500,Flows!$D$2:$D$1500,$A34,Flows!$C$2:$C$1500,"Input") -> 15 | K34: =I34-J34 -> -15 | L34: =IF(C34="Ambient","Site-supplied",IF(AND(I34=0,J34=0),"Not in design",IF(K34<-0.0001*MAX(J34,1),"Deficit",IF(K34>0.0001*MAX(I34,1),"Surplus","Balanced")))) -> Deficit | M34: Shed/workshop space for tools and bikes.
A35: Land area | B35: sq ft | C35: Capacity | F35: =COUNTIFS(Flows!$D$2:$D$1500,$A35,Flows!$C$2:$C$1500,"Output") -> 3 | G35: =COUNTIFS(Flows!$D$2:$D$1500,$A35,Flows!$C$2:$C$1500,"Input") -> 0 | H35: =IF(C35="Ambient","Site-supplied",IF(AND(F35=0,G35=0),"Unused",IF(F35=0,"External source (no producer)",IF(G35=0,IF(D35<>"","Meets a human need","End product (no consumer)"),"Intermediate (made and used)")))) -> End product (no consumer) | I35: =SUMIFS(Flows!$J$2:$J$1500,Flows!$D$2:$D$1500,$A35,Flows!$C$2:$C$1500,"Output") -> 43560 | J35: =SUMIFS(Flows!$J$2:$J$1500,Flows!$D$2:$D$1500,$A35,Flows!$C$2:$C$1500,"Input") -> 0 | K35: =I35-J35 -> 43560 | L35: =IF(C35="Ambient","Site-supplied",IF(AND(I35=0,J35=0),"Not in design",IF(K35<-0.0001*MAX(J35,1),"Deficit",IF(K35>0.0001*MAX(I35,1),"Surplus","Balanced")))) -> Surplus | M35: Compared with system footprints on Design Summary.
A36: Fenced paddock | B36: sq ft | C36: Capacity | F36: =COUNTIFS(Flows!$D$2:$D$1500,$A36,Flows!$C$2:$C$1500,"Output") -> 1 | G36: =COUNTIFS(Flows!$D$2:$D$1500,$A36,Flows!$C$2:$C$1500,"Input") -> 3 | H36: =IF(C36="Ambient","Site-supplied",IF(AND(F36=0,G36=0),"Unused",IF(F36=0,"External source (no producer)",IF(G36=0,IF(D36<>"","Meets a human need","End product (no consumer)"),"Intermediate (made and used)")))) -> Intermediate (made and used) | I36: =SUMIFS(Flows!$J$2:$J$1500,Flows!$D$2:$D$1500,$A36,Flows!$C$2:$C$1500,"Output") -> 0 | J36: =SUMIFS(Flows!$J$2:$J$1500,Flows!$D$2:$D$1500,$A36,Flows!$C$2:$C$1500,"Input") -> 0 | K36: =I36-J36 -> 0 | L36: =IF(C36="Ambient","Site-supplied",IF(AND(I36=0,J36=0),"Not in design",IF(K36<-0.0001*MAX(J36,1),"Deficit",IF(K36>0.0001*MAX(I36,1),"Surplus","Balanced")))) -> Not in design | M36: Fenced grazing area for large livestock.
... A44: Carbon | B44: lbs | C44: Flow | F44: =COUNTIFS(Flows!$D$2:$D$1500,$A44,Flows!$C$2:$C$1500,"Output") -> 10 | G44: =COUNTIFS(Flows!$D$2:$D$1500,$A44,Flows!$C$2:$C$1500,"Input") -> 11 | H44: =IF(C44="Ambient","Site-supplied",IF(AND(F44=0,G44=0),"Unused",IF(F44=0,"External source (no producer)",IF(G44=0,IF(D44<>"","Meets a human need","End product (no consumer)"),"Intermediate (made and used)")))) -> Intermediate (made and used) | I44: =SUMIFS(Flows!$J$2:$J$1500,Flows!$D$2:$D$1500,$A44,Flows!$C$2:$C$1500,"Output") -> 1.3461538 | J44: =SUMIFS(Flows!$J$2:$J$1500,Flows!$D$2:$D$1500,$A44,Flows!$C$2:$C$1500,"Input") -> 40 | K44: =I44-J44 -> -38.653846 | L44: =IF(C44="Ambient","Site-supplied",IF(AND(I44=0,J44=0),"Not in design",IF(K44<-0.0001*MAX(J44,1),"Deficit",IF(K44>0.0001*MAX(I44,1),"Surplus","Balanced")))) -> Deficit | M44: Brown material: straw, leaves, sawdust, bran.
A45: Compost | B45: lbs | C45: Flow | F45: =COUNTIFS(Flows!$D$2:$D$1500,$A45,Flows!$C$2:$C$1500,"Output") -> 8 | G45: =COUNTIFS(Flows!$D$2:$D$1500,$A45,Flows!$C$2:$C$1500,"Input") -> 8 | H45: =IF(C45="Ambient","Site-supplied",IF(AND(F45=0,G45=0),"Unused",IF(F45=0,"External source (no producer)",IF(G45=0,IF(D45<>"","Meets a human need","End product (no consumer)"),"Intermediate (made and used)")))) -> Intermediate (made and used) | I45: =SUMIFS(Flows!$J$2:$J$1500,Flows!$D$2:$D$1500,$A45,Flows!$C$2:$C$1500,"Output") -> 30 | J45: =SUMIFS(Flows!$J$2:$J$1500,Flows!$D$2:$D$1500,$A45,Flows!$C$2:$C$1500,"Input") -> 0.48076923 | K45: =I45-J45 -> 29.519231 | L45: =IF(C45="Ambient","Site-supplied",IF(AND(I45=0,J45=0),"Not in design",IF(K45<-0.0001*MAX(J45,1),"Deficit",IF(K45>0.0001*MAX(I45,1),"Surplus","Balanced")))) -> Surplus
A46: Manure | B46: lbs | C46: Flow | F46: =COUNTIFS(Flows!$D$2:$D$1500,$A46,Flows!$C$2:$C$1500,"Output") -> 12 | G46: =COUNTIFS(Flows!$D$2:$D$1500,$A46,Flows!$C$2:$C$1500,"Input") -> 2 | H46: =IF(C46="Ambient","Site-supplied",IF(AND(F46=0,G46=0),"Unused",IF(F46=0,"External source (no producer)",IF(G46=0,IF(D46<>"","Meets a human need","End product (no consumer)"),"Intermediate (made and used)")))) -> Intermediate (made and used) | I46: =SUMIFS(Flows!$J$2:$J$1500,Flows!$D$2:$D$1500,$A46,Flows!$C$2:$C$1500,"Output") -> 18 | J46: =SUMIFS(Flows!$J$2:$J$1500,Flows!$D$2:$D$1500,$A46,Flows!$C$2:$C$1500,"Input") -> 0 | K46: =I46-J46 -> 18 | L46: =IF(C46="Ambient","Site-supplied",IF(AND(I46=0,J46=0),"Not in design",IF(K46<-0.0001*MAX(J46,1),"Deficit",IF(K46>0.0001*MAX(I46,1),"Surplus","Balanced")))) -> Surplus | M46: Animal manure and insect frass.
A47: Liquid fertilizer | B47: gal | C47: Flow | F47: =COUNTIFS(Flows!$D$2:$D$1500,$A47,Flows!$C$2:$C$1500,"Output") -> 6 | G47: =COUNTIFS(Flows!$D$2:$D$1500,$A47,Flows!$C$2:$C$1500,"Input") -> 2 | H47: =IF(C47="Ambient","Site-supplied",IF(AND(F47=0,G47=0),"Unused",IF(F47=0,"External source (no producer)",IF(G47=0,IF(D47<>"","Meets a human need","End product (no consumer)"),"Intermediate (made and used)")))) -> Intermediate (made and used) | I47: =SUMIFS(Flows!$J$2:$J$1500,Flows!$D$2:$D$1500,$A47,Flows!$C$2:$C$1500,"Output") -> 0 | J47: =SUMIFS(Flows!$J$2:$J$1500,Flows!$D$2:$D$1500,$A47,Flows!$C$2:$C$1500,"Input") -> 0.25 | K47: =I47-J47 -> -0.25 | L47: =IF(C47="Ambient","Site-supplied",IF(AND(I47=0,J47=0),"Not in design",IF(K47<-0.0001*MAX(J47,1),"Deficit",IF(K47>0.0001*MAX(I47,1),"Surplus","Balanced")))) -> Deficit | M47: Compost tea, digestate, diluted urine.
A48: Biochar | B48: lbs | C48: Flow | F48: =COUNTIFS(Flows!$D$2:$D$1500,$A48,Flows!$C$2:$C$1500,"Output") -> 4 | G48: =COUNTIFS(Flows!$D$2:$D$1500,$A48,Flows!$C$2:$C$1500,"Input") -> 1 | H48: =IF(C48="Ambient","Site-supplied",IF(AND(F48=0,G48=0),"Unused",IF(F48=0,"External source (no producer)",IF(G48=0,IF(D48<>"","Meets a human need","End product (no consumer)"),"Intermediate (made and used)")))) -> Intermediate (made and used) | I48: =SUMIFS(Flows!$J$2:$J$1500,Flows!$D$2:$D$1500,$A48,Flows!$C$2:$C$1500,"Output") -> 0 | J48: =SUMIFS(Flows!$J$2:$J$1500,Flows!$D$2:$D$1500,$A48,Flows!$C$2:$C$1500,"Input") -> 2 | K48: =I48-J48 -> -2 | L48: =IF(C48="Ambient","Site-supplied",IF(AND(I48=0,J48=0),"Not in design",IF(K48<-0.0001*MAX(J48,1),"Deficit",IF(K48>0.0001*MAX(I48,1),"Surplus","Balanced")))) -> Deficit
A49: Organic waste | B49: lbs | C49: Flow | F49: =COUNTIFS(Flows!$D$2:$D$1500,$A49,Flows!$C$2:$C$1500,"Output") -> 2 | G49: =COUNTIFS(Flows!$D$2:$D$1500,$A49,Flows!$C$2:$C$1500,"Input") -> 6 | H49: =IF(C49="Ambient","Site-supplied",IF(AND(F49=0,G49=0),"Unused",IF(F49=0,"External source (no producer)",IF(G49=0,IF(D49<>"","Meets a human need","End product (no consumer)"),"Intermediate (made and used)")))) -> Intermediate (made and used) | I49: =SUMIFS(Flows!$J$2:$J$1500,Flows!$D$2:$D$1500,$A49,Flows!$C$2:$C$1500,"Output") -> 17.5 | J49: =SUMIFS(Flows!$J$2:$J$1500,Flows!$D$2:$D$1500,$A49,Flows!$C$2:$C$1500,"Input") -> 35 | K49: =I49-J49 -> -17.5 | L49: =IF(C49="Ambient","Site-supplied",IF(AND(I49=0,J49=0),"Not in design",IF(K49<-0.0001*MAX(J49,1),"Deficit",IF(K49>0.0001*MAX(I49,1),"Surplus","Balanced")))) -> Deficit | M49: Human and pet waste needing sanitation.
A50: Food waste | B50: lbs | C50: Flow | F50: =COUNTIFS(Flows!$D$2:$D$1500,$A50,Flows!$C$2:$C$1500,"Output") -> 4 | G50: =COUNTIFS(Flows!$D$2:$D$1500,$A50,Flows!$C$2:$C$1500,"Input") -> 9 | H50: =IF(C50="Ambient","Site-supplied",IF(AND(F50=0,G50=0),"Unused",IF(F50=0,"External source (no producer)",IF(G50=0,IF(D50<>"","Meets a human need","End product (no consumer)"),"Intermediate (made and used)")))) -> Intermediate (made and used) | I50: =SUMIFS(Flows!$J$2:$J$1500,Flows!$D$2:$D$1500,$A50,Flows!$C$2:$C$1500,"Output") -> 3 | J50: =SUMIFS(Flows!$J$2:$J$1500,Flows!$D$2:$D$1500,$A50,Flows!$C$2:$C$1500,"Input") -> 3 | K50: =I50-J50 -> 0 | L50: =IF(C50="Ambient","Site-supplied",IF(AND(I50=0,J50=0),"Not in design",IF(K50<-0.0001*MAX(J50,1),"Deficit",IF(K50>0.0001*MAX(I50,1),"Surplus","Balanced")))) -> Balanced | M50: Kitchen scraps.
A51: Coffee grounds | B51: lbs | C51: Flow | F51: =COUNTIFS(Flows!$D$2:$D$1500,$A51,Flows!$C$2:$C$1500,"Output") -> 1 | G51: =COUNTIFS(Flows!$D$2:$D$1500,$A51,Flows!$C$2:$C$1500,"Input") -> 2 | H51: =IF(C51="Ambient","Site-supplied",IF(AND(F51=0,G51=0),"Unused",IF(F51=0,"External source (no producer)",IF(G51=0,IF(D51<>"","Meets a human need","End product (no consumer)"),"Intermediate (made and used)")))) -> Intermediate (made and used) | I51: =SUMIFS(Flows!$J$2:$J$1500,Flows!$D$2:$D$1500,$A51,Flows!$C$2:$C$1500,"Output") -> 0 | J51: =SUMIFS(Flows!$J$2:$J$1500,Flows!$D$2:$D$1500,$A51,Flows!$C$2:$C$1500,"Input") -> 0 | K51: =I51-J51 -> 0 | L51: =IF(C51="Ambient","Site-supplied",IF(AND(I51=0,J51=0),"Not in design",IF(K51<-0.0001*MAX(J51,1),"Deficit",IF(K51>0.0001*MAX(I51,1),"Surplus","Balanced")))) -> Not in design
A52: Chicken feed | B52: lbs | C52: Flow | F52: =COUNTIFS(Flows!$D$2:$D$1500,$A52,Flows!$C$2:$C$1500,"Output") -> 1 | G52: =COUNTIFS(Flows!$D$2:$D$1500,$A52,Flows!$C$2:$C$1500,"Input") -> 8 | H52: =IF(C52="Ambient","Site-supplied",IF(AND(F52=0,G52=0),"Unused",IF(F52=0,"External source (no producer)",IF(G52=0,IF(D52<>"","Meets a human need","End product (no consumer)"),"Intermediate (made and used)")))) -> Intermediate (made and used) | I52: =SUMIFS(Flows!$J$2:$J$1500,Flows!$D$2:$D$1500,$A52,Flows!$C$2:$C$1500,"Output") -> 0 | J52: =SUMIFS(Flows!$J$2:$J$1500,Flows!$D$2:$D$1500,$A52,Flows!$C$2:$C$1500,"Input") -> 18 | K52: =I52-J52 -> -18 | L52: =IF(C52="Ambient","Site-supplied",IF(AND(I52=0,J52=0),"Not in design",IF(K52<-0.0001*MAX(J52,1),"Deficit",IF(K52>0.0001*MAX(I52,1),"Surplus","Balanced")))) -> Deficit | M52: Bagged poultry/fish feed.
A53: Grubs | B53: lbs | C53: Flow | F53: =COUNTIFS(Flows!$D$2:$D$1500,$A53,Flows!$C$2:$C$1500,"Output") -> 2 | G53: =COUNTIFS(Flows!$D$2:$D$1500,$A53,Flows!$C$2:$C$1500,"Input") -> 4 | H53: =IF(C53="Ambient","Site-supplied",IF(AND(F53=0,G53=0),"Unused",IF(F53=0,"External source (no producer)",IF(G53=0,IF(D53<>"","Meets a human need","End product (no consumer)"),"Intermediate (made and used)")))) -> Intermediate (made and used) | I53: =SUMIFS(Flows!$J$2:$J$1500,Flows!$D$2:$D$1500,$A53,Flows!$C$2:$C$1500,"Output") -> 0 | J53: =SUMIFS(Flows!$J$2:$J$1500,Flows!$D$2:$D$1500,$A53,Flows!$C$2:$C$1500,"Input") -> 2 | K53: =I53-J53 -> -2 | L53: =IF(C53="Ambient","Site-supplied",IF(AND(I53=0,J53=0),"Not in design",IF(K53<-0.0001*MAX(J53,1),"Deficit",IF(K53>0.0001*MAX(I53,1),"Surplus","Balanced")))) -> Deficit | M53: Insect larvae (BSF, mealworms) fed to birds.
A54: Seeds | B54: oz | C54: Flow | F54: =COUNTIFS(Flows!$D$2:$D$1500,$A54,Flows!$C$2:$C$1500,"Output") -> 2 | G54: =COUNTIFS(Flows!$D$2:$D$1500,$A54,Flows!$C$2:$C$1500,"Input") -> 9 | H54: =IF(C54="Ambient","Site-supplied",IF(AND(F54=0,G54=0),"Unused",IF(F54=0,"External source (no producer)",IF(G54=0,IF(D54<>"","Meets a human need","End product (no consumer)"),"Intermediate (made and used)")))) -> Intermediate (made and used) | I54: =SUMIFS(Flows!$J$2:$J$1500,Flows!$D$2:$D$1500,$A54,Flows!$C$2:$C$1500,"Output") -> 0 | J54: =SUMIFS(Flows!$J$2:$J$1500,Flows!$D$2:$D$1500,$A54,Flows!$C$2:$C$1500,"Input") -> 0.0019230769 | K54: =I54-J54 -> -0.0019230769 | L54: =IF(C54="Ambient","Site-supplied",IF(AND(I54=0,J54=0),"Not in design",IF(K54<-0.0001*MAX(J54,1),"Deficit",IF(K54>0.0001*MAX(I54,1),"Surplus","Balanced")))) -> Deficit
A55: Seedlings | B55: plants | C55: Flow | F55: =COUNTIFS(Flows!$D$2:$D$1500,$A55,Flows!$C$2:$C$1500,"Output") -> 2 | G55: =COUNTIFS(Flows!$D$2:$D$1500,$A55,Flows!$C$2:$C$1500,"Input") -> 15 | H55: =IF(C55="Ambient","Site-supplied",IF(AND(F55=0,G55=0),"Unused",IF(F55=0,"External source (no producer)",IF(G55=0,IF(D55<>"","Meets a human need","End product (no consumer)"),"Intermediate (made and used)")))) -> Intermediate (made and used) | I55: =SUMIFS(Flows!$J$2:$J$1500,Flows!$D$2:$D$1500,$A55,Flows!$C$2:$C$1500,"Output") -> 0 | J55: =SUMIFS(Flows!$J$2:$J$1500,Flows!$D$2:$D$1500,$A55,Flows!$C$2:$C$1500,"Input") -> 0 | K55: =I55-J55 -> 0 | L55: =IF(C55="Ambient","Site-supplied",IF(AND(I55=0,J55=0),"Not in design",IF(K55<-0.0001*MAX(J55,1),"Deficit",IF(K55>0.0001*MAX(I55,1),"Surplus","Balanced")))) -> Not in design
A56: Soil | B56: cu ft | C56: Flow | F56: =COUNTIFS(Flows!$D$2:$D$1500,$A56,Flows!$C$2:$C$1500,"Output") -> 4 | G56: =COUNTIFS(Flows!$D$2:$D$1500,$A56,Flows!$C$2:$C$1500,"Input") -> 7 | H56: =IF(C56="Ambient","Site-supplied",IF(AND(F56=0,G56=0),"Unused",IF(F56=0,"External source (no producer)",IF(G56=0,IF(D56<>"","Meets a human need","End product (no consumer)"),"Intermediate (made and used)")))) -> Intermediate (made and used) | I56: =SUMIFS(Flows!$J$2:$J$1500,Flows!$D$2:$D$1500,$A56,Flows!$C$2:$C$1500,"Output") -> 0 | J56: =SUMIFS(Flows!$J$2:$J$1500,Flows!$D$2:$D$1500,$A56,Flows!$C$2:$C$1500,"Input") -> 0 | K56: =I56-J56 -> 0 | L56: =IF(C56="Ambient","Site-supplied",IF(AND(I56=0,J56=0),"Not in design",IF(K56<-0.0001*MAX(J56,1),"Deficit",IF(K56>0.0001*MAX(I56,1),"Surplus","Balanced")))) -> Not in design | M56: Prepared soil or building earth.
A57: Gasoline | B57: gal | C57: Flow | F57: =COUNTIFS(Flows!$D$2:$D$1500,$A57,Flows!$C$2:$C$1500,"Output") -> 1 | G57: =COUNTIFS(Flows!$D$2:$D$1500,$A57,Flows!$C$2:$C$1500,"Input") -> 5 | H57: =IF(C57="Ambient","Site-supplied",IF(AND(F57=0,G57=0),"Unused",IF(F57=0,"External source (no producer)",IF(G57=0,IF(D57<>"","Meets a human need","End product (no consumer)"),"Intermediate (made and used)")))) -> Intermediate (made and used) | I57: =SUMIFS(Flows!$J$2:$J$1500,Flows!$D$2:$D$1500,$A57,Flows!$C$2:$C$1500,"Output") -> 0 | J57: =SUMIFS(Flows!$J$2:$J$1500,Flows!$D$2:$D$1500,$A57,Flows!$C$2:$C$1500,"Input") -> 0 | K57: =I57-J57 -> 0 | L57: =IF(C57="Ambient","Site-supplied",IF(AND(I57=0,J57=0),"Not in design",IF(K57<-0.0001*MAX(J57,1),"Deficit",IF(K57>0.0001*MAX(I57,1),"Surplus","Balanced")))) -> Not in design
A58: Propane | B58: gal | C58: Flow | F58: =COUNTIFS(Flows!$D$2:$D$1500,$A58,Flows!$C$2:$C$1500,"Output") -> 1 | G58: =COUNTIFS(Flows!$D$2:$D$1500,$A58,Flows!$C$2:$C$1500,"Input") -> 3 | H58: =IF(C58="Ambient","Site-supplied",IF(AND(F58=0,G58=0),"Unused",IF(F58=0,"External source (no producer)",IF(G58=0,IF(D58<>"","Meets a human need","End product (no consumer)"),"Intermediate (made and used)")))) -> Intermediate (made and used) | I58: =SUMIFS(Flows!$J$2:$J$1500,Flows!$D$2:$D$1500,$A58,Flows!$C$2:$C$1500,"Output") -> 0 | J58: =SUMIFS(Flows!$J$2:$J$1500,Flows!$D$2:$D$1500,$A58,Flows!$C$2:$C$1500,"Input") -> 0 | K58: =I58-J58 -> 0 | L58: =IF(C58="Ambient","Site-supplied",IF(AND(I58=0,J58=0),"Not in design",IF(K58<-0.0001*MAX(J58,1),"Deficit",IF(K58>0.0001*MAX(I58,1),"Surplus","Balanced")))) -> Not in design | M58: ~91,500 BTU/gal.
A59: Wool | B59: lbs | C59: Flow | F59: =COUNTIFS(Flows!$D$2:$D$1500,$A59,Flows!$C$2:$C$1500,"Output") -> 1 | G59: =COUNTIFS(Flows!$D$2:$D$1500,$A59,Flows!$C$2:$C$1500,"Input") -> 0 | H59: =IF(C59="Ambient","Site-supplied",IF(AND(F59=0,G59=0),"Unused",IF(F59=0,"External source (no producer)",IF(G59=0,IF(D59<>"","Meets a human need","End product (no consumer)"),"Intermediate (made and used)")))) -> End product (no consumer) | I59: =SUMIFS(Flows!$J$2:$J$1500,Flows!$D$2:$D$1500,$A59,Flows!$C$2:$C$1500,"Output") -> 0 | J59: =SUMIFS(Flows!$J$2:$J$1500,Flows!$D$2:$D$1500,$A59,Flows!$C$2:$C$1500,"Input") -> 0 | K59: =I59-J59 -> 0 | L59: =IF(C59="Ambient","Site-supplied",IF(AND(I59=0,J59=0),"Not in design",IF(K59<-0.0001*MAX(J59,1),"Deficit",IF(K59>0.0001*MAX(I59,1),"Surplus","Balanced")))) -> Not in design | M59: End product; no consumer yet.
A60: Pollination | B60: units | C60: Service | F60: =COUNTIFS(Flows!$D$2:$D$1500,$A60,Flows!$C$2:$C$1500,"Output") -> 3 | G60: =COUNTIFS(Flows!$D$2:$D$1500,$A60,Flows!$C$2:$C$1500,"Input") -> 5 | H60: =IF(C60="Ambient","Site-supplied",IF(AND(F60=0,G60=0),"Unused",IF(F60=0,"External source (no producer)",IF(G60=0,IF(D60<>"","Meets a human need","End product (no consumer)"),"Intermediate (made and used)")))) -> Intermediate (made and used) | I60: =SUMIFS(Flows!$J$2:$J$1500,Flows!$D$2:$D$1500,$A60,Flows!$C$2:$C$1500,"Output") -> 0 | J60: =SUMIFS(Flows!$J$2:$J$1500,Flows!$D$2:$D$1500,$A60,Flows!$C$2:$C$1500,"Input") -> 0.1 | K60: =I60-J60 -> -0.1 | L60: =IF(C60="Ambient","Site-supplied",IF(AND(I60=0,J60=0),"Not in design",IF(K60<-0.0001*MAX(J60,1),"Deficit",IF(K60>0.0001*MAX(I60,1),"Surplus","Balanced")))) -> Deficit | M60: 1 unit ~ pollination for 1/4 acre.
A61: Pollinator flowers | B61: sq ft | C61: Service | F61: =COUNTIFS(Flows!$D$2:$D$1500,$A61,Flows!$C$2:$C$1500,"Output") -> 16 | G61: =COUNTIFS(Flows!$D$2:$D$1500,$A61,Flows!$C$2:$C$1500,"Input") -> 4 | H61: =IF(C61="Ambient","Site-supplied",IF(AND(F61=0,G61=0),"Unused",IF(F61=0,"External source (no producer)",IF(G61=0,IF(D61<>"","Meets a human need","End product (no consumer)"),"Intermediate (made and used)")))) -> Intermediate (made and used) | I61: =SUMIFS(Flows!$J$2:$J$1500,Flows!$D$2:$D$1500,$A61,Flows!$C$2:$C$1500,"Output") -> 0 | J61: =SUMIFS(Flows!$J$2:$J$1500,Flows!$D$2:$D$1500,$A61,Flows!$C$2:$C$1500,"Input") -> 0 | K61: =I61-J61 -> 0 | L61: =IF(C61="Ambient","Site-supplied",IF(AND(I61=0,J61=0),"Not in design",IF(K61<-0.0001*MAX(J61,1),"Deficit",IF(K61>0.0001*MAX(I61,1),"Surplus","Balanced")))) -> Not in design | M61: Area in bloom that supports pollinators.
A62: Pest control | B62: units | C62: Service | F62: =COUNTIFS(Flows!$D$2:$D$1500,$A62,Flows!$C$2:$C$1500,"Output") -> 9 | G62: =COUNTIFS(Flows!$D$2:$D$1500,$A62,Flows!$C$2:$C$1500,"Input") -> 3 | H62: =IF(C62="Ambient","Site-supplied",IF(AND(F62=0,G62=0),"Unused",IF(F62=0,"External source (no producer)",IF(G62=0,IF(D62<>"","Meets a human need","End product (no consumer)"),"Intermediate (made and used)")))) -> Intermediate (made and used) | I62: =SUMIFS(Flows!$J$2:$J$1500,Flows!$D$2:$D$1500,$A62,Flows!$C$2:$C$1500,"Output") -> 0.5 | J62: =SUMIFS(Flows!$J$2:$J$1500,Flows!$D$2:$D$1500,$A62,Flows!$C$2:$C$1500,"Input") -> 0.1 | K62: =I62-J62 -> 0.4 | L62: =IF(C62="Ambient","Site-supplied",IF(AND(I62=0,J62=0),"Not in design",IF(K62<-0.0001*MAX(J62,1),"Deficit",IF(K62>0.0001*MAX(I62,1),"Surplus","Balanced")))) -> Surplus | M62: Predator/insect pressure relief for crops.
A63: Wellbeing | B63: points | C63: Service | F63: =COUNTIFS(Flows!$D$2:$D$1500,$A63,Flows!$C$2:$C$1500,"Output") -> 36 | G63: =COUNTIFS(Flows!$D$2:$D$1500,$A63,Flows!$C$2:$C$1500,"Input") -> 0 | H63: =IF(C63="Ambient","Site-supplied",IF(AND(F63=0,G63=0),"Unused",IF(F63=0,"External source (no producer)",IF(G63=0,IF(D63<>"","Meets a human need","End product (no consumer)"),"Intermediate (made and used)")))) -> End product (no consumer) | I63: =SUMIFS(Flows!$J$2:$J$1500,Flows!$D$2:$D$1500,$A63,Flows!$C$2:$C$1500,"Output") -> 10 | J63: =SUMIFS(Flows!$J$2:$J$1500,Flows!$D$2:$D$1500,$A63,Flows!$C$2:$C$1500,"Input") -> 0 | K63: =I63-J63 -> 10 | L63: =IF(C63="Ambient","Site-supplied",IF(AND(I63=0,J63=0),"Not in design",IF(K63<-0.0001*MAX(J63,1),"Deficit",IF(K63>0.0001*MAX(I63,1),"Surplus","Balanced")))) -> Surplus | M63: Non-material benefit; game-style score.
A64: Preserved food | B64: kcal | C64: Flow | D64: Food | E64: 1 | F64: =COUNTIFS(Flows!$D$2:$D$1500,$A64,Flows!$C$2:$C$1500,"Output") -> 0 | G64: =COUNTIFS(Flows!$D$2:$D$1500,$A64,Flows!$C$2:$C$1500,"Input") -> 0 | H64: =IF(C64="Ambient","Site-supplied",IF(AND(F64=0,G64=0),"Unused",IF(F64=0,"External source (no producer)",IF(G64=0,IF(D64<>"","Meets a human need","End product (no consumer)"),"Intermediate (made and used)")))) -> Unused | I64: =SUMIFS(Flows!$J$2:$J$1500,Flows!$D$2:$D$1500,$A64,Flows!$C$2:$C$1500,"Output") -> 0 | J64: =SUMIFS(Flows!$J$2:$J$1500,Flows!$D$2:$D$1500,$A64,Flows!$C$2:$C$1500,"Input") -> 0 | K64: =I64-J64 -> 0 | L64: =IF(C64="Ambient","Site-supplied",IF(AND(I64=0,J64=0),"Not in design",IF(K64<-0.0001*MAX(J64,1),"Deficit",IF(K64>0.0001*MAX(I64,1),"Surplus","Balanced")))) -> Not in design | M64: Shelf-stable food energy after canning or drying. Processing consumes fresh food and loses some calories; not additional harvest.

Sheet Matrix
A1: System | B1: Water | C1: Drinking water | D1: Hot water | E1: Greywater | F1: Food | G1: Vegetables fruit fiber herbs | H1: Root crops | I1: Grain | J1: Eggs | K1: Honey | L1: Meat | M1: Milk | N1: Fish | O1: Nuts | P1: Mushrooms | Q1: Shelter | R1: Sanitation | S1: Electricity | T1: Transportation | U1: Cooking fuel | V1: Heat | W1: Cooling | X1: Labor | Y1: Capital | Z1: Sunlight | AA1: Rainfall | AB1: Wind | AC1: Stream flow | AD1: Roofing area | AE1: Water storage | AF1: Battery storage | AG1: Food storage | AH1: Storage space | AI1: Land area | AJ1: Fenced paddock | AK1: Nesting habitat | AL1: Woody biomass | AM1: Wood chips | AN1: Wood pellets | AO1: Waste lumber | AP1: Green biomass | AQ1: Hay | AR1: Carbon | AS1: Compost | AT1: Manure | AU1: Liquid fertilizer | AV1: Biochar | AW1: Organic waste | AX1: Food waste | AY1: Coffee grounds | AZ1: Chicken feed | BA1: Grubs | BB1: Seeds | BC1: Seedlings | BD1: Soil | BE1: Gasoline | BF1: Propane | BG1: Wool | BH1: Pollination | BI1: Pollinator flowers | BJ1: Pest control | BK1: Wellbeing
A2: =Systems!B2 -> 2kwh Lead Acid Battery | B2: =IF(COUNTIF(Flows!$M$2:$M$1500,$A2&"|"&B$1&"|Input"),IF(COUNTIF(Flows!$M$2:$M$1500,$A2&"|"&B$1&"|Output"),"I/O","IN"),IF(COUNTIF(Flows!$M$2:$M$1500,$A2&"|"&B$1&"|Output"),"OUT","")) | C2: =IF(COUNTIF(Flows!$M$2:$M$1500,$A2&"|"&C$1&"|Input"),IF(COUNTIF(Flows!$M$2:$M$1500,$A2&"|"&C$1&"|Output"),"I/O","IN"),IF(COUNTIF(Flows!$M$2:$M$1500,$A2&"|"&C$1&"|Output"),"OUT","")) | D2: =IF(COUNTIF(Flows!$M$2:$M$1500,$A2&"|"&D$1&"|Input"),IF(COUNTIF(Flows!$M$2:$M$1500,$A2&"|"&D$1&"|Output"),"I/O","IN"),IF(COUNTIF(Flows!$M$2:$M$1500,$A2&"|"&D$1&"|Output"),"OUT","")) | E2: =IF(COUNTIF(Flows!$M$2:$M$1500,$A2&"|"&E$1&"|Input"),IF(COUNTIF(Flows!$M$2:$M$1500,$A2&"|"&E$1&"|Output"),"I/O","IN"),IF(COUNTIF(Flows!$M$2:$M$1500,$A2&"|"&E$1&"|Output"),"OUT","")) | F2: =IF(COUNTIF(Flows!$M$2:$M$1500,$A2&"|"&F$1&"|Input"),IF(COUNTIF(Flows!$M$2:$M$1500,$A2&"|"&F$1&"|Output"),"I/O","IN"),IF(COUNTIF(Flows!$M$2:$M$1500,$A2&"|"&F$1&"|Output"),"OUT","")) | G2: =IF(COUNTIF(Flows!$M$2:$M$1500,$A2&"|"&G$1&"|Input"),IF(COUNTIF(Flows!$M$2:$M$1500,$A2&"|"&G$1&"|Output"),"I/O","IN"),IF(COUNTIF(Flows!$M$2:$M$1500,$A2&"|"&G$1&"|Output"),"OUT","")) | H2: =IF(COUNTIF(Flows!$M$2:$M$1500,$A2&"|"&H$1&"|Input"),IF(COUNTIF(Flows!$M$2:$M$1500,$A2&"|"&H$1&"|Output"),"I/O","IN"),IF(COUNTIF(Flows!$M$2:$M$1500,$A2&"|"&H$1&"|Output"),"OUT","")) | I2: =IF(COUNTIF(Flows!$M$2:$M$1500,$A2&"|"&I$1&"|Input"),IF(COUNTIF(Flows!$M$2:$M$1500,$A2&"|"&I$1&"|Output"),"I/O","IN"),IF(COUNTIF(Flows!$M$2:$M$1500,$A2&"|"&I$1&"|Output"),"OUT","")) | ... BK2: =IF(COUNTIF(Flows!$M$2:$M$1500,$A2&"|"&BK$1&"|Input"),IF(COUNTIF(Flows!$M$2:$M$1500,$A2&"|"&BK$1&"|Output"),"I/O","IN"),IF(COUNTIF(Flows!$M$2:$M$1500,$A2&"|"&BK$1&"|Output"),"OUT",""))
A3: =Systems!B3 -> 500W Photovoltaic Panels | B3: =IF(COUNTIF(Flows!$M$2:$M$1500,$A3&"|"&B$1&"|Input"),IF(COUNTIF(Flows!$M$2:$M$1500,$A3&"|"&B$1&"|Output"),"I/O","IN"),IF(COUNTIF(Flows!$M$2:$M$1500,$A3&"|"&B$1&"|Output"),"OUT","")) | C3: =IF(COUNTIF(Flows!$M$2:$M$1500,$A3&"|"&C$1&"|Input"),IF(COUNTIF(Flows!$M$2:$M$1500,$A3&"|"&C$1&"|Output"),"I/O","IN"),IF(COUNTIF(Flows!$M$2:$M$1500,$A3&"|"&C$1&"|Output"),"OUT","")) | D3: =IF(COUNTIF(Flows!$M$2:$M$1500,$A3&"|"&D$1&"|Input"),IF(COUNTIF(Flows!$M$2:$M$1500,$A3&"|"&D$1&"|Output"),"I/O","IN"),IF(COUNTIF(Flows!$M$2:$M$1500,$A3&"|"&D$1&"|Output"),"OUT","")) | E3: =IF(COUNTIF(Flows!$M$2:$M$1500,$A3&"|"&E$1&"|Input"),IF(COUNTIF(Flows!$M$2:$M$1500,$A3&"|"&E$1&"|Output"),"I/O","IN"),IF(COUNTIF(Flows!$M$2:$M$1500,$A3&"|"&E$1&"|Output"),"OUT","")) | F3: =IF(COUNTIF(Flows!$M$2:$M$1500,$A3&"|"&F$1&"|Input"),IF(COUNTIF(Flows!$M$2:$M$1500,$A3&"|"&F$1&"|Output"),"I/O","IN"),IF(COUNTIF(Flows!$M$2:$M$1500,$A3&"|"&F$1&"|Output"),"OUT","")) | G3: =IF(COUNTIF(Flows!$M$2:$M$1500,$A3&"|"&G$1&"|Input"),IF(COUNTIF(Flows!$M$2:$M$1500,$A3&"|"&G$1&"|Output"),"I/O","IN"),IF(COUNTIF(Flows!$M$2:$M$1500,$A3&"|"&G$1&"|Output"),"OUT","")) | H3: =IF(COUNTIF(Flows!$M$2:$M$1500,$A3&"|"&H$1&"|Input"),IF(COUNTIF(Flows!$M$2:$M$1500,$A3&"|"&H$1&"|Output"),"I/O","IN"),IF(COUNTIF(Flows!$M$2:$M$1500,$A3&"|"&H$1&"|Output"),"OUT","")) | I3: =IF(COUNTIF(Flows!$M$2:$M$1500,$A3&"|"&I$1&"|Input"),IF(COUNTIF(Flows!$M$2:$M$1500,$A3&"|"&I$1&"|Output"),"I/O","IN"),IF(COUNTIF(Flows!$M$2:$M$1500,$A3&"|"&I$1&"|Output"),"OUT","")) | ... BK3: =IF(COUNTIF(Flows!$M$2:$M$1500,$A3&"|"&BK$1&"|Input"),IF(COUNTIF(Flows!$M$2:$M$1500,$A3&"|"&BK$1&"|Output"),"I/O","IN"),IF(COUNTIF(Flows!$M$2:$M$1500,$A3&"|"&BK$1&"|Output"),"OUT",""))
A4: =Systems!B4 -> All Power Labs CHP | B4: =IF(COUNTIF(Flows!$M$2:$M$1500,$A4&"|"&B$1&"|Input"),IF(COUNTIF(Flows!$M$2:$M$1500,$A4&"|"&B$1&"|Output"),"I/O","IN"),IF(COUNTIF(Flows!$M$2:$M$1500,$A4&"|"&B$1&"|Output"),"OUT","")) | C4: =IF(COUNTIF(Flows!$M$2:$M$1500,$A4&"|"&C$1&"|Input"),IF(COUNTIF(Flows!$M$2:$M$1500,$A4&"|"&C$1&"|Output"),"I/O","IN"),IF(COUNTIF(Flows!$M$2:$M$1500,$A4&"|"&C$1&"|Output"),"OUT","")) | D4: =IF(COUNTIF(Flows!$M$2:$M$1500,$A4&"|"&D$1&"|Input"),IF(COUNTIF(Flows!$M$2:$M$1500,$A4&"|"&D$1&"|Output"),"I/O","IN"),IF(COUNTIF(Flows!$M$2:$M$1500,$A4&"|"&D$1&"|Output"),"OUT","")) | E4: =IF(COUNTIF(Flows!$M$2:$M$1500,$A4&"|"&E$1&"|Input"),IF(COUNTIF(Flows!$M$2:$M$1500,$A4&"|"&E$1&"|Output"),"I/O","IN"),IF(COUNTIF(Flows!$M$2:$M$1500,$A4&"|"&E$1&"|Output"),"OUT","")) | F4: =IF(COUNTIF(Flows!$M$2:$M$1500,$A4&"|"&F$1&"|Input"),IF(COUNTIF(Flows!$M$2:$M$1500,$A4&"|"&F$1&"|Output"),"I/O","IN"),IF(COUNTIF(Flows!$M$2:$M$1500,$A4&"|"&F$1&"|Output"),"OUT","")) | G4: =IF(COUNTIF(Flows!$M$2:$M$1500,$A4&"|"&G$1&"|Input"),IF(COUNTIF(Flows!$M$2:$M$1500,$A4&"|"&G$1&"|Output"),"I/O","IN"),IF(COUNTIF(Flows!$M$2:$M$1500,$A4&"|"&G$1&"|Output"),"OUT","")) | H4: =IF(COUNTIF(Flows!$M$2:$M$1500,$A4&"|"&H$1&"|Input"),IF(COUNTIF(Flows!$M$2:$M$1500,$A4&"|"&H$1&"|Output"),"I/O","IN"),IF(COUNTIF(Flows!$M$2:$M$1500,$A4&"|"&H$1&"|Output"),"OUT","")) | I4: =IF(COUNTIF(Flows!$M$2:$M$1500,$A4&"|"&I$1&"|Input"),IF(COUNTIF(Flows!$M$2:$M$1500,$A4&"|"&I$1&"|Output"),"I/O","IN"),IF(COUNTIF(Flows!$M$2:$M$1500,$A4&"|"&I$1&"|Output"),"OUT","")) | ... BK4: =IF(COUNTIF(Flows!$M$2:$M$1500,$A4&"|"&BK$1&"|Input"),IF(COUNTIF(Flows!$M$2:$M$1500,$A4&"|"&BK$1&"|Output"),"I/O","IN"),IF(COUNTIF(Flows!$M$2:$M$1500,$A4&"|"&BK$1&"|Output"),"OUT",""))
A5: =Systems!B5 -> Biochar | B5: =IF(COUNTIF(Flows!$M$2:$M$1500,$A5&"|"&B$1&"|Input"),IF(COUNTIF(Flows!$M$2:$M$1500,$A5&"|"&B$1&"|Output"),"I/O","IN"),IF(COUNTIF(Flows!$M$2:$M$1500,$A5&"|"&B$1&"|Output"),"OUT","")) -> IN | C5: =IF(COUNTIF(Flows!$M$2:$M$1500,$A5&"|"&C$1&"|Input"),IF(COUNTIF(Flows!$M$2:$M$1500,$A5&"|"&C$1&"|Output"),"I/O","IN"),IF(COUNTIF(Flows!$M$2:$M$1500,$A5&"|"&C$1&"|Output"),"OUT","")) | D5: =IF(COUNTIF(Flows!$M$2:$M$1500,$A5&"|"&D$1&"|Input"),IF(COUNTIF(Flows!$M$2:$M$1500,$A5&"|"&D$1&"|Output"),"I/O","IN"),IF(COUNTIF(Flows!$M$2:$M$1500,$A5&"|"&D$1&"|Output"),"OUT","")) | E5: =IF(COUNTIF(Flows!$M$2:$M$1500,$A5&"|"&E$1&"|Input"),IF(COUNTIF(Flows!$M$2:$M$1500,$A5&"|"&E$1&"|Output"),"I/O","IN"),IF(COUNTIF(Flows!$M$2:$M$1500,$A5&"|"&E$1&"|Output"),"OUT","")) | F5: =IF(COUNTIF(Flows!$M$2:$M$1500,$A5&"|"&F$1&"|Input"),IF(COUNTIF(Flows!$M$2:$M$1500,$A5&"|"&F$1&"|Output"),"I/O","IN"),IF(COUNTIF(Flows!$M$2:$M$1500,$A5&"|"&F$1&"|Output"),"OUT","")) | G5: =IF(COUNTIF(Flows!$M$2:$M$1500,$A5&"|"&G$1&"|Input"),IF(COUNTIF(Flows!$M$2:$M$1500,$A5&"|"&G$1&"|Output"),"I/O","IN"),IF(COUNTIF(Flows!$M$2:$M$1500,$A5&"|"&G$1&"|Output"),"OUT","")) | H5: =IF(COUNTIF(Flows!$M$2:$M$1500,$A5&"|"&H$1&"|Input"),IF(COUNTIF(Flows!$M$2:$M$1500,$A5&"|"&H$1&"|Output"),"I/O","IN"),IF(COUNTIF(Flows!$M$2:$M$1500,$A5&"|"&H$1&"|Output"),"OUT","")) | I5: =IF(COUNTIF(Flows!$M$2:$M$1500,$A5&"|"&I$1&"|Input"),IF(COUNTIF(Flows!$M$2:$M$1500,$A5&"|"&I$1&"|Output"),"I/O","IN"),IF(COUNTIF(Flows!$M$2:$M$1500,$A5&"|"&I$1&"|Output"),"OUT","")) | ... BK5: =IF(COUNTIF(Flows!$M$2:$M$1500,$A5&"|"&BK$1&"|Input"),IF(COUNTIF(Flows!$M$2:$M$1500,$A5&"|"&BK$1&"|Output"),"I/O","IN"),IF(COUNTIF(Flows!$M$2:$M$1500,$A5&"|"&BK$1&"|Output"),"OUT",""))
A6: =Systems!B6 -> Biochar Double Barrel Retort | B6: =IF(COUNTIF(Flows!$M$2:$M$1500,$A6&"|"&B$1&"|Input"),IF(COUNTIF(Flows!$M$2:$M$1500,$A6&"|"&B$1&"|Output"),"I/O","IN"),IF(COUNTIF(Flows!$M$2:$M$1500,$A6&"|"&B$1&"|Output"),"OUT","")) | C6: =IF(COUNTIF(Flows!$M$2:$M$1500,$A6&"|"&C$1&"|Input"),IF(COUNTIF(Flows!$M$2:$M$1500,$A6&"|"&C$1&"|Output"),"I/O","IN"),IF(COUNTIF(Flows!$M$2:$M$1500,$A6&"|"&C$1&"|Output"),"OUT","")) | D6: =IF(COUNTIF(Flows!$M$2:$M$1500,$A6&"|"&D$1&"|Input"),IF(COUNTIF(Flows!$M$2:$M$1500,$A6&"|"&D$1&"|Output"),"I/O","IN"),IF(COUNTIF(Flows!$M$2:$M$1500,$A6&"|"&D$1&"|Output"),"OUT","")) | E6: =IF(COUNTIF(Flows!$M$2:$M$1500,$A6&"|"&E$1&"|Input"),IF(COUNTIF(Flows!$M$2:$M$1500,$A6&"|"&E$1&"|Output"),"I/O","IN"),IF(COUNTIF(Flows!$M$2:$M$1500,$A6&"|"&E$1&"|Output"),"OUT","")) | F6: =IF(COUNTIF(Flows!$M$2:$M$1500,$A6&"|"&F$1&"|Input"),IF(COUNTIF(Flows!$M$2:$M$1500,$A6&"|"&F$1&"|Output"),"I/O","IN"),IF(COUNTIF(Flows!$M$2:$M$1500,$A6&"|"&F$1&"|Output"),"OUT","")) | G6: =IF(COUNTIF(Flows!$M$2:$M$1500,$A6&"|"&G$1&"|Input"),IF(COUNTIF(Flows!$M$2:$M$1500,$A6&"|"&G$1&"|Output"),"I/O","IN"),IF(COUNTIF(Flows!$M$2:$M$1500,$A6&"|"&G$1&"|Output"),"OUT","")) | H6: =IF(COUNTIF(Flows!$M$2:$M$1500,$A6&"|"&H$1&"|Input"),IF(COUNTIF(Flows!$M$2:$M$1500,$A6&"|"&H$1&"|Output"),"I/O","IN"),IF(COUNTIF(Flows!$M$2:$M$1500,$A6&"|"&H$1&"|Output"),"OUT","")) | I6: =IF(COUNTIF(Flows!$M$2:$M$1500,$A6&"|"&I$1&"|Input"),IF(COUNTIF(Flows!$M$2:$M$1500,$A6&"|"&I$1&"|Output"),"I/O","IN"),IF(COUNTIF(Flows!$M$2:$M$1500,$A6&"|"&I$1&"|Output"),"OUT","")) | ... BK6: =IF(COUNTIF(Flows!$M$2:$M$1500,$A6&"|"&BK$1&"|Input"),IF(COUNTIF(Flows!$M$2:$M$1500,$A6&"|"&BK$1&"|Output"),"I/O","IN"),IF(COUNTIF(Flows!$M$2:$M$1500,$A6&"|"&BK$1&"|Output"),"OUT",""))
A7: =Systems!B7 -> A-Frame House | B7: =IF(COUNTIF(Flows!$M$2:$M$1500,$A7&"|"&B$1&"|Input"),IF(COUNTIF(Flows!$M$2:$M$1500,$A7&"|"&B$1&"|Output"),"I/O","IN"),IF(COUNTIF(Flows!$M$2:$M$1500,$A7&"|"&B$1&"|Output"),"OUT","")) | C7: =IF(COUNTIF(Flows!$M$2:$M$1500,$A7&"|"&C$1&"|Input"),IF(COUNTIF(Flows!$M$2:$M$1500,$A7&"|"&C$1&"|Output"),"I/O","IN"),IF(COUNTIF(Flows!$M$2:$M$1500,$A7&"|"&C$1&"|Output"),"OUT","")) | D7: =IF(COUNTIF(Flows!$M$2:$M$1500,$A7&"|"&D$1&"|Input"),IF(COUNTIF(Flows!$M$2:$M$1500,$A7&"|"&D$1&"|Output"),"I/O","IN"),IF(COUNTIF(Flows!$M$2:$M$1500,$A7&"|"&D$1&"|Output"),"OUT","")) | E7: =IF(COUNTIF(Flows!$M$2:$M$1500,$A7&"|"&E$1&"|Input"),IF(COUNTIF(Flows!$M$2:$M$1500,$A7&"|"&E$1&"|Output"),"I/O","IN"),IF(COUNTIF(Flows!$M$2:$M$1500,$A7&"|"&E$1&"|Output"),"OUT","")) | F7: =IF(COUNTIF(Flows!$M$2:$M$1500,$A7&"|"&F$1&"|Input"),IF(COUNTIF(Flows!$M$2:$M$1500,$A7&"|"&F$1&"|Output"),"I/O","IN"),IF(COUNTIF(Flows!$M$2:$M$1500,$A7&"|"&F$1&"|Output"),"OUT","")) | G7: =IF(COUNTIF(Flows!$M$2:$M$1500,$A7&"|"&G$1&"|Input"),IF(COUNTIF(Flows!$M$2:$M$1500,$A7&"|"&G$1&"|Output"),"I/O","IN"),IF(COUNTIF(Flows!$M$2:$M$1500,$A7&"|"&G$1&"|Output"),"OUT","")) | H7: =IF(COUNTIF(Flows!$M$2:$M$1500,$A7&"|"&H$1&"|Input"),IF(COUNTIF(Flows!$M$2:$M$1500,$A7&"|"&H$1&"|Output"),"I/O","IN"),IF(COUNTIF(Flows!$M$2:$M$1500,$A7&"|"&H$1&"|Output"),"OUT","")) | I7: =IF(COUNTIF(Flows!$M$2:$M$1500,$A7&"|"&I$1&"|Input"),IF(COUNTIF(Flows!$M$2:$M$1500,$A7&"|"&I$1&"|Output"),"I/O","IN"),IF(COUNTIF(Flows!$M$2:$M$1500,$A7&"|"&I$1&"|Output"),"OUT","")) | ... BK7: =IF(COUNTIF(Flows!$M$2:$M$1500,$A7&"|"&BK$1&"|Input"),IF(COUNTIF(Flows!$M$2:$M$1500,$A7&"|"&BK$1&"|Output"),"I/O","IN"),IF(COUNTIF(Flows!$M$2:$M$1500,$A7&"|"&BK$1&"|Output"),"OUT",""))
A8: =Systems!B8 -> Average Suburban Home | B8: =IF(COUNTIF(Flows!$M$2:$M$1500,$A8&"|"&B$1&"|Input"),IF(COUNTIF(Flows!$M$2:$M$1500,$A8&"|"&B$1&"|Output"),"I/O","IN"),IF(COUNTIF(Flows!$M$2:$M$1500,$A8&"|"&B$1&"|Output"),"OUT","")) -> OUT | C8: =IF(COUNTIF(Flows!$M$2:$M$1500,$A8&"|"&C$1&"|Input"),IF(COUNTIF(Flows!$M$2:$M$1500,$A8&"|"&C$1&"|Output"),"I/O","IN"),IF(COUNTIF(Flows!$M$2:$M$1500,$A8&"|"&C$1&"|Output"),"OUT","")) -> OUT | D8: =IF(COUNTIF(Flows!$M$2:$M$1500,$A8&"|"&D$1&"|Input"),IF(COUNTIF(Flows!$M$2:$M$1500,$A8&"|"&D$1&"|Output"),"I/O","IN"),IF(COUNTIF(Flows!$M$2:$M$1500,$A8&"|"&D$1&"|Output"),"OUT","")) -> OUT | E8: =IF(COUNTIF(Flows!$M$2:$M$1500,$A8&"|"&E$1&"|Input"),IF(COUNTIF(Flows!$M$2:$M$1500,$A8&"|"&E$1&"|Output"),"I/O","IN"),IF(COUNTIF(Flows!$M$2:$M$1500,$A8&"|"&E$1&"|Output"),"OUT","")) | F8: =IF(COUNTIF(Flows!$M$2:$M$1500,$A8&"|"&F$1&"|Input"),IF(COUNTIF(Flows!$M$2:$M$1500,$A8&"|"&F$1&"|Output"),"I/O","IN"),IF(COUNTIF(Flows!$M$2:$M$1500,$A8&"|"&F$1&"|Output"),"OUT","")) | G8: =IF(COUNTIF(Flows!$M$2:$M$1500,$A8&"|"&G$1&"|Input"),IF(COUNTIF(Flows!$M$2:$M$1500,$A8&"|"&G$1&"|Output"),"I/O","IN"),IF(COUNTIF(Flows!$M$2:$M$1500,$A8&"|"&G$1&"|Output"),"OUT","")) | H8: =IF(COUNTIF(Flows!$M$2:$M$1500,$A8&"|"&H$1&"|Input"),IF(COUNTIF(Flows!$M$2:$M$1500,$A8&"|"&H$1&"|Output"),"I/O","IN"),IF(COUNTIF(Flows!$M$2:$M$1500,$A8&"|"&H$1&"|Output"),"OUT","")) | I8: =IF(COUNTIF(Flows!$M$2:$M$1500,$A8&"|"&I$1&"|Input"),IF(COUNTIF(Flows!$M$2:$M$1500,$A8&"|"&I$1&"|Output"),"I/O","IN"),IF(COUNTIF(Flows!$M$2:$M$1500,$A8&"|"&I$1&"|Output"),"OUT","")) | ... BK8: =IF(COUNTIF(Flows!$M$2:$M$1500,$A8&"|"&BK$1&"|Input"),IF(COUNTIF(Flows!$M$2:$M$1500,$A8&"|"&BK$1&"|Output"),"I/O","IN"),IF(COUNTIF(Flows!$M$2:$M$1500,$A8&"|"&BK$1&"|Output"),"OUT",""))
A9: =Systems!B9 -> Bell Tent | B9: =IF(COUNTIF(Flows!$M$2:$M$1500,$A9&"|"&B$1&"|Input"),IF(COUNTIF(Flows!$M$2:$M$1500,$A9&"|"&B$1&"|Output"),"I/O","IN"),IF(COUNTIF(Flows!$M$2:$M$1500,$A9&"|"&B$1&"|Output"),"OUT","")) | C9: =IF(COUNTIF(Flows!$M$2:$M$1500,$A9&"|"&C$1&"|Input"),IF(COUNTIF(Flows!$M$2:$M$1500,$A9&"|"&C$1&"|Output"),"I/O","IN"),IF(COUNTIF(Flows!$M$2:$M$1500,$A9&"|"&C$1&"|Output"),"OUT","")) | D9: =IF(COUNTIF(Flows!$M$2:$M$1500,$A9&"|"&D$1&"|Input"),IF(COUNTIF(Flows!$M$2:$M$1500,$A9&"|"&D$1&"|Output"),"I/O","IN"),IF(COUNTIF(Flows!$M$2:$M$1500,$A9&"|"&D$1&"|Output"),"OUT","")) | E9: =IF(COUNTIF(Flows!$M$2:$M$1500,$A9&"|"&E$1&"|Input"),IF(COUNTIF(Flows!$M$2:$M$1500,$A9&"|"&E$1&"|Output"),"I/O","IN"),IF(COUNTIF(Flows!$M$2:$M$1500,$A9&"|"&E$1&"|Output"),"OUT","")) | F9: =IF(COUNTIF(Flows!$M$2:$M$1500,$A9&"|"&F$1&"|Input"),IF(COUNTIF(Flows!$M$2:$M$1500,$A9&"|"&F$1&"|Output"),"I/O","IN"),IF(COUNTIF(Flows!$M$2:$M$1500,$A9&"|"&F$1&"|Output"),"OUT","")) | G9: =IF(COUNTIF(Flows!$M$2:$M$1500,$A9&"|"&G$1&"|Input"),IF(COUNTIF(Flows!$M$2:$M$1500,$A9&"|"&G$1&"|Output"),"I/O","IN"),IF(COUNTIF(Flows!$M$2:$M$1500,$A9&"|"&G$1&"|Output"),"OUT","")) | H9: =IF(COUNTIF(Flows!$M$2:$M$1500,$A9&"|"&H$1&"|Input"),IF(COUNTIF(Flows!$M$2:$M$1500,$A9&"|"&H$1&"|Output"),"I/O","IN"),IF(COUNTIF(Flows!$M$2:$M$1500,$A9&"|"&H$1&"|Output"),"OUT","")) | I9: =IF(COUNTIF(Flows!$M$2:$M$1500,$A9&"|"&I$1&"|Input"),IF(COUNTIF(Flows!$M$2:$M$1500,$A9&"|"&I$1&"|Output"),"I/O","IN"),IF(COUNTIF(Flows!$M$2:$M$1500,$A9&"|"&I$1&"|Output"),"OUT","")) | ... BK9: =IF(COUNTIF(Flows!$M$2:$M$1500,$A9&"|"&BK$1&"|Input"),IF(COUNTIF(Flows!$M$2:$M$1500,$A9&"|"&BK$1&"|Output"),"I/O","IN"),IF(COUNTIF(Flows!$M$2:$M$1500,$A9&"|"&BK$1&"|Output"),"OUT",""))
A10: =Systems!B10 -> Camp 365 Off-Grid Camper | B10: =IF(COUNTIF(Flows!$M$2:$M$1500,$A10&"|"&B$1&"|Input"),IF(COUNTIF(Flows!$M$2:$M$1500,$A10&"|"&B$1&"|Output"),"I/O","IN"),IF(COUNTIF(Flows!$M$2:$M$1500,$A10&"|"&B$1&"|Output"),"OUT","")) | C10: =IF(COUNTIF(Flows!$M$2:$M$1500,$A10&"|"&C$1&"|Input"),IF(COUNTIF(Flows!$M$2:$M$1500,$A10&"|"&C$1&"|Output"),"I/O","IN"),IF(COUNTIF(Flows!$M$2:$M$1500,$A10&"|"&C$1&"|Output"),"OUT","")) | D10: =IF(COUNTIF(Flows!$M$2:$M$1500,$A10&"|"&D$1&"|Input"),IF(COUNTIF(Flows!$M$2:$M$1500,$A10&"|"&D$1&"|Output"),"I/O","IN"),IF(COUNTIF(Flows!$M$2:$M$1500,$A10&"|"&D$1&"|Output"),"OUT","")) | E10: =IF(COUNTIF(Flows!$M$2:$M$1500,$A10&"|"&E$1&"|Input"),IF(COUNTIF(Flows!$M$2:$M$1500,$A10&"|"&E$1&"|Output"),"I/O","IN"),IF(COUNTIF(Flows!$M$2:$M$1500,$A10&"|"&E$1&"|Output"),"OUT","")) | F10: =IF(COUNTIF(Flows!$M$2:$M$1500,$A10&"|"&F$1&"|Input"),IF(COUNTIF(Flows!$M$2:$M$1500,$A10&"|"&F$1&"|Output"),"I/O","IN"),IF(COUNTIF(Flows!$M$2:$M$1500,$A10&"|"&F$1&"|Output"),"OUT","")) | G10: =IF(COUNTIF(Flows!$M$2:$M$1500,$A10&"|"&G$1&"|Input"),IF(COUNTIF(Flows!$M$2:$M$1500,$A10&"|"&G$1&"|Output"),"I/O","IN"),IF(COUNTIF(Flows!$M$2:$M$1500,$A10&"|"&G$1&"|Output"),"OUT","")) | H10: =IF(COUNTIF(Flows!$M$2:$M$1500,$A10&"|"&H$1&"|Input"),IF(COUNTIF(Flows!$M$2:$M$1500,$A10&"|"&H$1&"|Output"),"I/O","IN"),IF(COUNTIF(Flows!$M$2:$M$1500,$A10&"|"&H$1&"|Output"),"OUT","")) | I10: =IF(COUNTIF(Flows!$M$2:$M$1500,$A10&"|"&I$1&"|Input"),IF(COUNTIF(Flows!$M$2:$M$1500,$A10&"|"&I$1&"|Output"),"I/O","IN"),IF(COUNTIF(Flows!$M$2:$M$1500,$A10&"|"&I$1&"|Output"),"OUT","")) | ... BK10: =IF(COUNTIF(Flows!$M$2:$M$1500,$A10&"|"&BK$1&"|Input"),IF(COUNTIF(Flows!$M$2:$M$1500,$A10&"|"&BK$1&"|Output"),"I/O","IN"),IF(COUNTIF(Flows!$M$2:$M$1500,$A10&"|"&BK$1&"|Output"),"OUT",""))
A11: =Systems!B11 -> Camper Van | B11: =IF(COUNTIF(Flows!$M$2:$M$1500,$A11&"|"&B$1&"|Input"),IF(COUNTIF(Flows!$M$2:$M$1500,$A11&"|"&B$1&"|Output"),"I/O","IN"),IF(COUNTIF(Flows!$M$2:$M$1500,$A11&"|"&B$1&"|Output"),"OUT","")) | C11: =IF(COUNTIF(Flows!$M$2:$M$1500,$A11&"|"&C$1&"|Input"),IF(COUNTIF(Flows!$M$2:$M$1500,$A11&"|"&C$1&"|Output"),"I/O","IN"),IF(COUNTIF(Flows!$M$2:$M$1500,$A11&"|"&C$1&"|Output"),"OUT","")) | D11: =IF(COUNTIF(Flows!$M$2:$M$1500,$A11&"|"&D$1&"|Input"),IF(COUNTIF(Flows!$M$2:$M$1500,$A11&"|"&D$1&"|Output"),"I/O","IN"),IF(COUNTIF(Flows!$M$2:$M$1500,$A11&"|"&D$1&"|Output"),"OUT","")) | E11: =IF(COUNTIF(Flows!$M$2:$M$1500,$A11&"|"&E$1&"|Input"),IF(COUNTIF(Flows!$M$2:$M$1500,$A11&"|"&E$1&"|Output"),"I/O","IN"),IF(COUNTIF(Flows!$M$2:$M$1500,$A11&"|"&E$1&"|Output"),"OUT","")) | F11: =IF(COUNTIF(Flows!$M$2:$M$1500,$A11&"|"&F$1&"|Input"),IF(COUNTIF(Flows!$M$2:$M$1500,$A11&"|"&F$1&"|Output"),"I/O","IN"),IF(COUNTIF(Flows!$M$2:$M$1500,$A11&"|"&F$1&"|Output"),"OUT","")) | G11: =IF(COUNTIF(Flows!$M$2:$M$1500,$A11&"|"&G$1&"|Input"),IF(COUNTIF(Flows!$M$2:$M$1500,$A11&"|"&G$1&"|Output"),"I/O","IN"),IF(COUNTIF(Flows!$M$2:$M$1500,$A11&"|"&G$1&"|Output"),"OUT","")) | H11: =IF(COUNTIF(Flows!$M$2:$M$1500,$A11&"|"&H$1&"|Input"),IF(COUNTIF(Flows!$M$2:$M$1500,$A11&"|"&H$1&"|Output"),"I/O","IN"),IF(COUNTIF(Flows!$M$2:$M$1500,$A11&"|"&H$1&"|Output"),"OUT","")) | I11: =IF(COUNTIF(Flows!$M$2:$M$1500,$A11&"|"&I$1&"|Input"),IF(COUNTIF(Flows!$M$2:$M$1500,$A11&"|"&I$1&"|Output"),"I/O","IN"),IF(COUNTIF(Flows!$M$2:$M$1500,$A11&"|"&I$1&"|Output"),"OUT","")) | ... BK11: =IF(COUNTIF(Flows!$M$2:$M$1500,$A11&"|"&BK$1&"|Input"),IF(COUNTIF(Flows!$M$2:$M$1500,$A11&"|"&BK$1&"|Output"),"I/O","IN"),IF(COUNTIF(Flows!$M$2:$M$1500,$A11&"|"&BK$1&"|Output"),"OUT",""))
A12: =Systems!B12 -> Green Biomass | B12: =IF(COUNTIF(Flows!$M$2:$M$1500,$A12&"|"&B$1&"|Input"),IF(COUNTIF(Flows!$M$2:$M$1500,$A12&"|"&B$1&"|Output"),"I/O","IN"),IF(COUNTIF(Flows!$M$2:$M$1500,$A12&"|"&B$1&"|Output"),"OUT","")) -> IN | C12: =IF(COUNTIF(Flows!$M$2:$M$1500,$A12&"|"&C$1&"|Input"),IF(COUNTIF(Flows!$M$2:$M$1500,$A12&"|"&C$1&"|Output"),"I/O","IN"),IF(COUNTIF(Flows!$M$2:$M$1500,$A12&"|"&C$1&"|Output"),"OUT","")) | D12: =IF(COUNTIF(Flows!$M$2:$M$1500,$A12&"|"&D$1&"|Input"),IF(COUNTIF(Flows!$M$2:$M$1500,$A12&"|"&D$1&"|Output"),"I/O","IN"),IF(COUNTIF(Flows!$M$2:$M$1500,$A12&"|"&D$1&"|Output"),"OUT","")) | E12: =IF(COUNTIF(Flows!$M$2:$M$1500,$A12&"|"&E$1&"|Input"),IF(COUNTIF(Flows!$M$2:$M$1500,$A12&"|"&E$1&"|Output"),"I/O","IN"),IF(COUNTIF(Flows!$M$2:$M$1500,$A12&"|"&E$1&"|Output"),"OUT","")) | F12: =IF(COUNTIF(Flows!$M$2:$M$1500,$A12&"|"&F$1&"|Input"),IF(COUNTIF(Flows!$M$2:$M$1500,$A12&"|"&F$1&"|Output"),"I/O","IN"),IF(COUNTIF(Flows!$M$2:$M$1500,$A12&"|"&F$1&"|Output"),"OUT","")) | G12: =IF(COUNTIF(Flows!$M$2:$M$1500,$A12&"|"&G$1&"|Input"),IF(COUNTIF(Flows!$M$2:$M$1500,$A12&"|"&G$1&"|Output"),"I/O","IN"),IF(COUNTIF(Flows!$M$2:$M$1500,$A12&"|"&G$1&"|Output"),"OUT","")) | H12: =IF(COUNTIF(Flows!$M$2:$M$1500,$A12&"|"&H$1&"|Input"),IF(COUNTIF(Flows!$M$2:$M$1500,$A12&"|"&H$1&"|Output"),"I/O","IN"),IF(COUNTIF(Flows!$M$2:$M$1500,$A12&"|"&H$1&"|Output"),"OUT","")) | I12: =IF(COUNTIF(Flows!$M$2:$M$1500,$A12&"|"&I$1&"|Input"),IF(COUNTIF(Flows!$M$2:$M$1500,$A12&"|"&I$1&"|Output"),"I/O","IN"),IF(COUNTIF(Flows!$M$2:$M$1500,$A12&"|"&I$1&"|Output"),"OUT","")) | ... BK12: =IF(COUNTIF(Flows!$M$2:$M$1500,$A12&"|"&BK$1&"|Input"),IF(COUNTIF(Flows!$M$2:$M$1500,$A12&"|"&BK$1&"|Output"),"I/O","IN"),IF(COUNTIF(Flows!$M$2:$M$1500,$A12&"|"&BK$1&"|Output"),"OUT",""))
A13: =Systems!B13 -> Woody Biomass | B13: =IF(COUNTIF(Flows!$M$2:$M$1500,$A13&"|"&B$1&"|Input"),IF(COUNTIF(Flows!$M$2:$M$1500,$A13&"|"&B$1&"|Output"),"I/O","IN"),IF(COUNTIF(Flows!$M$2:$M$1500,$A13&"|"&B$1&"|Output"),"OUT","")) | C13: =IF(COUNTIF(Flows!$M$2:$M$1500,$A13&"|"&C$1&"|Input"),IF(COUNTIF(Flows!$M$2:$M$1500,$A13&"|"&C$1&"|Output"),"I/O","IN"),IF(COUNTIF(Flows!$M$2:$M$1500,$A13&"|"&C$1&"|Output"),"OUT","")) | D13: =IF(COUNTIF(Flows!$M$2:$M$1500,$A13&"|"&D$1&"|Input"),IF(COUNTIF(Flows!$M$2:$M$1500,$A13&"|"&D$1&"|Output"),"I/O","IN"),IF(COUNTIF(Flows!$M$2:$M$1500,$A13&"|"&D$1&"|Output"),"OUT","")) | E13: =IF(COUNTIF(Flows!$M$2:$M$1500,$A13&"|"&E$1&"|Input"),IF(COUNTIF(Flows!$M$2:$M$1500,$A13&"|"&E$1&"|Output"),"I/O","IN"),IF(COUNTIF(Flows!$M$2:$M$1500,$A13&"|"&E$1&"|Output"),"OUT","")) | F13: =IF(COUNTIF(Flows!$M$2:$M$1500,$A13&"|"&F$1&"|Input"),IF(COUNTIF(Flows!$M$2:$M$1500,$A13&"|"&F$1&"|Output"),"I/O","IN"),IF(COUNTIF(Flows!$M$2:$M$1500,$A13&"|"&F$1&"|Output"),"OUT","")) | G13: =IF(COUNTIF(Flows!$M$2:$M$1500,$A13&"|"&G$1&"|Input"),IF(COUNTIF(Flows!$M$2:$M$1500,$A13&"|"&G$1&"|Output"),"I/O","IN"),IF(COUNTIF(Flows!$M$2:$M$1500,$A13&"|"&G$1&"|Output"),"OUT","")) | H13: =IF(COUNTIF(Flows!$M$2:$M$1500,$A13&"|"&H$1&"|Input"),IF(COUNTIF(Flows!$M$2:$M$1500,$A13&"|"&H$1&"|Output"),"I/O","IN"),IF(COUNTIF(Flows!$M$2:$M$1500,$A13&"|"&H$1&"|Output"),"OUT","")) | I13: =IF(COUNTIF(Flows!$M$2:$M$1500,$A13&"|"&I$1&"|Input"),IF(COUNTIF(Flows!$M$2:$M$1500,$A13&"|"&I$1&"|Output"),"I/O","IN"),IF(COUNTIF(Flows!$M$2:$M$1500,$A13&"|"&I$1&"|Output"),"OUT","")) | ... BK13: =IF(COUNTIF(Flows!$M$2:$M$1500,$A13&"|"&BK$1&"|Input"),IF(COUNTIF(Flows!$M$2:$M$1500,$A13&"|"&BK$1&"|Output"),"I/O","IN"),IF(COUNTIF(Flows!$M$2:$M$1500,$A13&"|"&BK$1&"|Output"),"OUT",""))
